Workbook

Sheet 样品编号表
A1: 样品编号表 | S1: 胚布信息 | W1: 现货信息
A2: 序列号 | B2: *创建日期 Creative Date | C2: *业务员 Owner | D2: 客户 | E2: 项目当日编号 | F2: 材料名称 Name | G2: 布种类型 | H2: *布种编号 #Base | I2: 成份（中文) Composition | J2: *成份（英文） Composition | K2: *可裁门幅 Width | L2: *克重GSM | M2: *SPECIFICATION/规格 （经纱支x纬纱支） | N2: *SPECIFICATION/密度 （经密度x纬密度） | O2: 全部加工工艺（中文） Processes | P2: *全部加工工艺（英文） Processes | Q2: 备注（纱，组织，染整及功能特殊要求，指标等） Remark special yarn, weave, process, function,etc | R2: *塑胶类 厚度mm | S2: *胚布厂 Greige mill | T2: *胚布厂胚布编码 Greige #article | U2: *胚布采购价格RMB/M | W2: *一级供应商/mill | X2: *供应商编码/ #article | Y2: *二级供应商/mill | Z2: *供应商编码/ #article | AA2: *现货采购价格RMB/M | AB2: 报价日期 Date 年/月/日 | AC2: YDGE MOQ/Bulk MOQ 成品码样MOQ/成品大货MOQ | AD2: YDGE L/T/Bulk L/T 成品码样货期/成品大货货期 | AE2: YDGE Surcharge/Bulk Surcharge 成品码样费用/成品大货费用 | AF2: Stock available 成品是否有库存 | AG2: 小类别 | AH2: 备注 | AI2: 提供人员 | AJ2: 布料存放位置 | AK2: 数量 | AL2: 存放人员 | AM2: 是否已拍照
A3: 1 | B3: 45765 | C3: 陈炎林 | D3: GFG | E3: D18-1 | F3: 尚源纺织色卡或者类似 | H3: SC25001 | I3: 100%棉 | J3: 100%BCI COTTON | K3: 125 | O3: 染定 | P3: P/D | W3: 欧纺时尚 | X3: K321 | Y3: 尚源 | Z3: K321 | AG3: 小块样布 | AM3: 是
A4: 2 | B4: 45765 | C4: 陈炎林 | D4: GFG | F4: 新丰花边 | H4: SC25001-1 | I4: 100%棉 | J4: 100%BCI COTTON | K4: 125 | W4: 欧纺时尚 | X4: 花边 | Y4: 新丰花边 | Z4: 花边 | AG4: 小块样布 | AM4: 是
A5: 3 | B5: 45765 | C5: 陈炎林 | D5: GFG | F5: A-ONE | H5: SC25001-2 | I5: 100%棉 | J5: 100%BCI COTTON | K5: 125 | W5: 欧纺时尚 | X5: A-ONE | Y5: 欧纺时尚 | Z5: A-ONE | AG5: 小块样布 | AM5: 是
A6: 4 | B6: 45765 | C6: 陈炎林 | D6: GFG | F6: K321 | H6: SC25001-3 | I6: 100%棉 | J6: 100%BCI COTTON | K6: 125 | W6: 欧纺时尚 | X6: K321 | Y6: 欧纺时尚 | Z6: K321 | AA6: 13.2 | AB6: 45764 | AG6: 小块样布 | AM6: 是
A7: 5 | B7: 45765 | C7: 陈炎林 | D7: GFG | F7: 永成花边行李佩莲13424008907/许晓程13570899693 | H7: SC25001-4 | I7: 100%棉 | J7: 100%BCI COTTON | K7: 125 | W7: 欧纺时尚 | X7: 花边 | Y7: 永成花边行 | Z7: 花边 | AG7: 小块样布 | AM7: 是
A8: 6 | B8: 45765 | C8: 陈炎林 | D8: GFG | E8: D18-3 | F8: 花边1.5-2厘米有圈圈或格子 | H8: SC25002 | I8: 100%棉 | J8: 100%BCI COTTON | K8: 125 | O8: 染定 | P8: P/D | W8: 欧纺时尚 | X8: 1.5-2厘米圈圈或格子 | Y8: 欧纺时尚 | Z8: 1.5-2厘米圈圈或格子 | AG8: 小块样布 | AM8: 是
A9: 7 | B9: 45766 | C9: 陈炎林 | D9: GFG | F9: 瑞康3 楼C032 花边 | H9: SC25003 | I9: 100%棉 | J9: 100%BCI COTTON | K9: 125 | O9: 染定 | P9: P/D | W9: 欧纺时尚 | X9: 瑞康3 楼C032 花边 | Y9: 欧纺时尚 | Z9: 瑞康3 楼C032 花边 | AA9: 14.2 | AB9: 45766 | AG9: 小块样布 | AM9: 是
A10: 8 | B10: 45766 | C10: 陈炎林 | D10: GFG | F10: 刺绣/绣花 | H10: SC25004 | I10: 100%棉 | J10: 100%BCI COTTON | K10: 125 | O10: 染定 | P10: P/D | W10: 欧纺时尚 | X10: 刺绣/绣花 | Y10: 欧纺时尚 | Z10: 刺绣/绣花 | AG10: 小块样布 | AM10: 是
A11: 9 | B11: 45766 | C11: 陈炎林 | D11: GFG | F11: 刺绣/绣花-鑫隆8字花 | H11: SC25004-1 | I11: 100%棉 | J11: 100%BCI COTTON | K11: 125 | W11: 欧纺时尚 | X11: 8字花 | Y11: 鑫隆 | Z11: 8字花 | AG11: 小块样布 | AM11: 是
A12: 10 | B12: 45766 | C12: 陈炎林 | D12: GFG | F12: 刺绣/绣花-鑫隆578 | H12: SC25004-2 | I12: 100%棉 | J12: 100%BCI COTTON | K12: 125 | W12: 欧纺时尚 | X12: 578 | Y12: 鑫隆 | Z12: 578 | AG12: 小块样布 | AM12: 是
A13: 11 | B13: 45766 | C13: 陈炎林 | D13: GFG | F13: 刺绣/绣花-鑫隆A9065 | H13: SC25004-3 | I13: 100%棉 | J13: 100%BCI COTTON | K13: 125 | W13: 欧纺时尚 | X13: A9065 | Y13: 鑫隆 | Z13: A9065 | AG13: 小块样布 | AM13: 是
A14: 12 | B14: 45766 | C14: 陈炎林 | D14: GFG | F14: 刺绣/绣花-鑫隆双层太阳 | H14: SC25004-4 | I14: 100%棉 | J14: 100%BCI COTTON | K14: 125 | W14: 欧纺时尚 | X14: 双层太阳 | Y14: 鑫隆 | Z14: 双层太阳 | AG14: 小块样布 | AM14: 是
A15: 13 | B15: 45766 | C15: 陈炎林 | D15: GFG | F15: 刺绣/绣花-鑫隆C-5 | H15: SC25004-5 | I15: 100%棉 | J15: 100%BCI COTTON | K15: 125 | W15: 欧纺时尚 | X15: C-5 | Y15: 鑫隆 | Z15: C-5 | AG15: 小块样布 | AM15: 是
A16: 14 | B16: 45766 | C16: 陈炎林 | D16: GFG | F16: 刺绣/绣花-鑫隆C-1 | H16: SC25004-6 | I16: 100%棉 | J16: 100%BCI COTTON | K16: 125 | W16: 欧纺时尚 | X16: C-1 | Y16: 鑫隆 | Z16: C-1 | AG16: 小块样布 | AM16: 是
A17: 15 | B17: 45766 | C17: 陈炎林 | D17: GFG | F17: 永成花边行李佩莲13424008907/许晓程13570899693 | H17: SC25004-7 | I17: 100%棉 | J17: 100%BCI COTTON | K17: 125 | W17: 欧纺时尚 | Y17: 永成花边行李佩莲13424008907/许晓程13570899693 | AG17: 小块样布 | AM17: 是
A18: 16 | B18: 45769 | C18: 陈炎林 | D18: 永叙 | E18: D19-1 | F18: 67165 | H18: SC25005 | I18: 95%棉 5%氨纶 | J18: 95%COTTON 5%SP | K18: 140 | L18: 210 | O18: 染定 | P18: P/D | W18: 欧纺时尚 | X18: 67165 | Y18: 文涛布业 | Z18: 67165 | AA18: 18.8 | AB18: 45766 | AG18: 色卡
A19: 17 | B19: 45769 | C19: 陈炎林 | D19: 永叙 | E19: D19-1 | F19: 41112精棉 | H19: SC25006 | I19: 95%棉 5%氨纶 | J19: 95%COTTON 5%SP | K19: 175 | L19: 180 | O19: 染定 | P19: P/D | W19: 欧纺时尚 | X19: 41112 | Y19: 文涛布业 | Z19: 41112精棉 | AA19: 19.6 | AB19: 45766 | AG19: 色卡
A20: 18 | B20: 45769 | C20: 陈炎林 | D20: 永叙 | E20: D19-1 | F20: 3C1005-精棉拉架 | H20: SC25007 | I20: 95%棉 5%氨纶 | J20: 95%COTTON 5%SP | K20: 175 | L20: 180 | O20: 染定 | P20: P/D | W20: 欧纺时尚 | X20: 3C1005 | Y20: 恒信布业 | Z20: 3C1005 | AA20: 15 | AB20: 45766 | AG20: 色卡
A21: 19 | B21: 45769 | C21: 陈炎林 | D21: 永叙 | E21: D19-1 | F21: 3S1203-32支精棉双纱 | H21: SC25008 | I21: 100%棉 | J21: 100%COTTON | K21: 185 | L21: 230 | O21: 染定 | P21: P/D | W21: 欧纺时尚 | X21: 3S1203 | Y21: 恒信布业 | Z21: 3S1203 | AA21: 23.3 | AB21: 45766 | AG21: 色卡
A22: 20 | B22: 45769 | C22: 陈炎林 | D22: 永叙 | E22: D19-1 | F22: 12339#-优棉罗纹 | H22: SC25009 | I22: 95%棉 5%氨纶 | J22: 95%COTTON 5%SP | K22: 145 | L22: 220 | O22: 染定 | P22: P/D | W22: 欧纺时尚 | X22: 12339 | Y22: 锦盛纺织 | Z22: 12339# | AA22: 16.2 | AB22: 45766 | AG22: 色卡
A23: 21 | B23: 45769 | C23: 陈炎林 | D23: 永叙 | E23: D19-1 | F23: 12005#-摩登潮棉 | H23: SC25010 | I23: 100%棉 | J23: 100%COTTON | K23: 185 | L23: 200 | O23: 染定 | P23: P/D | W23: 欧纺时尚 | X23: 12005 | Y23: 锦盛纺织 | Z23: 12005# | AA23: 22 | AB23: 45766 | AG23: 色卡
A24: 22 | B24: 45769 | C24: 陈炎林 | D24: 永叙 | E24: D19-1 | F24: 2031-纯棉满天星网布 | H24: SC25011 | I24: 100%棉 | J24: 100%COTTON | K24: 190 | L24: 130 | O24: 染定 | P24: P/D | W24: 欧纺时尚 | X24: 2031 | Y24: 华联 | Z24: 2031 | AA24: 18 | AB24: 45766 | AG24: 色卡
A25: 23 | B25: 45769 | C25: 陈炎林 | D25: 永叙 | E25: D19-1 | F25: S450 | H25: SC25012 | I25: 100%棉 | J25: 100%COTTON | K25: 145 | O25: 染定 | P25: P/D | W25: 欧纺时尚 | X25: S450 | Y25: 盛业纺织 | Z25: S450 | AA25: 12.7 | AB25: 45766 | AG25: 色卡
A26: 24 | B26: 45773 | C26: 陈炎林 | D26: GFG | F26: 2C1505-21支精棉平纹 | H26: SC25013 | I26: 100%棉 | J26: 100%BCI COTTON | K26: 180 | L26: 180 | O26: 染定 | P26: P/D | W26: 欧纺时尚 | X26: 2C1505 | Y26: 星海 | Z26: 2C1505 | AA26: 17.2 | AB26: 45773 | AG26: 色卡
A27: 25 | B27: 45773 | C27: 陈炎林 | D27: GFG | F27: 3C1505-32支棉平纹拉架 | H27: SC25014 | I27: 95%棉5%氨纶 | J27: 95%BCI COTTON 5%SP | K27: 175 | L27: 180 | O27: 染定 | P27: P/D | W27: 欧纺时尚 | X27: 3C1505 | Y27: 星海 | Z27: 3C1505 | AA27: 13.5 | AB27: 45773 | AG27: 色卡
A28: 26 | B28: 45773 | C28: 陈炎林 | D28: GFG | F28: RM3010-欧丽棉 | H28: SC25015 | I28: 100%棉 | J28: 100%BCI COTTON | K28: 175 | L28: 180 | O28: 染定 | P28: P/D | W28: 欧纺时尚 | X28: RM3010 | Y28: 星海 | Z28: RM3010 | AA28: 13.5 | AB28: 45773 | AG28: 色卡
A29: 27 | B29: 45773 | C29: 陈炎林 | D29: GFG | F29: 2615#-精棉拉架 | H29: SC25016 | I29: 100%棉 | J29: 100%BCI COTTON | K29: 175 | L29: 180 | O29: 染定 | P29: P/D | W29: 欧纺时尚 | X29: 2615# | Y29: 伊彩儿 | Z29: 2615# | AA29: 15.7 | AB29: 45773 | AG29: 色卡
A30: 28 | B30: 45773 | C30: 陈炎林 | D30: GFG | F30: 2619#-纯棉拉架 | H30: SC25017 | I30: 100%棉 | J30: 100%BCI COTTON | K30: 175 | L30: 170 | O30: 染定 | P30: P/D | W30: 欧纺时尚 | X30: 2619# | Y30: 伊彩儿 | Z30: 2619# | AA30: 14.8 | AB30: 45773 | AG30: 色卡
A31: 29 | B31: 45773 | C31: 陈炎林 | D31: GFG | F31: D14454#-32S彩间 | H31: SC25018 | I31: 100%棉 | J31: 100%BCI COTTON | K31: 175 | L31: 180 | O31: 染定 | P31: P/D | W31: 欧纺时尚 | X31: D14454# | Y31: 布布昇 | Z31: D14454# | AA31: 18.1 | AB31: 45773 | AG31: 色卡
A32: 30 | B32: 45773 | C32: 陈炎林 | D32: GFG | F32: 52049#-棉纺系列 | H32: SC25019 | I32: 100%棉 | J32: 100%BCI COTTON | K32: 180 | L32: 190 | O32: 染定 | P32: P/D | W32: 欧纺时尚 | X32: 52049# | Y32: 盛氏布行 | Z32: 52049# | AB32: 45773 | AG32: 色卡
A33: 31 | B33: 45775 | C33: 陈炎林 | D33: GFG | E33: D24-3 | F33: B-0171 | H33: SC25020 | I33: 100%棉 | J33: 100%BCI COTTON | K33: 125 | O33: 染定 | P33: P/D | W33: 欧纺时尚 | X33: B-0171 | Y33: 真成纺织 | Z33: B-0171 | AA33: 15.7 | AB33: 45775 | AG33: 一个循环条
A34: 32 | B34: 45775 | C34: 陈炎林 | D34: GFG | E34: D24-3 | F34: B-029 | H34: SC25020-1 | I34: 100%棉 | J34: 100%BCI COTTON | K34: 125 | O34: 染定 | P34: P/D | W34: 欧纺时尚 | X34: B-029 | Y34: 真成纺织 | Z34: B-029 | AA34: 15.7 | AB34: 45775 | AG34: 一个循环条
A35: 33 | B35: 45775 | C35: 陈炎林 | D35: GFG | E35: D24-3 | F35: A2164 | H35: SC25020-10 | I35: 100%棉 | J35: 100%BCI COTTON | K35: 125 | O35: 染定 | P35: P/D | W35: 欧纺时尚 | X35: A2164 | Y35: 金绣 | Z35: A2164 | AA35: 14.8 | AB35: 45775 | AG35: 一个循环条
A36: 34 | B36: 45775 | C36: 陈炎林 | D36: GFG | E36: D24-3 | F36: A2207 | H36: SC25020-11 | I36: 100%棉 | J36: 100%BCI COTTON | K36: 125 | O36: 染定 | P36: P/D | W36: 欧纺时尚 | X36: A2207 | Y36: 金绣 | Z36: A2207 | AA36: 14.8 | AB36: 45775 | AG36: 一个循环条
A37: 35 | B37: 45775 | C37: 陈炎林 | D37: GFG | E37: D24-3 | F37: A2471 | H37: SC25020-12 | I37: 100%棉 | J37: 100%BCI COTTON | K37: 125 | O37: 染定 | P37: P/D | W37: 欧纺时尚 | X37: A2471 | Y37: 金绣 | Z37: A2471 | AA37: 16.2 | AB37: 45775 | AG37: 一个循环条
A38: 36 | B38: 45775 | C38: 陈炎林 | D38: GFG | E38: D24-3 | F38: A2376 | H38: SC25020-13 | I38: 100%棉 | J38: 100%BCI COTTON | K38: 125 | O38: 染定 | P38: P/D | W38: 欧纺时尚 | X38: A2376 | Y38: 金绣 | Z38: A2376 | AA38: 18.4 | AB38: 45775 | AG38: 一个循环条
A39: 37 | B39: 45775 | C39: 陈炎林 | D39: GFG | E39: D24-3 | F39: A2185 | H39: SC25020-14 | I39: 100%棉 | J39: 100%BCI COTTON | K39: 125 | O39: 染定 | P39: P/D | W39: 欧纺时尚 | X39: A2185 | Y39: 金绣 | Z39: A2185 | AA39: 14.6 | AB39: 45775 | AG39: 一个循环条
A40: 38 | B40: 45775 | C40: 陈炎林 | D40: GFG | E40: D24-3 | F40: F571 | H40: SC25020-15 | I40: 100%棉 | J40: 100%BCI COTTON | K40: 125 | O40: 染定 | P40: P/D | W40: 欧纺时尚 | X40: F571 | Y40: 新发布行 | Z40: F571 | AA40: 14 | AB40: 45775 | AG40: 一个循环条
A41: 39 | B41: 45775 | C41: 陈炎林 | D41: GFG | E41: D24-3 | F41: C-5 | H41: SC25020-16 | I41: 100%棉 | J41: 100%BCI COTTON | K41: 125 | O41: 染定 | P41: P/D | W41: 欧纺时尚 | X41: C-5 | Y41: 新发布行 | Z41: C-5 | AA41: 14 | AB41: 45775 | AG41: 一个循环条
A42: 40 | B42: 45775 | C42: 陈炎林 | D42: GFG | E42: D24-3 | F42: 元宝 | H42: SC25020-17 | I42: 100%棉 | J42: 100%BCI COTTON | K42: 125 | O42: 染定 | P42: P/D | W42: 欧纺时尚 | X42: 元宝 | Y42: 新发布行 | Z42: 元宝 | AA42: 14 | AB42: 45775 | AG42: 一个循环条
A43: 41 | B43: 45775 | C43: 陈炎林 | D43: GFG | E43: D24-3 | F43: 定位打孔 | H43: SC25020-18 | I43: 100%棉 | J43: 100%BCI COTTON | K43: 125 | O43: 染定 | P43: P/D | W43: 欧纺时尚 | X43: 定位打孔 | Y43: 新发布行 | Z43: 定位打孔 | AA43: 14 | AB43: 45775 | AG43: 一个循环条
A44: 42 | B44: 45775 | C44: 陈炎林 | D44: GFG | E44: D24-3 | F44: B-894 | H44: SC25020-2 | I44: 100%棉 | J44: 100%BCI COTTON | K44: 125 | O44: 染定 | P44: P/D | W44: 欧纺时尚 | X44: B-894 | Y44: 真成纺织 | Z44: B-894 | AA44: 16.5 | AB44: 45775 | AG44: 一个循环条
... A51: 49 | B51: 45775 | C51: 陈炎林 | D51: GFG | E51: D24-3 | F51: A2046 | H51: SC25020-9 | I51: 100%棉 | J51: 100%BCI COTTON | K51: 125 | O51: 染定 | P51: P/D | W51: 欧纺时尚 | X51: A2046 | Y51: 金绣 | Z51: A2046 | AA51: 14.8 | AB51: 45775 | AG51: 一个循环条
A52: 50 | B52: 45791 | C52: 陈炎林 | D52: GFG | F52: 40支全面皱 | H52: SC25021 | I52: 100%棉 | J52: 100%BCI COTTON | K52: 125 | L52: 86 | W52: 欧纺时尚 | X52: 40支全面皱 | Y52: 宇成纺织 | Z52: 40支全面皱 | AA52: 12.3 | AB52: 45791
A53: 51 | B53: 45799 | C53: 陈晓彬 | D53: GFG | F53: 686#（金丝棉） | H53: SC25022 | I53: 80%涤纶20%棉 | J53: 20%COTTON 80%POLY | K53: 150 | L53: 100 | W53: 欧纺时尚 | X53: 686#（金丝棉） | Y53: 欧纺时尚 | Z53: 686#（金丝棉） | AA53: 6.8 | AB53: 45799
A54: 52 | B54: 45799 | C54: 陈晓彬 | D54: GFG | F54: 110*110 60支仿天丝 | H54: SC25023 | I54: 100%棉 | J54: 100%BCI COTTON | K54: 150 | L54: 90 | W54: 欧纺时尚 | X54: 110*110 60支仿天丝 | Y54: 粤东纺织 | Z54: 110*110 60支仿天丝
A55: 53 | B55: 45799 | C55: 陈晓彬 | D55: GFG | F55: 9088 半工艺 | H55: SC25024 | I55: 100%棉 | J55: 100%BCI COTTON | K55: 150 | L55: 55 | W55: 欧纺时尚 | X55: 9088 半工艺 | Y55: 样样红纺织 | Z55: 9088 半工艺
A56: 54 | B56: 45803 | C56: 陈晓彬 | D56: SOLTO | H56: SC25025 | I56: 100%棉 | J56: 100%COTTON | M56: 10S*10S | Q56: 远东纱线，全环保 | S56: 世贸 | W56: 远东 | X56: 全环保 | Y56: 远东 | Z56: 全环保
A57: 55 | B57: 45803 | C57: 陈晓彬 | D57: SOLTO | H57: SC25026 | I57: 100%棉 | J57: 100%COTTON | M57: 10S*10S | Q57: 远东纱线，经向环保，纬向非环保 | S57: 世贸 | W57: 远东 | X57: 经向环保，纬向非环保 | Y57: 远东 | Z57: 经向环保，纬向非环保
A58: 56 | B58: 45803 | C58: 陈晓彬 | D58: SOLTO | H58: SC25027 | I58: 100%棉 | J58: 100%COTTON | M58: 10S/2*10S/2 | Q58: 远东纱线，全环保 | S58: 世贸 | W58: 远东 | X58: 全环保 | Y58: 远东 | Z58: 全环保
A59: 57 | B59: 45803 | C59: 陈晓彬 | D59: SOLTO | H59: SC25028 | I59: 100%棉 | J59: 100%COTTON | M59: 10S/2*10S/2 | Q59: 远东纱线，经向环保，纬向非环保 | S59: 世贸 | W59: 远东 | X59: 经向环保，纬向非环保 | Y59: 远东 | Z59: 经向环保，纬向非环保
A60: 58 | B60: 45803 | C60: 陈炎林 | D60: GFG | F60: 5668精品2*2罗纹 | H60: SC25029 | I60: 95%棉5%氨纶 | J60: 95%BCI COTTON 5%SP | K60: 135 | L60: 210 | W60: 欧纺时尚 | X60: 5668精品2*2罗纹 | Y60: 三联纺织 | Z60: 5668精品2*2罗纹 | AA60: 23.5 | AB60: 45803
A61: 59 | B61: 45803 | C61: 陈炎林 | D61: GFG | F61: D232 | H61: SC25030 | I61: 97%棉3%氨纶 | J61: 97%BCI COTTON 3%SP | K61: 185 | L61: 210 | W61: 欧纺时尚 | X61: D232 | Y61: 德生布业 | Z61: D232 | AA61: 26.5 | AB61: 45803
A62: 60 | B62: 45803 | C62: 陈炎林 | D62: GFG | F62: 0377 | H62: SC25031 | I62: 95%棉5%氨纶 | J62: 95%BCI COTTON 5%SP | K62: 190 | L62: 240 | W62: 欧纺时尚 | X62: 0377 | Y62: 德生布业 | Z62: 0377 | AA62: 27.5 | AB62: 45804
A63: 61 | B63: 45803 | C63: 陈炎林 | D63: GFG | F63: 2092 | H63: SC25032 | I63: 100%棉 | J63: 100%BCI COTTON | K63: 170 | L63: 180 | W63: 欧纺时尚 | X63: 2092 | Y63: 德生布业 | Z63: 2092 | AA63: 19.5 | AB63: 45804
A64: 62 | C64: 陈晓彬 | D64: 样板房 | H64: SC25033 | I64: 100%棉 | J64: 100%COTTON | K64: 150 | L64: 109 | W64: 欧纺时尚 | X64: 25283(匹马棉） | Y64: 栢利 | Z64: 25283(匹马棉） | AA64: 34 | AB64: 46043 | AG64: 雪纺 | AJ64: 2-3
A65: 63 | B65: 45804 | C65: 陈炎林 | D65: GFG | F65: 2093 | H65: SC25034 | I65: 95%棉5%氨纶 | J65: 95%BCI COTTON 5%SP | K65: 145 | L65: 119 | W65: 欧纺时尚 | X65: 2093 | Y65: 德盛布行 | Z65: 2093 | AA65: 20.5 | AB65: 45804
A66: 64 | B66: 45804 | C66: 陈炎林 | D66: GFG | F66: F047 | H66: SC25035 | I66: 95%棉5%氨纶 | J66: 95%BCI COTTON 5%SP | K66: 145 | L66: 176 | W66: 欧纺时尚 | X66: F047 | Y66: 德盛布行 | Z66: F047 | AA66: 22.5 | AB66: 45804
A67: 65 | B67: 45804 | C67: 陈炎林 | D67: GFG | F67: 精棉2*2 21012 | H67: SC25036 | I67: 95%棉5%氨纶 | J67: 95%BCI COTTON 5%SP | K67: 145 | L67: 240 | W67: 欧纺时尚 | X67: 21012 | Y67: 享和 | Z67: 21012 | AA67: 19 | AB67: 45804
A68: 66 | B68: 45804 | C68: 陈炎林 | D68: GFG | F68: 精棉2*2 21004 | H68: SC25037 | I68: 95%棉5%氨纶 | J68: 95%BCI COTTON 5%SP | K68: 145 | L68: 240 | W68: 欧纺时尚 | X68: 21004 | Y68: 享和 | Z68: 21004 | AA68: 19 | AB68: 45804
A69: 67 | B69: 45804 | C69: 陈炎林 | D69: GFG | F69: 精棉2*2 212017 | H69: SC25038 | I69: 95%棉5%氨纶 | J69: 95%BCI COTTON 5%SP | K69: 145 | L69: 240 | W69: 欧纺时尚 | X69: 212017 | Y69: 享和 | Z69: 212017 | AA69: 19 | AB69: 45804
A70: 68 | C70: 陈晓彬 | D70: 样板房 | H70: SC25040 | I70: 100%棉 | J70: 100%COTTON | K70: 145 | L70: 360 | W70: 欧纺时尚 | X70: K830# | Y70: 旭阳纺织 | Z70: K830# | AA70: 29 | AB70: 46104 | AG70: 仿麻系列 | AH70: 2026/03/14寄三佰 | AJ70: 4-4
A71: 69 | C71: 陈晓彬 | D71: 样板房 | H71: SC25041 | I71: 100%棉 | J71: 100%COTTON | K71: 145 | L71: 255 | W71: 欧纺时尚 | X71: K987#鱼骨纹 | Y71: 旭阳纺织 | Z71: K987#鱼骨纹 | AA71: 25.4 | AB71: 46104 | AG71: 仿麻系列 | AH71: 2026/03/14寄三佰 | AJ71: 4-5
A72: 70 | C72: 陈晓彬 | D72: 样板房 | H72: SC25042 | I72: 100%棉 | J72: 100%COTTON | K72: 145 | W72: 欧纺时尚 | X72: K1046#重磅（可洗褪） | Y72: 旭阳纺织 | Z72: K1046#重磅（可洗褪） | AG72: 仿麻系列 | AJ72: 4-4
A73: 71 | C73: 陈晓彬 | D73: 样板房 | H73: SC25043 | I73: 100%棉 | J73: 100%COTTON | K73: 145 | L73: 240 | W73: 欧纺时尚 | X73: K907# | Y73: 旭阳纺织 | Z73: K907# | AA73: 25.5 | AB73: 45861 | AG73: 仿麻系列 | AH73: 2025/7/17 GFG设计师选中。 | AJ73: 4-4
A74: 72 | C74: 陈晓彬 | D74: 样板房 | H74: SC25044 | I74: 97%棉 3%氨纶 | J74: 97%C 3%SP | K74: 145 | L74: 220 | W74: 欧纺时尚 | X74: K786# | Y74: 旭阳纺织 | Z74: K786# | AA74: 25.4 | AB74: 46104 | AG74: 仿麻系列 | AH74: 2026/03/14寄三佰 | AJ74: 4-4
A75: 73 | C75: 陈晓彬 | D75: 样板房 | H75: SC25045 | I75: 96%棉 4%氨纶 | J75: 96%C 4%SP | K75: 135 | L75: 190 | Q75: 3.9 | W75: 欧纺时尚 | X75: 41129B | Y75: 永欣贵 | Z75: 41129B | AA75: 90 | AB75: 46104 | AG75: 针织罗纹 | AH75: 2026/03/14寄三佰 | AJ75: 6-4
A76: 74 | C76: 陈晓彬 | D76: 样板房 | H76: SC25046 | I76: 95%棉 5%氨纶 | J76: 95%C 5%SP | K76: 145 | L76: 180 | W76: 欧纺时尚 | X76: 88467 | Y76: 新艺（裕兴）纺织 | Z76: 88467 | AB76: 46104 | AG76: 针织起皱 | AH76: 2026/03/14寄三佰 | AJ76: 6-3
A77: 75 | C77: 陈晓彬 | D77: 样板房 | H77: SC25047 | I77: 96%棉 4%氨纶 | J77: 96%C 4%SP | K77: 150 | L77: 160 | W77: 欧纺时尚 | X77: 6508#皱皱布 | Y77: 优泰 | Z77: 6508#皱皱布 | AG77: 针织起皱 | AJ77: 6-3
A78: 76 | B78: 45769 | C78: 陈炎林 | D78: 永叙 | F78: HL-55000 零感云绉 | H78: SN25001 | I78: 100%尼龙 | J78: 100%NYLON | K78: 140 | O78: 染色+泼水 | P78: P/D+W/R | Q78: 采用超细旦尼龙纤维匠心织造而成，搭配先进的染整工艺，布面形成自然立体绉感，呈现不规则肌理，打破尼龙面料传统的光华质感，提升设计层次感（大牌同款面料） | W78: 思科纺 | X78: HL-55000 | Y78: 思科纺 | Z78: HL-55000 | AA78: 12(含税含运到广东福建） | AB78: 45769 | AG78: 色卡
A79: 77 | B79: 45800 | C79: 陈炎林 | D79: GFG | F79: 塔丝隆228 | H79: SN25002 | I79: 100%尼龙 | J79: 100%NYLON | K79: 150 | L79: 100 | Q79: 70D*160D | W79: 世贸纺织 | X79: 塔丝隆228 色卡一 | Y79: 汇恩布行 | Z79: E981 228T消光塔丝隆（防水） | AA79: 6.3 | AH79: 汇恩报价，对应SY252960
A80: 78 | C80: 陈晓彬 | D80: 样板房 | H80: SN25003 | I80: 93%尼龙 3%氨纶 | J80: 93%N 3%SP | K80: 145 | W80: 欧纺时尚 | X80: 640 | Y80: 彩富 | Z80: 640 | AG80: 女士梭织外套 | AJ80: 3-1
A81: 79 | C81: 陈晓彬 | D81: 样板房 | H81: SN25004 | I81: 100%尼龙 | J81: 100%N | K81: 145 | W81: 欧纺时尚 | X81: 764 | Y81: 彩富 | Z81: 764 | AG81: 雪纺 | AJ81: 1-5
A82: 80 | C82: 陈晓彬 | D82: 样板房 | H82: SN25005 | I82: 100%尼龙 | J82: 100%N | K82: 145 | W82: 欧纺时尚 | X82: 468 | Y82: 彩富 | Z82: 468 | AG82: 雪纺 | AJ82: 2-3
A83: 81 | C83: 陈晓彬 | D83: 样板房 | H83: SN25016 | I83: 40%人棉 47%涤纶 11%尼龙 2%氨纶 | J83: 40%R 47%T 11%N 2%SP | K83: 145 | W83: 欧纺时尚 | X83: A2879-6 | Y83: 沃玛 | Z83: A2879-6 | AG83: 梭织提花 | AJ83: 6-2
A84: 82 | B84: 45765 | C84: 陈炎林 | D84: GFG | F84: 6017 | H84: SP25001 | I84: 94%涤纶 6%氨纶 | J84: 94%Recycle POLY 6%SP | K84: 165 | L84: 200 | O84: 染定 | P84: P/D | W84: 欧纺时尚 | X84: 6017 | Y84: 欧纺时尚 | Z84: 6017 | AA84: 45.5 | AB84: 45764 | AG84: 色卡 | AM84: 是
A85: 83 | B85: 45765 | C85: 陈炎林 | D85: GFG | F85: F62 | H85: SP25002 | I85: 95%酷丝棉 5%SP | J85: 95%Recycle POLY 5%SP | K85: 165 | L85: 200 | O85: 染定 | P85: P/D | W85: 欧纺时尚 | X85: F62 | Y85: 欧纺时尚 | Z85: F62 | AA85: 43.2 | AB85: 45764 | AG85: 色卡 | AM85: 是
A86: 84 | B86: 45766 | C86: 陈炎林 | D86: GFG | E86: D18-2 | F86: 50D乔其纱 | H86: SP25003 | I86: 100%涤纶 | J86: 100%Recycle POLY | K86: 148 | L86: 70 | O86: 染定 | P86: P/D | W86: 欧纺时尚 | X86: 乔其纱 | Y86: 蓬发 | Z86: 乔其纱 | AA86: 9.2 | AB86: 45766 | AG86: 色卡 | AM86: 是
A87: 85 | B87: 45769 | C87: 陈炎林 | D87: 永叙 | F87: HL-30000 冬俪（幻影）格 | H87: SP25004 | I87: 100%涤纶 | J87: 100%POLY | K87: 148 | O87: 染色+泼水 | P87: P/D+鲁道夫三防 | Q87: 采用15D超细纤维匠心织造而成，搭配特殊染整工艺，面料手感细腻爽滑又不失骨感，辅以无胆防绒，拒水防油，易去污等功能，外观超迷你细格，如影似乎似幻，简约而不简单 | W87: 思科纺 | X87: HL-30000 | Y87: 思科纺 | Z87: HL-30000 | AA87: 15.8(含税含运到广东福建） | AB87: 45769 | AG87: 色卡
A88: 86 | B88: 45769 | C88: 陈炎林 | D88: 永叙 | F88: HL-66000 零感纤云 | H88: SP25005 | I88: 100%涤纶 | J88: 100%POLY | K88: 150 | O88: 染色+三防+压光 | P88: 染色+三防+压光 | Q88: 采用超细旦涤纶高F匠心织造而成，搭配先进染整工艺，实现亲肤棉柔触感的同时也赋予类似尼龙般爽滑的特性，面料极致轻薄，克重34GSM（三防+防绒亚光） | W88: 思科纺 | X88: HL-66000 | Y88: 思科纺 | Z88: HL-66000 | AA88: 15.5(含税含运到广东福建） | AB88: 45769 | AG88: 色卡
A89: 87 | B89: 45769 | C89: 陈炎林 | D89: 永叙 | F89: HL-20000 冬俪丝 | H89: SP25006 | I89: 100%涤纶 | J89: 100%POLY | K89: 148 | O89: 染色+泼水+三防+压光 | P89: P/D+三防+CIRE | Q89: 采用15D超细纤维匠心织造而成，搭配特殊染整工艺，在保留面料手感轻柔细腻以及无胆防绒的同时，还具备拒水防油，易去污等防护功能 | W89: 思科纺 | X89: HL-20000 | Y89: 思科纺 | Z89: HL-20000 | AA89: 15(含税含运到广东福建） | AB89: 45769 | AG89: 色卡
A90: 88 | B90: 45769 | C90: 陈炎林 | D90: 永叙 | F90: HL-10000 慕丝棉 | H90: SP25007 | I90: 100%涤纶 | J90: 100%POLY | K90: 148 | O90: 染色+三防+压光 | P90: 染色+三防+压光 | Q90: 采用25D超细纤维匠心织造而成，搭配特殊的染整工艺，使面料手感不仅棉柔细腻，而且抗皱回弹性良好，成衣成型度俱佳，面料具备三防和无胆防绒等功能 | W90: 思科纺 | X90: HL-10000 | Y90: 思科纺 | Z90: HL-10000 | AA90: 10.5(含税含运到广东福建） | AB90: 45769 | AG90: 色卡
A91: 89 | B91: 45769 | C91: 陈炎林 | D91: 永叙 | E91: D19-1 | F91: 119211083-250g双刷单摇-186 | H91: SP25008 | I91: 100%涤纶 | J91: 100%POLY | K91: 160 | L91: 250 | O91: 染定 | P91: P/D | W91: 欧纺时尚 | X91: 119211083 | Y91: 裕丰毛绒 | Z91: 119211083 | AA91: 13.7 | AB91: 45766 | AG91: 色卡
A92: 90 | B92: 45769 | C92: 陈炎林 | D92: 永叙 | E92: D19-1 | F92: 1172910835-加厚摇粒绒-52 | H92: SP25009 | I92: 100%涤纶 | J92: 100%POLY | K92: 160 | L92: 180 | O92: 染定 | P92: P/D | W92: 欧纺时尚 | X92: 1172910835 | Y92: 裕丰毛绒 | Z92: 1172910835 | AA92: 9.7 | AB92: 45766 | AG92: 色卡
A93: 91 | B93: 45769 | C93: 陈炎林 | D93: 永叙 | E93: D19-1 | F93: 1265251083-四面弹格子摇粒-52 | H93: SP25010 | I93: 100%涤纶 | J93: 100%POLY | K93: 172 | L93: 210 | O93: 染定 | P93: P/D | W93: 欧纺时尚 | X93: 1265251083 | Y93: 裕丰毛绒 | Z93: 1265251083 | AA93: 15.6 | AB93: 45766 | AG93: 色卡
A94: 92 | B94: 45769 | C94: 陈炎林 | D94: 永叙 | E94: D19-1 | F94: 21532-300g单面吸水珊瑚绒-66 | H94: SP25011 | I94: 100%涤纶 | J94: 100%POLY | K94: 185 | L94: 300 | O94: 染定 | P94: P/D | W94: 欧纺时尚 | X94: 21532 | Y94: 裕丰毛绒 | Z94: 21532 | AA94: 16.9 | AB94: 45766 | AG94: 色卡
A95: 93 | B95: 45769 | C95: 陈炎林 | D95: 永叙 | E95: D19-1 | F95: 9800Y2-宝宝绒 | H95: SP25012 | I95: 100%涤纶 | J95: 100%POLY | K95: 160 | O95: 染定 | P95: P/D | W95: 欧纺时尚 | X95: 9800Y2 | Y95: 江汉纺织 | Z95: 9800Y2 | AG95: 色卡
A96: 94 | B96: 45769 | C96: 陈炎林 | D96: 永叙 | E96: D19-1 | F96: 3682-593-96F双刷单摇 | H96: SP25013 | I96: 100%涤纶 | J96: 100%POLY | K96: 160 | L96: 220 | O96: 染定 | P96: P/D | W96: 欧纺时尚 | X96: 3682-593 | Y96: 广源毛绒 | Z96: 3682-593# | AA96: 10.5 | AB96: 45766 | AG96: 色卡
A97: 95 | B97: 45769 | C97: 陈炎林 | D97: 永叙 | E97: D19-1 | F97: A9411-精品加厚奥尔粒 | H97: SP25014 | I97: 100%涤纶 | J97: 100%POLY | K97: 160 | L97: 290 | O97: 染定 | P97: P/D | W97: 欧纺时尚 | X97: A9411 | Y97: 伟利达毛绒 | Z97: A9411 | AA97: 13 | AB97: 45766 | AG97: 色卡
A98: 96 | B98: 45769 | C98: 陈炎林 | D98: 永叙 | E98: D19-1 | F98: N35BH | H98: SP25015 | I98: 95%涤纶5%氨纶 | J98: 95%POLY5%SP | K98: 140 | L98: 180 | O98: 染定 | P98: P/D | W98: 欧纺时尚 | X98: N35BH | Y98: 新宇勋 | Z98: N35BH | AA98: 9 | AB98: 45766 | AG98: 色卡
A99: 97 | B99: 45769 | C99: 陈炎林 | D99: 永叙 | E99: D19-1 | F99: T7122-丹麦提花 | H99: SP25016 | I99: 95%涤纶5%氨纶 | J99: 95%POLY5%SP | K99: 180 | L99: 110 | O99: 染定 | P99: P/D | W99: 欧纺时尚 | X99: T7122 | Y99: 一朵棉纺织 | Z99: T7122# | AG99: 色卡
A100: 98 | B100: 45769 | C100: 陈炎林 | D100: 永叙 | E100: D19-1 | F100: A999洞布 | H100: SP25017 | I100: 100%涤纶 | J100: 100%POLY | K100: 160 | L100: 140 | O100: 染定 | P100: P/D | W100: 欧纺时尚 | X100: A999洞布 | Y100: 茂源运动 | Z100: A999洞布 | AA100: 7.9（35.2/kg） | AB100: 45766 | AG100: 色卡
A101: 99 | B101: 45769 | C101: 陈炎林 | D101: 永叙 | E101: D19-1 | F101: 2.5公分条纹 | H101: SP25018 | I101: 100%涤纶 | J101: 100%POLY | K101: 160 | L101: 120 | O101: 染定 | P101: P/D | W101: 欧纺时尚 | X101: 2.5公分条纹 | Y101: 昊源网布 | Z101: 2.5公分条纹 | AA101: 5.7 | AB101: 45766 | AG101: 小块布样
A102: 100 | B102: 45769 | C102: 陈炎林 | D102: 永叙 | E102: D19-1 | F102: 4.5公分条纹 | H102: SP25019 | I102: 100%涤纶 | J102: 100%POLY | K102: 160 | L102: 120 | O102: 染定 | P102: P/D | W102: 欧纺时尚 | X102: 4.5公分条纹 | Y102: 昊源网布 | Z102: 4.5公分条纹 | AA102: 5.7 | AB102: 45766 | AG102: 小块布样
A103: 101 | B103: 45769 | C103: 陈炎林 | D103: 永叙 | E103: D19-1 | F103: S2627# | H103: SP25020 | I103: 100%涤纶 | J103: 100%POLY | K103: 145 | O103: 染定 | P103: P/D | W103: 欧纺时尚 | X103: S2627# | Y103: 盛业纺织 | Z103: S2627# | AA103: 6.8 | AB103: 45766 | AG103: 色卡
A104: 102 | B104: 45769 | C104: 陈炎林 | D104: 永叙 | E104: D19-1 | F104: 7078 | H104: SP25021 | I104: 100%涤纶 | J104: 100%POLY | K104: 145 | O104: 染定 | P104: P/D | W104: 欧纺时尚 | X104: 7078 | Y104: 昌盛纺织 | Z104: 7078 | AA104: 8 | AB104: 45766 | AG104: 色卡
A105: 103 | B105: 45769 | C105: 陈炎林 | D105: 永叙 | E105: D19-1 | F105: 11286与SP25021一样，所以没寄出 | H105: SP25022 | I105: 100%涤纶 | J105: 100%POLY | K105: 145 | O105: 染定 | P105: P/D | W105: 欧纺时尚 | X105: 11286 | Y105: 杰鑫格子 | Z105: 11286 | AA105: 8.2 | AB105: 45766 | AG105: 色卡
A106: 104 | B106: 45769 | C106: 陈炎林 | D106: 永叙 | E106: D19-1 | F106: 102-64# | H106: SP25023 | I106: 100%涤纶 | J106: 100%POLY | K106: 145 | O106: 染定 | P106: P/D | W106: 欧纺时尚 | X106: 102-64 | Y106: 茂盛纺织 | Z106: 102-64# | AA106: 6.8 | AB106: 45766 | AG106: 色卡
...

Sheet 正式编号化纤加工别
A1: 信兴隆化纤厂加工别代码一览表 （新表）
A2: 栏位 | B2: 1 | C2: 2 | E2: 3 | G2: 4 | I2: 5 | K2: 6 | M2: 7
A3: 项目 | B3: 染色 | C3: 胶类 | E3: 防水度 | G3: 透湿度 | I3: 泼水度 | K3: 功能 | M3: 压光/特殊加工
A4: 代号 | B4: 说明 | C4: 代号 | D4: 说明 | E4: 代号 | F4: 说明 | G4: 代号 | H4: 说明 | I4: 代号 | J4: 说明 | K4: 代号 | L4: 说明 | M4: 代号 | N4: 说明
A5: O | B5: 无染色 | C5: O | D5: 无上胶 | E5: O | F5: 无水压 | G5: O | H5: 无透湿度 | I5: O | J5: 无泼水 | K5: O | L5: 无功能 | M5: A | N5: PU感温膜 | O5: 新表
A6: A | B6: 磨毛染色 | C6: A | D6: 压克力透明胶 | E6: 1~9 | F6: 100~900mmH2O | G6: 1 | H6: 1000 G/M2.D | I6: S | J6: 一般定型 | K6: F | L6: 阻燃 | M6: B | N6: 双面压光
A7: B | B7: Beam 染色 | C7: B | D7: 水性AC透明胶 | E7: A | F7: 1000mmH2O↑ | G7: 2 | H7: 2000 G/M2.D | I7: T | J7: 柔软定型 | K7: B | L7: UV CUT加工 | M7: C | N7: 压皱
A8: C | B8: 抗氯染色 | C8: C | D8: 压克力白胶 | E8: B | F8: 1500mmH2O↑ | G8: 3 | H8: 3000 G/M2.D | I8: R | J8: C8防水(50-60分） | K8: C | L8: 抗静电 | M8: D | N8: 防绒压光
A9: D | B9: 荧光漂白 | C9: D | D9: 水性AC白胶 | E9: C | F9: 2000mmH2O↑ | G9: 4 | H9: 4000 G/M2.D | I9: C | J9: C8防水3级(70-80分) | K9: D | L9: 抗菌防臭加工 | M9: E | N9: 压花
A10: E | B10: 涤纶本白印花 | C10: E | D10: 水性PU透明胶 | E10: D | F10: 3000mmH2O↑ | G10: 5 | H10: 5000 G/M2.D | I10: N | J10: C8超泼水、三防及含吊牌 | K10: E | L10: 消光 | M10: F | N10: 铁牛印花（滚涂印花）
A11: F | B11: 磨毛抗氯染色 | C11: F | D11: 防火(PU) | E11: E | F11: 5000mmH2O↑ | G11: 6 | H11: 6000 G/M2.D | I11: E | J11: C8防水4级 | K11: G | L11: 吸湿排汗 | M11: K | N11: 正面硅胶,另一面不压光PU涂层
A12: G | B12: 吸湿排汗染色 | C12: I | D12: 离型纸转贴 | E12: F | F12: 10000mmH2O↑ | G12: 7 | H12: 7000 G/M2.D | I12: F | J12: C8三防加工及无吊牌耐洗3-5次 | K12: A | L12: 吸湿排汗易去污 | M12: L | N12: 一般压光
A13: J | B13: JG染色 | C13: J | D13: 珠光胶 | E13: G | F13: 8000mmH2O↑ | G13: 8 | H13: 8000 G/M2.D | I13: B | J13: C8三防无吊牌耐洗10次 | K13: R | L13: 易去污 | M13: O | N13: 不经压光
A14: K | B14: RP染皱染色 | C14: K | D14: UV CUT加工 | E14: H | F14: 20000mmH2O↑ | G14: 9 | H14: 9000 G/M2.D | I14: X | J14: C6防水(50-60分） | K14: Y | L14: 抗黄变定型 | M14: P | N14: PU微多孔膜
A15: R | B15: RP染色 | C15: L | D15: PU色胶 | G15: A | H15: 10000 G/M2.D | I15: J | J15: C6防水3级(70-80分) | K15: H | L15: 防蚊助剂 | M15: S | N15: 压光面做面
A16: Y | B16: 抗黄变染色 | C16: M | D16: 远红外线透湿胶 | G16: B | H16: 15000 G/M2.D | I16: K | J16: C6防水4级 | K16: I | L16: 吸湿速干 | M16: T | N16: 正面硅胶,另一面压光加PU涂层
A17: H | B17: 抗菌染色 | C17: P | D17: PU 印花膜 | G17: C | H17: 20000 G/M2.D | I17: U | J17: C6三防加工及无吊牌耐洗3-5次 | K17: P | L17: 抗花粉整理 | M17: M | N17: 防绒贴条
A18: L | B18: 抗紫外染色 | C18: S | D18: Silicone coating | I18: V | J18: C6三防无吊牌耐洗10次 | K18: S | L18: 树脂 | M18: N | N18: 离型纸转贴作面
A19: P | B19: 染底纸印花 | C19: T | D19: PU透湿白胶 | I19: W | J19: C6超泼水、三防及含吊牌 | K19: J | L19: 胶原蛋白 | M19: W | N19: PU转移远红外线保温印花膜
A20: S | B20: 磨毛+吸湿 | C20: U | D20: PU透明胶 | I20: A | J20: 无氟防水(50-60分） | K20: K | L20: 芳香 | M20: G | N20: 激光冲孔
A21: N | B21: 尼龙印花 | C21: W | D21: PU透明透湿胶 | I21: G | J21: 无氟防水3级(70-80分) | K21: M | L21: 抗菌防霉 | M21: H | N21: 烫金工艺
A22: M | B22: 拉毛+印花 | C22: X | D22: PU白胶 | I22: L | J22: 无氟防水4级 | K22: L | L22: UPF+吸湿排汗 | M22: J | N22: 针织贴合
A23: X | B23: 冷转移印花 | C23: Q | D23: A/C透明强力胶 | I23: P | J23: 无氟防水鲁道夫吊牌 | K23: N | L23: 抗病毒 | M23: I | N23: 海绵复合
A24: Z | B24: 抓绒 | C24: N | D24: PU蜡感胶 | I24: Q | J24: 无氟防水3M吊牌 | K24: P | L24: 凉感 | M24: 2 | N24: 摇粒绒贴合
A25: W | B25: 单上胶 | C25: G | D25: 水性AC色胶 | I25: Y | J25: 无氟防水R3杜邦吊牌 | K25: V | L25: 温控 | M25: 3 | N25: 涂层复合不压光
A26: Q | B26: 重压光染皱 | C26: H | D26: 微多孔湿法透湿白胶 | I26: D | J26: C6三防无吊牌耐洗20次 | M26: 4 | N26: 膜二层复合+压光
C27: V | D27: 微多孔干法透湿白胶 | I27: H | J27: C0三防无吊牌耐洗10次 | M27: 5 | N27: 膜二层复合+不压光
C28: Z | D28: 肤感胶 | M28: 6 | N28: 膜三层复合+压光
C29: 2 | D29: TPU透湿透明膜 | M29: 7 | N29: 膜三层复合+不压光
C30: 3 | D30: TPU透湿白色膜 | M30: 8 | N30: 梭织布贴合
C31: 4 | D31: TPU透湿白色雾面膜 | M31: 9 | N31: 超声波绗棉+无纺布
C32: 5 | D32: TPU透湿雾面膜 | M32: Q | N32: 缝线压花+无纺布
C33: 6 | D33: TPU透湿印花膜 | M33: R | N33: 镭射贴膜
C34: 7 | D34: PU透湿透明膜 | M34: X | N34: EVA复合
C35: 8 | D35: PU透湿白色膜 | M35: Y | N35: PVC复合
C36: 9 | D36: PTFE透湿白色膜 | M36: U | N36: TPU重贴作面
C37: R | D37: 反光材料 | M37: V | N37: 热熔膜
C38: Y | D38: 透明发热胶 | M38: Z | N38: 压花+针织复合
C39: a | D39: 温感色胶 | M39: a | N39: 石墨烯PU高透膜
C40: b | D40: TPU透湿导电印花膜 | M40: b | N40: 夜光膜
C41: c | D41: 烫银PU膜 | M41: c | N41: 发热膜
C42: d | D42: 黑色TPU膜 | M42: d | N42: OPP膜
C43: e | D43: PU透气膜 | M43: e | N43: 刷毛
A46: 1、目前此代号对应MP014渐变功能胶，以后若是增加颜色按照珠光渐变功能胶的色号编列。
A47: 2、对于MP001渐变不透底四个色用1#、2#、3#、4#代号，后续有增加花型以此类推。
A48: 3、标黄色是广州增加的代码

Sheet 正式编号棉布加工别
A1: 信兴隆棉类产品加工别代码一览表
A2: 栏位 | B2: 1 | C2: 2 | E2: 3 | G2: 4 | I2: 5
A3: 项目 | B3: 染色 | C3: 手感、毛感整理 | E3: 泼水度 | G3: 定型功能 | I3: 胶类
A4: 代号 | B4: 说明 | C4: 代号 | D4: 说明 | E4: 代号 | F4: 说明 | G4: 代号 | H4: 说明 | I4: 代号 | J4: 说明
A5: O | B5: 前处理不染色 | C5: O | D5: 无整理 | E5: O | F5: 无泼水 | G5: O | H5: 无功能 | I5: O | J5: 无上胶
A6: N | B6: 普染/NORMAL FINISHING | C6: M | D6: 磨毛/MICRO SAND | E6: C | F6: 低度泼水(50°-70°)/LOW W/R | G6: F | H6: 阻燃定型/ FLAME RETARDANT | I6: A | J6: 压克力透明胶/A/C COATING
A7: F | B7: 洗褪/FADING AWAY | C7: T | D7: 碳素磨毛/CARBON SUEDE | E7: R | F7: 泼水定型(80°以上)/ W/R | G7: B | H7: 抗紫外线/UV CUT | I7: B | J7: 水性AC透明胶/ WATER BASE A/C COATING
A8: L | B8: 冷染/COLD PAD-BATCH DYEING | C8: R | D8: 抓剪毛/RAISING&SHEARING | E8: T | F8: 柔软定型/ SOFT FINISHING | G8: C | H8: 抗静电加工/ ANTI-STATIC | I8: C | J8: 压克力色胶/A/C COLOR COATING
A9: D | B9: 染底印花/DYEING & PRINTING | C9: H | D9: 磨花/PATTERN SUEDE | E9: U | F9: 泼水柔软定型/ SOFT & W/R FINISHING | G9: D | H9: 抗菌防臭加工/ANTI-MICROBES | I9: E | J9: 水性PU透明胶/ WATER BASE PU COATING
A10: P | B10: 本白印花/PRINTING | C10: S | D10: 仿天丝/SILKY TOUCH | E10: H | F10: 树脂定型/ RESIN FINISHING | G10: S | H10: 三防加工/W/R & O/R & S/R | I10: F | J10: 防火(PU)/FLAME RETARDANT PU COATING
A11: B | B11: 双面印花/BOTH SIDES PRINTING | C11: W | D11: 磨毛+仿天丝/MICRO SAND & SILKY TOUCH | E11: M | F11: 泼水树脂/ RESINATE & W/R | G11: R | H11: 易去污/ S/R | I11: J | J11: 针织拉绒复合
A12: X | B12: 洗褪印花/FADING AWAY & PRINTING | C12: G | D12: 碳磨+仿天丝/MICRO SAND & SILKY TOUCH | E12: N | F12: 超泼水定型/ W/R & O/R | G12: Y | H12: 抗黄变定型/ ANTI-YELLOWING | I12: L | J12: PU色胶(蜡感胶)/ PU COLOR COATING( WAX COATING)
A13: R | B13: 冷染印花/COLD PAD-BATCH DYEING & PRINTING | E13: E | F13: 加强泼水/ ENHANCE W/R | G13: A | H13: 抛松整理（特柔）/AIRO FINISH | I13: S | J13: 硅胶/SIlICONE COATING
A14: Y | B14: 拔印/DISCHARGE PRINTING | I14: T | J14: PU透湿色胶/PU COLOR COATING
A15: H | B15: 烫金/BRONZING | I15: U | J15: PU透明胶/PU COATING
I16: W | J16: PU透明透湿胶/ PU BREATHABLE COATING
I17: Y | J17: 油墨胶/ CARBON COATING
I18: G | J18: 水性AC色胶/ WATER BASE A/C COLOR COATING
I19: H | J19: 水性PU色胶/ WATER BASE PU COLOR COATING
I20: V | J20: 水性PU白胶/ WATER BASE PU MILKY COATING
I21: P | J21: 纸感胶PAPER TOUCHA
I22: I | J22: 亮光胶
I23: K | J23: PU皮感胶
I24: H | J24: 龟裂胶CHAP COATING
I25: Q | J25: TEFLON(10次)
I26: D | J26: 毛感胶
I27: X | J27: 仿记忆胶SHAPE MEMORY COATING
... I30: R | J30: 肤感胶
I31: 2 | J31: 复合二层/2-LAYER LAMINATION
I32: 3 | J32: 复合三层/ 3-LAYER LAMINATION

Sheet 编号规则
A1: 昇奕隆布种命名（布种编号）规则
A2: 更新日期： | B2: 46140
A3: 命名规则：
A4: 1：主要以SY+年份+数字从小到大编号，例如SY26001-SY261001-SY2610001等
A5: 2：鉴于很多产品现货为主，现货色卡有些同底布不同纹路或者加工整理等情况，会出现后缀情况，例如SY26268-3,SY26268-185,SY26269-293-3,其中-3，-185，-293-3是代表其在SY26268/SY26269色卡内的色号或者色卡内的品质代号。
A6: 3：后续有遇到新的问题将持续完善编号规则

Sheet SYL编号表
A1: 昇奕隆编号表 | N1: 胚布信息 | V1: 成品信息
A2: （年/月/日） | B2: *业务员 Owner | C2: 客户 Customer | D2: 布种编号 #Base | E2: 材料名称 Name | F2: 成份（中文) Composition | G2: *成份（英文） Composition | H2: *SPECIFICATION/规格 （经纱支x纬纱支/经密度x纬密度） | I2: 全部加工工艺（中文） Processes | J2: *全部加工工艺（英文） Processes | K2: *可裁门幅 Width | L2: *克重GSM | M2: *厚度mm | N2: *胚布厂 Greige mill | O2: *胚布厂胚布编码 Greige #article | P2: *胚布采购价格RMB/M | V2: *材料成品厂（供应商） FG mill | W2: *成品厂材料编码 FG #article | X2: *成品采购价格RMB/M | Z2: YDGE MOQ/Bulk MOQ 成品码样MOQ/成品大货MOQ | AA2: YDGE L/T/Bulk L/T 成品码样货期/成品大货货期 | AB2: YDGE Surcharge/Bulk Surcharge 成品码样费用/成品大货费用 | AC2: Stock available 成品是否有库存
A3: *开发日期 Creative Date | M3: 塑胶类 | P3: 价格 Price | Q3: 报价日期 Date 年/月/日 | R3: YDGE MOQ/Bulk MOQ 胚布码样MOQ/胚布大货MOQ | S3: YDGE L/T/Bulk L/T 胚布码样货期/胚布大货货期 | T3: YDGE Surcharge/Bulk Surcharge 胚布码样费用/胚布大货费用 | U3: Stock available 胚布是否有库存 | X3: 价格 Price | Y3: 报价日期 Date 年/月/日
A4: 45870 | B4: 陈晓彬 | C4: 中普/茂迪 | D4: SYL25001 / SYL20250927-5 | E4: 灰黑舞龙布 | F4: 100%涤纶 | G4: 100%POLY | H4: 600D*600D | I4: 染泼+PU透明胶 | J4: P/D+W/R+PU COATING | V4: 运邦 | W4: 灰黑舞龙布
A5: 45870 | B5: 陈晓彬 | C5: 乾元 | D5: SYL25002 | E5: 加捻弹力色丁 | F5: 93%尼龙7%氨纶 | G5: 93%NYLON 7%SP | H5: 50D*50D+20D | I5: 染色 | J5: P/D | K5: 145 | L5: 105 | V5: 运邦 | W5: 加捻弹力色丁
A6: 45950 | B6: 陈炎林 | C6: 泰瑞 | D6: SYL25003 | E6: 2/2斜纹 | F6: 100%涤纶 | H6: 150D*16S 0.37MM | I6: P/D | K6: 150 | L6: 204 | V6: 和记 | W6: JP172 1# | Y6: 10.2
A7: 45954 | B7: 陈晓彬 | C7: 中普/茂迪 | D7: SYL25004 | E7: 600D涤纶牛津格子布 | F7: 100%涤纶 | H7: 600D*600D
A8: 45954 | B8: 陈晓彬 | C8: 中普/茂迪 | D8: SYL25005 | E8: 300D涤纶牛津平格 | F8: 100%涤纶 | H8: 300D*300D
A9: 45959 | B9: 陈炎林 | C9: 泰瑞 | D9: SYL25006 | E9: 2/2斜纹 | F9: 100%涤纶 | H9: 150D*10S | I9: P/D | K9: 150 | L9: 242 | V9: 和记 | W9: JP172-1 | Y9: 10.25
A10: 45959 | B10: 陈炎林 | C10: 泰瑞 | D10: SYL25007 | E10: 乐丽丝 | F10: 100%涤纶 | I10: P/D | K10: 145 | L10: 170 | V10: 世贸 | W10: 第二套
A11: 45959 | B11: 陈炎林 | C11: 泰瑞 | D11: SYL25008 | E11: 阳涤 | F11: 100%涤纶 | I11: P/D | K11: 145 | L11: 213 | V11: 世贸 | W11: 第三套
A12: 45961 | B12: 陈炎林 | C12: 泰瑞 | D12: SYL25009 | E12: YCQ3085AU-D | F12: 100%TPU | H12: 0.5±0.02mm | K12: 137 | V12: 福建佳南 | W12: YCQ3085AU-D | Y12: 10.3
A13: 45961 | B13: 陈炎林 | C13: 泰瑞 | D13: SYL25010 | E13: MKN63235 | F13: 100%TPU | H13: 0.5±0.05mm | K13: 132 | V13: 广州明可 | W13: MKN63235 | X13: 28/Y | Y13: 10.31 | Z13: 50/300Y | AA13: 20/30天 | AB13: 150美元/颜色
A14: 45961 | B14: 陈炎林 | C14: 泰瑞 | D14: SYL25011 | E14: MKN63236 | F14: 100%TPU（90A) | H14: 0.5±0.05mm | K14: 132 | V14: 广州明可 | W14: MKN63236 | X14: 32/Y | Y14: 10.31 | Z14: 50/300Y | AA14: 20/30天 | AB14: 150美元/颜色
A15: 45961 | B15: 陈炎林 | C15: 泰瑞 | D15: SYL25012 | E15: 100D双层粗斜四面弹 | F15: 92%POLY8%SP | H15: 100D+40D*100D+40D | I15: P/D | K15: 145 | L15: 280 | V15: 世贸 | W15: FMG251029-4 | X15: 8.5（胚布价） | Y15: 10.31
A16: 45961 | B16: 陈炎林 | C16: 泰瑞 | D16: SYL25013 | E16: TR直贡尼四面弹 | F16: 76%POLY20%Rayon4%SP | H16: 32S+40D*150D+40D | I16: P/D | K16: 145 | L16: 265 | V16: 世贸 | W16: FMG251029-2 | X16: 10（胚布价） | Y16: 10.31
A17: 45961 | B17: 陈炎林 | C17: 泰瑞 | D17: SYL25014 | E17: 300*150复合丝变斜四面弹 | F17: 93%POLY7%SP | H17: 300D+40D*150D+40D | I17: P/D | K17: 145 | L17: 285 | V17: 世贸 | W17: FMG251029-1 | X17: 7.4（胚布价） | Y17: 10.31
A18: 45961 | B18: 陈炎林 | C18: 泰瑞 | D18: SYL25015 | E18: 300D复合丝变斜四面弹 | F18: 93%POLY7%SP | H18: 300D+40D*300D+40D | I18: P/D | K18: 145 | L18: 305 | V18: 世贸 | W18: FMG251029-3 | X18: 7.4（胚布价） | Y18: 10.31
A19: 45966 | B19: 陈炎林 | C19: META | D19: SYL25016 | E19: 75D*75D | F19: 100%涤纶 | H19: 75D*75D | I19: P/D | V19: 卓总提供
A20: 45967 | B20: 陈炎林 | C20: META | D20: SYL25017 | E20: MKN63215 | F20: 60%POLY40%PU | H20: 1.0±0.05mm | I20: P/D | K20: 52" | L20: 600 | V20: 明可 | W20: MKN63215 | X20: 28.5/码（含税含运） | Y20: 45966
A21: 45967 | B21: 陈炎林 | C21: META | D21: SYL25018 | E21: 文字D三层大提花 | F21: 98%POLY2%SP | H21: 100D*150D+300D+150/40D | I21: P/D | K21: 57 | L21: 270 | V21: 世贸 | W21: FMG251024-10 | X21: 11.8（胚布价） | Y21: 45965
A22: 45967 | B22: 陈炎林 | C22: META | D22: SYL25019 | E22: 闪电纹三层大提花 | F22: 98%POLY2%SP | H22: 100D*150D+300D+150/40D | I22: P/D | K22: 57 | L22: 270 | V22: 世贸 | W22: FMG251024-9 | X22: 11.6（胚布价） | Y22: 45965
A23: 45967 | B23: 陈炎林 | C23: META | D23: SYL25020 | E23: 玄武甲三层大提花 | F23: 98%POLY2%SP | H23: 100D*150D+300D+150/40D | I23: P/D | K23: 57 | L23: 276 | V23: 世贸 | W23: FMG251024-8 | X23: 11.8（胚布价） | Y23: 45965
A24: 45967 | B24: 陈炎林 | C24: META | D24: SYL25021 | E24: 龙鳞盾色织大提花 | F24: 100%POLY | H24: 100D*75D | I24: Y/D | K24: 57 | L24: 125 | V24: 世贸 | W24: FMG251024-7 | X24: 14（胚布价） | Y24: 45965
A25: 45967 | B25: 陈炎林 | C25: META | D25: SYL25022 | E25: 万疆大提花 | F25: 100%POLY | H25: 75D*75D | I25: P/D | K25: 57 | L25: 121 | V25: 世贸 | W25: FMG251024-2 | X25: 8（胚布价） | Y25: 45965
A26: 45967 | B26: 陈炎林 | C26: META | D26: SYL25023 | E26: 黑绿色织提花3#丛林 | F26: 100%POLY | H26: 75D*150D | I26: Y/D | K26: 57 | L26: 150 | V26: 世贸 | W26: FMG251024-6 | X26: 13.8（胚布价） | Y26: 45965
A27: 45967 | B27: 陈炎林 | C27: META | D27: SYL25024 | E27: 黑丝色织1#罗纹 | F27: 100%POLY | H27: 75D*150D | I27: Y/D | K27: 57 | L27: 150 | V27: 世贸 | W27: FMG251024-4 | X27: 13.8（胚布价） | Y27: 45965
A28: 45967 | B28: 陈炎林 | C28: META | D28: SYL25025 | E28: 金丝万花色织大提花 | F28: 100%POLY | H28: 150D*150D+300D+金丝 | I28: Y/D | K28: 57 | L28: 187 | V28: 世贸 | W28: FMG251024-3 | X28: 20（胚布价） | Y28: 45965
A29: 45968 | B29: 陈晓彬 | C29: 优步 | D29: SYL25026 | E29: T8酷丝绵登山布 | F29: 100%POLY | H29: 40S*150D+150D | L29: 310 | V29: 运邦-浙江日月梭 | W29: SYL20251105-005
A30: 45968 | B30: 陈晓彬 | C30: 优步 | D30: SYL25027 | E30: 1050D尼龙拷杜拉 | F30: 100%NYLON | H30: 1050D | V30: 运邦 | W30: SYL20251105-001
A31: 45973 | B31: 陈晓彬 | C31: 光瑞 | D31: SYL25028 | E31: 75D加密平桃 | V31: 运邦 | W31: SYL20251110-5
A32: 45975 | B32: 陈炎林 | C32: 泰瑞 | D32: SYL25029 | E32: 2/2斜氨纶加厚 | F32: 98%涤纶2%氨纶 | H32: 150D*600D+70D | V32: 和记 | W32: JP172SP-1 | Y32: 45975
A33: 45978 | B33: 陈晓彬 | C33: 优步 | D33: SYL25030 | E33: 考杜拉四面弹 | F33: 86%尼龙考杜拉 11%氨纶 | H33: (70D+40D)*(70D+40D)+250D/175T*150T | I33: P/D+W/R | K33: 141 | L33: 225 | V33: 运邦 | W33: 考杜拉四面弹
A34: 45985 | B34: 陈炎林 | C34: 泰瑞 | D34: SYL25031 | E34: 双色布 | F34: 100%POLY | H34: 100D*150D+150D+150D+75D | I34: Y/D | K34: 150 | L34: 143 | V34: 和记 | W34: JP182
B35: 陈晓彬 | C35: 光瑞 | D35: SYL25032
A36: 45999 | B36: 陈晓彬 | C36: 兆盈 | D36: SYL25033 | E36: 500D牛津布 | V36: 运邦
A37: 45999 | B37: 陈晓彬 | C37: 兆盈 | D37: SYL25034 | E37: 420D尼龙100T | V37: 运邦
A38: 45999 | B38: 陈晓彬 | C38: 兆盈 | D38: SYL25035 | E38: 尼龙塔丝隆牛津PU明一刀 | V38: 运邦
C39: 兆盈 | D39: SYL25036 | E39: 420D加密 | F39: 100%NYLON | I39: 染泼+PU透明胶 | K39: 58“ | V39: 兆兴 | W39: ZX-3013 | X39: 10.5 | Y39: 46001 | Z39: 100 | AD39: 100码以下，+开剪费1元
C40: 兆盈 | D40: SYL25037 | E40: 500D可提拉 | F40: 100%NYLON | I40: 染泼+PU透明胶 | K40: 58“ | V40: 兆兴 | W40: ZX-5003 | X40: 19 | Y40: 46001 | Z40: 100 | AD40: 100码以下，+开剪费1元
C41: META | D41: SYL25038 | E41: DS3978改牛仔风格 | F41: 98%涤纶2%氨纶 | G41: 98%POLY2%SP | K41: 140 | L41: 290 | V41: 和记 | W41: JP187 | X41: 28.6 | Y41: 含税不含运
C42: 仁和智能 | D42: SYL25039 | E42: 210T尼丝纺PU透 | F42: 100%NYLON | G42: 100%NYLON | K42: 145 | L42: 68
C43: 匠运 | D43: SYL25040 | E43: C10210帆布 | F43: 100%棉 | G43: 100%COTTON | H43: 10S/2*10S/42T*38T | I43: 染泼 | J43: P/D+W/R | L43: 300 | V43: 运邦 | W43: SYL20251227-01
C44: 匠运 | D44: SYL25041 | E44: C212107240帆布 | F44: 100%棉 | G44: 100%COTTON | H44: 21S/2*10S/72T*40T | I44: 染泼 | J44: P/D+W/R | L44: 260 | V44: 运邦 | W44: SYL20251227-02
C45: PVH | D45: SYL25042 | E45: 310T尼丝纺涂PA | V45: 运邦 | W45: SYL20251224-01
C46: 女真 | D46: SYL26001 | E46: 190T平桃 | F46: 100%涤纶 | G46: 100%POLY | V46: 运邦 | W46: SYL20250926-4
C47: 女真 | D47: SYL26002 | E47: 涤纶针织布 | F47: 100%涤纶 | G47: 100%POLY | V47: 运邦 | W47: SYL20251110-3
C48: 光瑞 | D48: SYL26003 | E48: 600D低弹牛津布 | F48: 100%涤纶 | G48: 100%POLY | K48: 145 | L48: 298 | V48: 运邦 | W48: SYL20260120-1
C49: META | D49: SYL26004 | E49: 织带 | F49: 100%涤纶 | G49: 100%POLY | V49: 百事得
C50: 安克 | D50: SYL26005 | F50: 85%人棉 15%亚麻 | G50: 85%Rayon 14%Linen 1%SP | K50: 136 | L50: 220 | V50: 湖南杰新
C51: 安克 | D51: SYL26006-1 | E51: 黑丝尼龙小人字 | V51: 世贸 | W51: FM260507-1#
C52: 安克 | D52: SYL26007 | V52: 和记 | W52: DS2448 | X52: 26.4/米含税
C53: 安克 | D53: SYL26006-2 | E53: 黑丝尼龙大人字 | V53: 世贸 | W53: FM260507-2#

Sheet 剪样
A1: 日期 | B1: 加工厂 | C1: 布种编号 | D1: 供应商 | E1: 编号 | F1: 颜色 | G1: 数量 | H1: 单位 | I1: 实际出货数量 | J1: 出货日期 | K1: 销售价 | L1: 销售金额 | M1: 付款方式 | N1: 报价 | O1: 采购价 | P1: 采购金额 | Q1: 备注 | R1: 对账
A2: 45770 | B2: 圣德 | C2: SY25016 | D2: =_xlfn.SINGLE(INDEX(样品编号表!Y:Y,_xlfn.SINGLE(MATCH(_xlfn.SINGLE(C:C),样品编号表!H:H,0)))) -> 光大纺织 | E2: =_xlfn.SINGLE(INDEX(样品编号表!Z:Z,_xlfn.SINGLE(MATCH(_xlfn.SINGLE(C:C),样品编号表!H:H,0)))) -> C580 | F2: 15# | G2: 7 | H2: 米 | I2: 7 | J2: 45771 | K2: 17 | L2: =I2*K2 -> 119 | M2: 微信 | N2: =_xlfn.SINGLE(INDEX(样品编号表!AA:AA,_xlfn.SINGLE(MATCH(_xlfn.SINGLE(C:C),样品编号表!H:H,0)))) -> 9.8 | O2: 14 | P2: =I2*O2 -> 98 | R2: 已对账
A3: 45793 | B3: D&J | C3: SP25032 | D3: =_xlfn.SINGLE(INDEX(样品编号表!Y:Y,_xlfn.SINGLE(MATCH(_xlfn.SINGLE(C:C),样品编号表!H:H,0)))) -> 昌勋纺织 | E3: =_xlfn.SINGLE(INDEX(样品编号表!Z:Z,_xlfn.SINGLE(MATCH(_xlfn.SINGLE(C:C),样品编号表!H:H,0)))) -> C734 | F3: 32# | G3: 4 | H3: 米 | I3: 4 | J3: 45796 | K3: 22 | L3: =I3*K3 -> 88 | M3: 微信 | N3: =_xlfn.SINGLE(INDEX(样品编号表!AA:AA,_xlfn.SINGLE(MATCH(_xlfn.SINGLE(C:C),样品编号表!H:H,0)))) -> 10.8 | O3: 14 | P3: =I3*O3 -> 56 | R3: 已对账
A4: 45801 | B4: 乐力 | C4: AB2364 | D4: 欧纺时尚 | E4: B364 | F4: 白色 | G4: 20 | H4: 米 | I4: 20 | J4: 45803 | K4: 15.6 | L4: =I4*K4 -> 312 | M4: 微信 | N4: 11 | O4: 11 | P4: =I4*O4 -> 220 | R4: 已对账
A5: 45803 | B5: 圣德 | C5: SY25016 | D5: =_xlfn.SINGLE(INDEX(样品编号表!Y:Y,_xlfn.SINGLE(MATCH(_xlfn.SINGLE(C:C),样品编号表!H:H,0)))) -> 光大纺织 | E5: =_xlfn.SINGLE(INDEX(样品编号表!Z:Z,_xlfn.SINGLE(MATCH(_xlfn.SINGLE(C:C),样品编号表!H:H,0)))) -> C580 | F5: 91# | G5: 2 | H5: 米 | I5: 2 | J5: 45804 | K5: 17 | L5: =I5*K5 -> 34 | M5: 微信 | N5: =_xlfn.SINGLE(INDEX(样品编号表!AA:AA,_xlfn.SINGLE(MATCH(_xlfn.SINGLE(C:C),样品编号表!H:H,0)))) -> 9.8 | O5: 14 | P5: =I5*O5 -> 28 | R5: 已对账
A6: 45803 | B6: 圣德 | C6: SY25016 | D6: =_xlfn.SINGLE(INDEX(样品编号表!Y:Y,_xlfn.SINGLE(MATCH(_xlfn.SINGLE(C:C),样品编号表!H:H,0)))) -> 光大纺织 | E6: =_xlfn.SINGLE(INDEX(样品编号表!Z:Z,_xlfn.SINGLE(MATCH(_xlfn.SINGLE(C:C),样品编号表!H:H,0)))) -> C580 | F6: 5# | G6: 1 | H6: 米 | I6: 1 | J6: 45804 | K6: 17 | L6: =I6*K6 -> 17 | M6: 微信 | N6: =_xlfn.SINGLE(INDEX(样品编号表!AA:AA,_xlfn.SINGLE(MATCH(_xlfn.SINGLE(C:C),样品编号表!H:H,0)))) -> 9.8 | O6: 14 | P6: =I6*O6 -> 14 | R6: 已对账
A7: 45814 | B7: 万泰 | C7: SC25020-14 | D7: =_xlfn.SINGLE(INDEX(样品编号表!Y:Y,_xlfn.SINGLE(MATCH(_xlfn.SINGLE(C:C),样品编号表!H:H,0)))) -> 金绣 | E7: =_xlfn.SINGLE(INDEX(样品编号表!Z:Z,_xlfn.SINGLE(MATCH(_xlfn.SINGLE(C:C),样品编号表!H:H,0)))) -> A2185 | F7: 白色 | G7: 6 | H7: 米 | I7: 6 | J7: 45815 | K7: 33 | L7: =I7*K7 -> 198 | M7: 微信 | N7: =_xlfn.SINGLE(INDEX(样品编号表!AA:AA,_xlfn.SINGLE(MATCH(_xlfn.SINGLE(C:C),样品编号表!H:H,0)))) -> 14.6 | O7: 25 | P7: =I7*O7 -> 150 | R7: 已对账
A8: 45814 | B8: 万泰 | C8: SC25020-2 | D8: =_xlfn.SINGLE(INDEX(样品编号表!Y:Y,_xlfn.SINGLE(MATCH(_xlfn.SINGLE(C:C),样品编号表!H:H,0)))) -> 真成纺织 | E8: =_xlfn.SINGLE(INDEX(样品编号表!Z:Z,_xlfn.SINGLE(MATCH(_xlfn.SINGLE(C:C),样品编号表!H:H,0)))) -> B-894 | F8: 白色 | G8: 3 | H8: 米 | I8: 3 | J8: 45815 | K8: 33.7 | L8: =I8*K8 -> 101.1 | M8: 微信 | N8: =_xlfn.SINGLE(INDEX(样品编号表!AA:AA,_xlfn.SINGLE(MATCH(_xlfn.SINGLE(C:C),样品编号表!H:H,0)))) -> 16.5 | O8: 25 | P8: =I8*O8 -> 75 | R8: 已对账
A9: 45817 | B9: 无锡美盛 | C9: SY25063 | D9: =_xlfn.SINGLE(INDEX(样品编号表!Y:Y,_xlfn.SINGLE(MATCH(_xlfn.SINGLE(C:C),样品编号表!H:H,0)))) -> 年年发纺织 | E9: =_xlfn.SINGLE(INDEX(样品编号表!Z:Z,_xlfn.SINGLE(MATCH(_xlfn.SINGLE(C:C),样品编号表!H:H,0)))) -> 303# | F9: 4#米黄色 | G9: 4 | H9: 米 | I9: 4 | J9: 45818 | K9: 21 | L9: =I9*K9 -> 84 | M9: 微信 | N9: =_xlfn.SINGLE(INDEX(样品编号表!AA:AA,_xlfn.SINGLE(MATCH(_xlfn.SINGLE(C:C),样品编号表!H:H,0)))) -> 11.3 | O9: 15 | P9: =I9*O9 -> 60 | R9: 已对账
A10: 45818 | B10: D&J | C10: SY25016 | D10: =_xlfn.SINGLE(INDEX(样品编号表!Y:Y,_xlfn.SINGLE(MATCH(_xlfn.SINGLE(C:C),样品编号表!H:H,0)))) -> 光大纺织 | E10: =_xlfn.SINGLE(INDEX(样品编号表!Z:Z,_xlfn.SINGLE(MATCH(_xlfn.SINGLE(C:C),样品编号表!H:H,0)))) -> C580 | F10: 1#白色 | G10: 6 | H10: 米 | I10: 6 | J10: 45819 | K10: 17 | L10: =I10*K10 -> 102 | M10: 微信 | N10: =_xlfn.SINGLE(INDEX(样品编号表!AA:AA,_xlfn.SINGLE(MATCH(_xlfn.SINGLE(C:C),样品编号表!H:H,0)))) -> 9.8 | O10: 14 | P10: =I10*O10 -> 84 | R10: 已对账
A11: 45828 | B11: 圣德 | C11: SY25016 | D11: =_xlfn.SINGLE(INDEX(样品编号表!Y:Y,_xlfn.SINGLE(MATCH(_xlfn.SINGLE(C:C),样品编号表!H:H,0)))) -> 光大纺织 | E11: =_xlfn.SINGLE(INDEX(样品编号表!Z:Z,_xlfn.SINGLE(MATCH(_xlfn.SINGLE(C:C),样品编号表!H:H,0)))) -> C580 | F11: 91# | G11: 2 | H11: 米 | I11: 2 | J11: 45829 | K11: 17 | L11: =I11*K11 -> 34 | M11: 微信 | N11: =_xlfn.SINGLE(INDEX(样品编号表!AA:AA,_xlfn.SINGLE(MATCH(_xlfn.SINGLE(C:C),样品编号表!H:H,0)))) -> 9.8 | O11: 14 | P11: =I11*O11 -> 28 | R11: 已对账
A12: 45842 | B12: 乐力 | C12: AB2364 | D12: 欧纺时尚 | E12: B364 | F12: 白色 | G12: 20 | H12: 米 | I12: 20 | J12: 45843 | K12: 15.6 | L12: =I12*K12 -> 312 | M12: 微信 | N12: 11 | O12: 11 | P12: =I12*O12 -> 220 | R12: 已对账
A13: 45847 | B13: 万泰 | C13: SC25013 | D13: =_xlfn.SINGLE(INDEX(样品编号表!Y:Y,_xlfn.SINGLE(MATCH(_xlfn.SINGLE(C:C),样品编号表!H:H,0)))) -> 星海 | E13: =_xlfn.SINGLE(INDEX(样品编号表!Z:Z,_xlfn.SINGLE(MATCH(_xlfn.SINGLE(C:C),样品编号表!H:H,0)))) -> 2C1505 | F13: 4#咖色 | G13: 2 | H13: 米 | I13: 2 | J13: 45850 | K13: 30 | L13: =I13*K13 -> 60 | M13: 微信 | N13: =_xlfn.SINGLE(INDEX(样品编号表!AA:AA,_xlfn.SINGLE(MATCH(_xlfn.SINGLE(C:C),样品编号表!H:H,0)))) -> 17.2 | O13: 30 | P13: =I13*O13 -> 60 | R13: 已对账
A14: 45847 | B14: 万泰 | C14: SC25013 | D14: =_xlfn.SINGLE(INDEX(样品编号表!Y:Y,_xlfn.SINGLE(MATCH(_xlfn.SINGLE(C:C),样品编号表!H:H,0)))) -> 星海 | E14: =_xlfn.SINGLE(INDEX(样品编号表!Z:Z,_xlfn.SINGLE(MATCH(_xlfn.SINGLE(C:C),样品编号表!H:H,0)))) -> 2C1505 | F14: 6#黑白 | G14: 2 | H14: 米 | I14: 2 | J14: 45850 | K14: 30 | L14: =I14*K14 -> 60 | M14: 微信 | N14: =_xlfn.SINGLE(INDEX(样品编号表!AA:AA,_xlfn.SINGLE(MATCH(_xlfn.SINGLE(C:C),样品编号表!H:H,0)))) -> 17.2 | O14: 30 | P14: =I14*O14 -> 60 | R14: 已对账
A15: 45854 | B15: 扑喜 | C15: SY25567 | D15: =_xlfn.SINGLE(INDEX(样品编号表!Y:Y,_xlfn.SINGLE(MATCH(_xlfn.SINGLE(C:C),样品编号表!H:H,0)))) -> 恒鑫 | E15: =_xlfn.SINGLE(INDEX(样品编号表!Z:Z,_xlfn.SINGLE(MATCH(_xlfn.SINGLE(C:C),样品编号表!H:H,0)))) -> 1090A# | F15: 1#白色 | G15: 1 | H15: 米 | I15: 1 | J15: 45855 | K15: 26 | L15: =I15*K15 -> 26 | M15: 微信 | N15: =_xlfn.SINGLE(INDEX(样品编号表!AA:AA,_xlfn.SINGLE(MATCH(_xlfn.SINGLE(C:C),样品编号表!H:H,0)))) -> 13.5 | O15: 20 | P15: =I15*O15 -> 20 | R15: 已对账
A16: 45863 | B16: 圣德 | C16: SY25016 | D16: =_xlfn.SINGLE(INDEX(样品编号表!Y:Y,_xlfn.SINGLE(MATCH(_xlfn.SINGLE(C:C),样品编号表!H:H,0)))) -> 光大纺织 | E16: =_xlfn.SINGLE(INDEX(样品编号表!Z:Z,_xlfn.SINGLE(MATCH(_xlfn.SINGLE(C:C),样品编号表!H:H,0)))) -> C580 | F16: 5# | G16: 1 | H16: 米 | I16: 1 | J16: 45866 | K16: 17 | L16: =I16*K16 -> 17 | M16: 微信 | N16: =_xlfn.SINGLE(INDEX(样品编号表!AA:AA,_xlfn.SINGLE(MATCH(_xlfn.SINGLE(C:C),样品编号表!H:H,0)))) -> 9.8 | O16: 14 | P16: =I16*O16 -> 14 | R16: 已对账
A17: 45869 | B17: 倍德 | C17: SP25051 | D17: =_xlfn.SINGLE(INDEX(样品编号表!Y:Y,_xlfn.SINGLE(MATCH(_xlfn.SINGLE(C:C),样品编号表!H:H,0)))) -> 马利布行 | E17: =_xlfn.SINGLE(INDEX(样品编号表!Z:Z,_xlfn.SINGLE(MATCH(_xlfn.SINGLE(C:C),样品编号表!H:H,0)))) -> 10172# | F17: 1#黑色 | G17: 3 | H17: 米 | I17: 3 | J17: 45871 | K17: 25.7 | L17: =I17*K17 -> 77.1 | M17: 微信 | N17: =_xlfn.SINGLE(INDEX(样品编号表!AA:AA,_xlfn.SINGLE(MATCH(_xlfn.SINGLE(C:C),样品编号表!H:H,0)))) -> 12.2 | O17: 17 | P17: =I17*O17 -> 51 | R17: 已对账
A18: 45874 | B18: 万泰 | C18: SY25827 | D18: =_xlfn.SINGLE(INDEX(样品编号表!Y:Y,_xlfn.SINGLE(MATCH(_xlfn.SINGLE(C:C),样品编号表!H:H,0)))) -> 万利行 | E18: =_xlfn.SINGLE(INDEX(样品编号表!Z:Z,_xlfn.SINGLE(MATCH(_xlfn.SINGLE(C:C),样品编号表!H:H,0)))) -> 521-2# | F18: 64#土黄色 | G18: 7 | H18: 米 | I18: 7 | J18: 45880 | K18: 21.1 | L18: =I18*K18 -> 147.7 | M18: 微信 | N18: =_xlfn.SINGLE(INDEX(样品编号表!AA:AA,_xlfn.SINGLE(MATCH(_xlfn.SINGLE(C:C),样品编号表!H:H,0)))) -> 10.5 | O18: 16 | P18: =I18*O18 -> 112 | R18: 已对账
A19: 45874 | B19: 万泰 | C19: SY25827 | D19: =_xlfn.SINGLE(INDEX(样品编号表!Y:Y,_xlfn.SINGLE(MATCH(_xlfn.SINGLE(C:C),样品编号表!H:H,0)))) -> 万利行 | E19: =_xlfn.SINGLE(INDEX(样品编号表!Z:Z,_xlfn.SINGLE(MATCH(_xlfn.SINGLE(C:C),样品编号表!H:H,0)))) -> 521-2# | F19: 3#米白色 | G19: 23 | H19: 米 | I19: 23 | J19: 45880 | K19: 21.1 | L19: =I19*K19 -> 485.3 | M19: 微信 | N19: =_xlfn.SINGLE(INDEX(样品编号表!AA:AA,_xlfn.SINGLE(MATCH(_xlfn.SINGLE(C:C),样品编号表!H:H,0)))) -> 10.5 | O19: 11 | P19: =I19*O19 -> 253 | R19: 已对账
A20: 45875 | B20: 杰登 | C20: SY25531 | D20: =_xlfn.SINGLE(INDEX(样品编号表!Y:Y,_xlfn.SINGLE(MATCH(_xlfn.SINGLE(C:C),样品编号表!H:H,0)))) -> 凯盛亨 | E20: =_xlfn.SINGLE(INDEX(样品编号表!Z:Z,_xlfn.SINGLE(MATCH(_xlfn.SINGLE(C:C),样品编号表!H:H,0)))) -> 839# | F20: 1#白色 | G20: 3 | H20: 米 | I20: 3 | J20: 45879 | K20: 20 | L20: =I20*K20 -> 60 | M20: 支付宝 | N20: =_xlfn.SINGLE(INDEX(样品编号表!AA:AA,_xlfn.SINGLE(MATCH(_xlfn.SINGLE(C:C),样品编号表!H:H,0)))) -> 11.3 | O20: 16 | P20: =I20*O20 -> 48 | R20: 已对账
A21: 45876 | B21: D&J | C21: SY25016 | D21: =_xlfn.SINGLE(INDEX(样品编号表!Y:Y,_xlfn.SINGLE(MATCH(_xlfn.SINGLE(C:C),样品编号表!H:H,0)))) -> 光大纺织 | E21: =_xlfn.SINGLE(INDEX(样品编号表!Z:Z,_xlfn.SINGLE(MATCH(_xlfn.SINGLE(C:C),样品编号表!H:H,0)))) -> C580 | F21: 1#白色 | G21: 2 | H21: 米 | I21: 2 | J21: 45877 | K21: 17 | L21: =I21*K21 -> 34 | M21: 微信 | N21: =_xlfn.SINGLE(INDEX(样品编号表!AA:AA,_xlfn.SINGLE(MATCH(_xlfn.SINGLE(C:C),样品编号表!H:H,0)))) -> 9.8 | O21: 14 | P21: =I21*O21 -> 28 | R21: 已对账
A22: 45876 | B22: D&J | C22: SY25287 | D22: =_xlfn.SINGLE(INDEX(样品编号表!Y:Y,_xlfn.SINGLE(MATCH(_xlfn.SINGLE(C:C),样品编号表!H:H,0)))) -> 宝隆纺织 | E22: =_xlfn.SINGLE(INDEX(样品编号表!Z:Z,_xlfn.SINGLE(MATCH(_xlfn.SINGLE(C:C),样品编号表!H:H,0)))) -> 1562 | F22: 51#淡蓝色 | G22: 3 | H22: 米 | I22: 3 | J22: 45877 | K22: 21 | L22: =I22*K22 -> 63 | M22: 微信 | N22: =_xlfn.SINGLE(INDEX(样品编号表!AA:AA,_xlfn.SINGLE(MATCH(_xlfn.SINGLE(C:C),样品编号表!H:H,0)))) -> 6.8 | O22: 12 | P22: =I22*O22 -> 36 | R22: 已对账
A23: 45876 | B23: D&J | C23: SY25287 | D23: =_xlfn.SINGLE(INDEX(样品编号表!Y:Y,_xlfn.SINGLE(MATCH(_xlfn.SINGLE(C:C),样品编号表!H:H,0)))) -> 宝隆纺织 | E23: =_xlfn.SINGLE(INDEX(样品编号表!Z:Z,_xlfn.SINGLE(MATCH(_xlfn.SINGLE(C:C),样品编号表!H:H,0)))) -> 1562 | F23: 53#棕色 | G23: 2 | H23: 米 | I23: 2 | J23: 45881 | K23: 21 | L23: =I23*K23 -> 42 | M23: 微信 | N23: =_xlfn.SINGLE(INDEX(样品编号表!AA:AA,_xlfn.SINGLE(MATCH(_xlfn.SINGLE(C:C),样品编号表!H:H,0)))) -> 6.8 | O23: 12 | P23: =I23*O23 -> 24 | R23: 已对账
A24: 45876 | B24: 圣德 | C24: SY25531 | D24: =_xlfn.SINGLE(INDEX(样品编号表!Y:Y,_xlfn.SINGLE(MATCH(_xlfn.SINGLE(C:C),样品编号表!H:H,0)))) -> 凯盛亨 | E24: =_xlfn.SINGLE(INDEX(样品编号表!Z:Z,_xlfn.SINGLE(MATCH(_xlfn.SINGLE(C:C),样品编号表!H:H,0)))) -> 839# | F24: 43#黄油色 | G24: 2 | H24: 米 | I24: 2 | J24: 45879 | K24: 20 | L24: =I24*K24 -> 40 | M24: 微信 | N24: =_xlfn.SINGLE(INDEX(样品编号表!AA:AA,_xlfn.SINGLE(MATCH(_xlfn.SINGLE(C:C),样品编号表!H:H,0)))) -> 11.3 | O24: 16 | P24: =I24*O24 -> 32 | R24: 已对账
... A40: 45919 | B40: D&J | C40: SY25544 | D40: =_xlfn.SINGLE(INDEX(样品编号表!Y:Y,_xlfn.SINGLE(MATCH(_xlfn.SINGLE(C:C),样品编号表!H:H,0)))) -> 润森 | E40: =_xlfn.SINGLE(INDEX(样品编号表!Z:Z,_xlfn.SINGLE(MATCH(_xlfn.SINGLE(C:C),样品编号表!H:H,0)))) -> 华尔缎 | F40: 98#深绿色 | G40: 8 | H40: 米 | I40: 7 | J40: 45925 | K40: 18 | L40: =I40*K40 -> 126 | M40: 微信 | N40: =_xlfn.SINGLE(INDEX(样品编号表!AA:AA,_xlfn.SINGLE(MATCH(_xlfn.SINGLE(C:C),样品编号表!H:H,0)))) -> 10.5 | O40: 15 | P40: =I40*O40 -> 105 | R40: 已对账
A41: 45919 | B41: D&J | C41: SY25544 | D41: =_xlfn.SINGLE(INDEX(样品编号表!Y:Y,_xlfn.SINGLE(MATCH(_xlfn.SINGLE(C:C),样品编号表!H:H,0)))) -> 润森 | E41: =_xlfn.SINGLE(INDEX(样品编号表!Z:Z,_xlfn.SINGLE(MATCH(_xlfn.SINGLE(C:C),样品编号表!H:H,0)))) -> 华尔缎 | F41: 120#米白 | G41: 3 | H41: 米 | I41: 2 | J41: 45925 | K41: 18 | L41: =I41*K41 -> 36 | M41: 微信 | N41: =_xlfn.SINGLE(INDEX(样品编号表!AA:AA,_xlfn.SINGLE(MATCH(_xlfn.SINGLE(C:C),样品编号表!H:H,0)))) -> 10.5 | O41: 15 | P41: =I41*O41 -> 30 | Q41: 已对账 | R41: 已对账
A42: 45923 | B42: BTC | C42: SP25051 | D42: =_xlfn.SINGLE(INDEX(样品编号表!Y:Y,_xlfn.SINGLE(MATCH(_xlfn.SINGLE(C:C),样品编号表!H:H,0)))) -> 马利布行 | E42: =_xlfn.SINGLE(INDEX(样品编号表!Z:Z,_xlfn.SINGLE(MATCH(_xlfn.SINGLE(C:C),样品编号表!H:H,0)))) -> 10172# | F42: 16#酒红色 | G42: 2 | H42: 米 | I42: 2 | J42: 45926 | K42: 25.7 | L42: =I42*K42 -> 51.4 | M42: 微信 | N42: =_xlfn.SINGLE(INDEX(样品编号表!AA:AA,_xlfn.SINGLE(MATCH(_xlfn.SINGLE(C:C),样品编号表!H:H,0)))) -> 12.2 | O42: 17 | P42: =I42*O42 -> 34 | R42: 已对账
A43: 45923 | B43: BTC | C43: SY25776 | D43: =_xlfn.SINGLE(INDEX(样品编号表!Y:Y,_xlfn.SINGLE(MATCH(_xlfn.SINGLE(C:C),样品编号表!H:H,0)))) -> 新合盛布业 | E43: =_xlfn.SINGLE(INDEX(样品编号表!Z:Z,_xlfn.SINGLE(MATCH(_xlfn.SINGLE(C:C),样品编号表!H:H,0)))) -> 8112 | F43: 米白色 | G43: 14 | H43: 米 | I43: 14 | J43: 45926 | K43: 17 | L43: =I43*K43 -> 238 | M43: 微信 | N43: =_xlfn.SINGLE(INDEX(样品编号表!AA:AA,_xlfn.SINGLE(MATCH(_xlfn.SINGLE(C:C),样品编号表!H:H,0)))) -> 9.6 | O43: 14 | P43: =I43*O43 -> 196 | R43: 已对账
A44: 45923 | B44: BTC | C44: SY25776 | D44: =_xlfn.SINGLE(INDEX(样品编号表!Y:Y,_xlfn.SINGLE(MATCH(_xlfn.SINGLE(C:C),样品编号表!H:H,0)))) -> 新合盛布业 | E44: =_xlfn.SINGLE(INDEX(样品编号表!Z:Z,_xlfn.SINGLE(MATCH(_xlfn.SINGLE(C:C),样品编号表!H:H,0)))) -> 8112 | F44: 2#黑色 | G44: 3 | H44: 米 | I44: 3 | J44: 45926 | K44: 17 | L44: =I44*K44 -> 51 | M44: 微信 | N44: =_xlfn.SINGLE(INDEX(样品编号表!AA:AA,_xlfn.SINGLE(MATCH(_xlfn.SINGLE(C:C),样品编号表!H:H,0)))) -> 9.6 | O44: 14 | P44: =I44*O44 -> 42 | Q44: 已对账 | R44: 已对账
A45: 45925 | B45: 三佰 | C45: SY25419 | D45: =_xlfn.SINGLE(INDEX(样品编号表!Y:Y,_xlfn.SINGLE(MATCH(_xlfn.SINGLE(C:C),样品编号表!H:H,0)))) -> 艺纺 | E45: =_xlfn.SINGLE(INDEX(样品编号表!Z:Z,_xlfn.SINGLE(MATCH(_xlfn.SINGLE(C:C),样品编号表!H:H,0)))) -> 11865-3 | F45: 9#棕色 | G45: 3 | H45: 米 | I45: 3 | J45: 45929 | K45: 25 | L45: =I45*K45 -> 75 | M45: 微信 | N45: =_xlfn.SINGLE(INDEX(样品编号表!AA:AA,_xlfn.SINGLE(MATCH(_xlfn.SINGLE(C:C),样品编号表!H:H,0)))) -> 12.8 | O45: 18 | P45: =I45*O45 -> 54 | R45: 已对账
A46: 45926 | B46: BTC | C46: SY25738 | D46: =_xlfn.SINGLE(INDEX(样品编号表!Y:Y,_xlfn.SINGLE(MATCH(_xlfn.SINGLE(C:C),样品编号表!H:H,0)))) -> 新嘉彩 | E46: =_xlfn.SINGLE(INDEX(样品编号表!Z:Z,_xlfn.SINGLE(MATCH(_xlfn.SINGLE(C:C),样品编号表!H:H,0)))) -> 938 | F46: 2#黑色 | G46: 3 | H46: 米 | I46: 3 | J46: 45926 | K46: 20 | L46: =I46*K46 -> 60 | M46: 微信 | N46: =_xlfn.SINGLE(INDEX(样品编号表!AA:AA,_xlfn.SINGLE(MATCH(_xlfn.SINGLE(C:C),样品编号表!H:H,0)))) -> 8.8 | O46: 15 | P46: =I46*O46 -> 45 | Q46: 已对账 | R46: 已对账
A47: 45926 | B47: BTC | C47: SY25776 | D47: =_xlfn.SINGLE(INDEX(样品编号表!Y:Y,_xlfn.SINGLE(MATCH(_xlfn.SINGLE(C:C),样品编号表!H:H,0)))) -> 新合盛布业 | E47: =_xlfn.SINGLE(INDEX(样品编号表!Z:Z,_xlfn.SINGLE(MATCH(_xlfn.SINGLE(C:C),样品编号表!H:H,0)))) -> 8112 | F47: 2#黑色 | G47: 4 | H47: 米 | I47: 4 | J47: 45926 | K47: 17 | L47: =I47*K47 -> 68 | M47: 微信 | N47: =_xlfn.SINGLE(INDEX(样品编号表!AA:AA,_xlfn.SINGLE(MATCH(_xlfn.SINGLE(C:C),样品编号表!H:H,0)))) -> 9.6 | O47: 14 | P47: =I47*O47 -> 56 | Q47: 已对账 | R47: 已对账
A48: 45930 | B48: D&J | C48: SY25722 | D48: =_xlfn.SINGLE(INDEX(样品编号表!Y:Y,_xlfn.SINGLE(MATCH(_xlfn.SINGLE(C:C),样品编号表!H:H,0)))) -> 锦地印染 | E48: =_xlfn.SINGLE(INDEX(样品编号表!Z:Z,_xlfn.SINGLE(MATCH(_xlfn.SINGLE(C:C),样品编号表!H:H,0)))) -> 10993 | F48: 米白色 | G48: 2 | H48: 米 | I48: 2 | J48: 45937 | K48: 20 | L48: =I48*K48 -> 40 | M48: 微信 | N48: =_xlfn.SINGLE(INDEX(样品编号表!AA:AA,_xlfn.SINGLE(MATCH(_xlfn.SINGLE(C:C),样品编号表!H:H,0)))) -> 8.2 | O48: 14 | P48: =I48*O48 -> 28 | Q48: 已对账 | R48: 已对账
A49: 45930 | B49: 三佰 | C49: SY25722 | D49: =_xlfn.SINGLE(INDEX(样品编号表!Y:Y,_xlfn.SINGLE(MATCH(_xlfn.SINGLE(C:C),样品编号表!H:H,0)))) -> 锦地印染 | E49: =_xlfn.SINGLE(INDEX(样品编号表!Z:Z,_xlfn.SINGLE(MATCH(_xlfn.SINGLE(C:C),样品编号表!H:H,0)))) -> 10993 | F49: 30#黑色 | G49: 1 | H49: 米 | I49: 1 | J49: 45937 | K49: 20 | L49: =I49*K49 -> 20 | M49: 微信 | N49: =_xlfn.SINGLE(INDEX(样品编号表!AA:AA,_xlfn.SINGLE(MATCH(_xlfn.SINGLE(C:C),样品编号表!H:H,0)))) -> 8.2 | O49: 14 | P49: =I49*O49 -> 14 | Q49: 已对账 | R49: 已对账
A50: 45930 | B50: 三佰 | C50: SY25738 | D50: =_xlfn.SINGLE(INDEX(样品编号表!Y:Y,_xlfn.SINGLE(MATCH(_xlfn.SINGLE(C:C),样品编号表!H:H,0)))) -> 新嘉彩 | E50: =_xlfn.SINGLE(INDEX(样品编号表!Z:Z,_xlfn.SINGLE(MATCH(_xlfn.SINGLE(C:C),样品编号表!H:H,0)))) -> 938 | F50: 76# | G50: 3 | H50: 米 | I50: 3 | J50: 45937 | K50: 22 | L50: =I50*K50 -> 66 | M50: 微信 | N50: =_xlfn.SINGLE(INDEX(样品编号表!AA:AA,_xlfn.SINGLE(MATCH(_xlfn.SINGLE(C:C),样品编号表!H:H,0)))) -> 8.8 | O50: 15 | P50: =I50*O50 -> 45 | Q50: 已对账 | R50: 已对账
A51: 45930 | B51: 三佰 | C51: SY25738 | D51: =_xlfn.SINGLE(INDEX(样品编号表!Y:Y,_xlfn.SINGLE(MATCH(_xlfn.SINGLE(C:C),样品编号表!H:H,0)))) -> 新嘉彩 | E51: =_xlfn.SINGLE(INDEX(样品编号表!Z:Z,_xlfn.SINGLE(MATCH(_xlfn.SINGLE(C:C),样品编号表!H:H,0)))) -> 938 | F51: 118# | G51: 3 | H51: 米 | I51: 3 | J51: 45937 | K51: 22 | L51: =I51*K51 -> 66 | M51: 微信 | N51: =_xlfn.SINGLE(INDEX(样品编号表!AA:AA,_xlfn.SINGLE(MATCH(_xlfn.SINGLE(C:C),样品编号表!H:H,0)))) -> 8.8 | O51: 15 | P51: =I51*O51 -> 45 | Q51: 已对账 | R51: 已对账
A52: 45930 | B52: 三佰 | C52: SY25776 | D52: =_xlfn.SINGLE(INDEX(样品编号表!Y:Y,_xlfn.SINGLE(MATCH(_xlfn.SINGLE(C:C),样品编号表!H:H,0)))) -> 新合盛布业 | E52: =_xlfn.SINGLE(INDEX(样品编号表!Z:Z,_xlfn.SINGLE(MATCH(_xlfn.SINGLE(C:C),样品编号表!H:H,0)))) -> 8112 | F52: 2#黑色 | G52: 2 | H52: 米 | I52: 2 | J52: 45937 | K52: 21 | L52: =I52*K52 -> 42 | M52: 微信 | N52: =_xlfn.SINGLE(INDEX(样品编号表!AA:AA,_xlfn.SINGLE(MATCH(_xlfn.SINGLE(C:C),样品编号表!H:H,0)))) -> 9.6 | O52: 14 | P52: =I52*O52 -> 28 | Q52: 已对账 | R52: 已对账
A53: 45933 | B53: 杰登 | C53: SY25544 | D53: =_xlfn.SINGLE(INDEX(样品编号表!Y:Y,_xlfn.SINGLE(MATCH(_xlfn.SINGLE(C:C),样品编号表!H:H,0)))) -> 润森 | E53: =_xlfn.SINGLE(INDEX(样品编号表!Z:Z,_xlfn.SINGLE(MATCH(_xlfn.SINGLE(C:C),样品编号表!H:H,0)))) -> 华尔缎 | F53: 1#白色 | G53: 2 | H53: 米 | I53: 2 | J53: 45937 | K53: 18 | L53: =I53*K53 -> 36 | M53: 支付宝 | N53: =_xlfn.SINGLE(INDEX(样品编号表!AA:AA,_xlfn.SINGLE(MATCH(_xlfn.SINGLE(C:C),样品编号表!H:H,0)))) -> 10.5 | O53: 15 | P53: =I53*O53 -> 30 | Q53: 已对账 | R53: 已对账
A54: 45939 | B54: BTC | C54: SY25776 | D54: =_xlfn.SINGLE(INDEX(样品编号表!Y:Y,_xlfn.SINGLE(MATCH(_xlfn.SINGLE(C:C),样品编号表!H:H,0)))) -> 新合盛布业 | E54: =_xlfn.SINGLE(INDEX(样品编号表!Z:Z,_xlfn.SINGLE(MATCH(_xlfn.SINGLE(C:C),样品编号表!H:H,0)))) -> 8112 | F54: 本白 | G54: 9 | H54: 米 | I54: 9 | J54: 45940 | K54: 17 | L54: =I54*K54 -> 153 | M54: 微信 | N54: =_xlfn.SINGLE(INDEX(样品编号表!AA:AA,_xlfn.SINGLE(MATCH(_xlfn.SINGLE(C:C),样品编号表!H:H,0)))) -> 9.6 | O54: 14 | P54: =I54*O54 -> 126 | R54: 已对账
A55: 45939 | B55: 万泰 | C55: SY25824 | D55: =_xlfn.SINGLE(INDEX(样品编号表!Y:Y,_xlfn.SINGLE(MATCH(_xlfn.SINGLE(C:C),样品编号表!H:H,0)))) -> 合泰隆纺织 | E55: =_xlfn.SINGLE(INDEX(样品编号表!Z:Z,_xlfn.SINGLE(MATCH(_xlfn.SINGLE(C:C),样品编号表!H:H,0)))) -> T985 | F55: 21#藏青&白色 | G55: 6 | H55: 米 | I55: 6 | J55: 45940 | K55: 24 | L55: =I55*K55 -> 144 | M55: 微信 | N55: =_xlfn.SINGLE(INDEX(样品编号表!AA:AA,_xlfn.SINGLE(MATCH(_xlfn.SINGLE(C:C),样品编号表!H:H,0)))) -> 10.8 | O55: 18 | P55: =I55*O55 -> 108 | Q55: 布小帮 | R55: 已对账
A56: 45939 | B56: 万泰 | C56: SY25827 | D56: =_xlfn.SINGLE(INDEX(样品编号表!Y:Y,_xlfn.SINGLE(MATCH(_xlfn.SINGLE(C:C),样品编号表!H:H,0)))) -> 万利行 | E56: =_xlfn.SINGLE(INDEX(样品编号表!Z:Z,_xlfn.SINGLE(MATCH(_xlfn.SINGLE(C:C),样品编号表!H:H,0)))) -> 521-2# | F56: 1#黑色 | G56: 3 | H56: 米 | I56: 3 | J56: 45940 | K56: 20.1 | L56: =I56*K56 -> 60.3 | M56: 微信 | N56: =_xlfn.SINGLE(INDEX(样品编号表!AA:AA,_xlfn.SINGLE(MATCH(_xlfn.SINGLE(C:C),样品编号表!H:H,0)))) -> 10.5 | O56: 15 | P56: =I56*O56 -> 45 | R56: 已对账
A57: 45944 | B57: D&J | C57: SY25287 | D57: =_xlfn.SINGLE(INDEX(样品编号表!Y:Y,_xlfn.SINGLE(MATCH(_xlfn.SINGLE(C:C),样品编号表!H:H,0)))) -> 宝隆纺织 | E57: =_xlfn.SINGLE(INDEX(样品编号表!Z:Z,_xlfn.SINGLE(MATCH(_xlfn.SINGLE(C:C),样品编号表!H:H,0)))) -> 1562 | F57: 51#淡蓝色 | G57: 3 | H57: 米 | I57: 3 | J57: 45945 | K57: 21 | L57: =I57*K57 -> 63 | M57: 微信 | N57: =_xlfn.SINGLE(INDEX(样品编号表!AA:AA,_xlfn.SINGLE(MATCH(_xlfn.SINGLE(C:C),样品编号表!H:H,0)))) -> 6.8 | O57: 13 | P57: =I57*O57 -> 39 | R57: 已对账
A58: 45944 | B58: BTC | C58: SY25419 | D58: =_xlfn.SINGLE(INDEX(样品编号表!Y:Y,_xlfn.SINGLE(MATCH(_xlfn.SINGLE(C:C),样品编号表!H:H,0)))) -> 艺纺 | E58: =_xlfn.SINGLE(INDEX(样品编号表!Z:Z,_xlfn.SINGLE(MATCH(_xlfn.SINGLE(C:C),样品编号表!H:H,0)))) -> 11865-3 | F58: 米白色 | G58: 4 | H58: 米 | I58: 4 | J58: 45946 | K58: 25 | L58: =I58*K58 -> 100 | M58: 微信 | N58: =_xlfn.SINGLE(INDEX(样品编号表!AA:AA,_xlfn.SINGLE(MATCH(_xlfn.SINGLE(C:C),样品编号表!H:H,0)))) -> 12.8 | O58: 18 | P58: =I58*O58 -> 72 | R58: 已对账
A59: 45944 | B59: 三佰 | C59: SY25531 | D59: =_xlfn.SINGLE(INDEX(样品编号表!Y:Y,_xlfn.SINGLE(MATCH(_xlfn.SINGLE(C:C),样品编号表!H:H,0)))) -> 凯盛亨 | E59: =_xlfn.SINGLE(INDEX(样品编号表!Z:Z,_xlfn.SINGLE(MATCH(_xlfn.SINGLE(C:C),样品编号表!H:H,0)))) -> 839# | F59: 巧克力野花 | G59: 5 | H59: 米 | I59: 5 | J59: 45945 | K59: 37 | L59: =I59*K59 -> 185 | M59: 微信 | N59: =_xlfn.SINGLE(INDEX(样品编号表!AA:AA,_xlfn.SINGLE(MATCH(_xlfn.SINGLE(C:C),样品编号表!H:H,0)))) -> 11.3 | O59: 19.9 | P59: =I59*O59 -> 99.5 | Q59: 顺亚印花 | R59: 已对账
A60: 45945 | B60: BTC | C60: SY251062 | D60: =_xlfn.SINGLE(INDEX(样品编号表!Y:Y,_xlfn.SINGLE(MATCH(_xlfn.SINGLE(C:C),样品编号表!H:H,0)))) -> 万顺纺织 | E60: =_xlfn.SINGLE(INDEX(样品编号表!Z:Z,_xlfn.SINGLE(MATCH(_xlfn.SINGLE(C:C),样品编号表!H:H,0)))) -> A8784 | F60: 黑色 | G60: 4 | H60: 米 | I60: 4 | J60: 45946 | K60: 21 | L60: =I60*K60 -> 84 | M60: 微信 | N60: =_xlfn.SINGLE(INDEX(样品编号表!AA:AA,_xlfn.SINGLE(MATCH(_xlfn.SINGLE(C:C),样品编号表!H:H,0)))) -> 8.8 | O60: 14 | P60: =I60*O60 -> 56 | R60: 已对账
A61: 45945 | B61: BTC | C61: SY251062 | D61: =_xlfn.SINGLE(INDEX(样品编号表!Y:Y,_xlfn.SINGLE(MATCH(_xlfn.SINGLE(C:C),样品编号表!H:H,0)))) -> 万顺纺织 | E61: =_xlfn.SINGLE(INDEX(样品编号表!Z:Z,_xlfn.SINGLE(MATCH(_xlfn.SINGLE(C:C),样品编号表!H:H,0)))) -> A8784 | F61: 褐色 | G61: 5 | H61: 米 | I61: 5 | J61: 45946 | K61: 21 | L61: =I61*K61 -> 105 | M61: 微信 | N61: =_xlfn.SINGLE(INDEX(样品编号表!AA:AA,_xlfn.SINGLE(MATCH(_xlfn.SINGLE(C:C),样品编号表!H:H,0)))) -> 8.8 | O61: 14 | P61: =I61*O61 -> 70 | R61: 已对账
A62: 45946 | B62: 三佰 | C62: SP25088 | D62: =_xlfn.SINGLE(INDEX(样品编号表!Y:Y,_xlfn.SINGLE(MATCH(_xlfn.SINGLE(C:C),样品编号表!H:H,0)))) -> 联众 | E62: =_xlfn.SINGLE(INDEX(样品编号表!Z:Z,_xlfn.SINGLE(MATCH(_xlfn.SINGLE(C:C),样品编号表!H:H,0)))) -> A8207 | F62: 黑色 | G62: 8 | H62: 米 | I62: 8 | J62: 45947 | K62: 32 | L62: =I62*K62 -> 256 | M62: 微信 | N62: =_xlfn.SINGLE(INDEX(样品编号表!AA:AA,_xlfn.SINGLE(MATCH(_xlfn.SINGLE(C:C),样品编号表!H:H,0)))) -> 48 | O62: 25 | P62: =I62*O62 -> 200 | R62: 已对账
A63: 45946 | B63: 扑喜 | C63: SY25738 | D63: =_xlfn.SINGLE(INDEX(样品编号表!Y:Y,_xlfn.SINGLE(MATCH(_xlfn.SINGLE(C:C),样品编号表!H:H,0)))) -> 新嘉彩 | E63: =_xlfn.SINGLE(INDEX(样品编号表!Z:Z,_xlfn.SINGLE(MATCH(_xlfn.SINGLE(C:C),样品编号表!H:H,0)))) -> 938 | F63: 白色 | G63: 5 | H63: 米 | I63: 5 | J63: 45947 | K63: 20 | L63: =I63*K63 -> 100 | M63: 微信 | N63: =_xlfn.SINGLE(INDEX(样品编号表!AA:AA,_xlfn.SINGLE(MATCH(_xlfn.SINGLE(C:C),样品编号表!H:H,0)))) -> 8.8 | O63: 15 | P63: =I63*O63 -> 75 | R63: 已对账
A64: 45947 | B64: D&J | C64: SP25028 | D64: =_xlfn.SINGLE(INDEX(样品编号表!Y:Y,_xlfn.SINGLE(MATCH(_xlfn.SINGLE(C:C),样品编号表!H:H,0)))) -> 新合盛布业 | E64: =_xlfn.SINGLE(INDEX(样品编号表!Z:Z,_xlfn.SINGLE(MATCH(_xlfn.SINGLE(C:C),样品编号表!H:H,0)))) -> 6002 | F64: V字型印花 | G64: 6 | H64: 米 | I64: 6 | J64: 45951 | K64: 24 | L64: =I64*K64 -> 144 | M64: 微信 | N64: =_xlfn.SINGLE(INDEX(样品编号表!AA:AA,_xlfn.SINGLE(MATCH(_xlfn.SINGLE(C:C),样品编号表!H:H,0)))) -> 6.6 | O64: 18 | P64: =I64*O64 -> 108 | R64: 已对账
A65: 45947 | B65: BTC | C65: SY251062 | D65: =_xlfn.SINGLE(INDEX(样品编号表!Y:Y,_xlfn.SINGLE(MATCH(_xlfn.SINGLE(C:C),样品编号表!H:H,0)))) -> 万顺纺织 | E65: =_xlfn.SINGLE(INDEX(样品编号表!Z:Z,_xlfn.SINGLE(MATCH(_xlfn.SINGLE(C:C),样品编号表!H:H,0)))) -> A8784 | F65: 本白 | G65: 1 | H65: 米 | I65: 1 | J65: 45950 | K65: 22 | L65: =I65*K65 -> 22 | M65: 微信 | N65: =_xlfn.SINGLE(INDEX(样品编号表!AA:AA,_xlfn.SINGLE(MATCH(_xlfn.SINGLE(C:C),样品编号表!H:H,0)))) -> 8.8 | O65: 14 | P65: =I65*O65 -> 14 | R65: 已对账
A66: 45947 | B66: 扑喜 | C66: SY25419 | D66: =_xlfn.SINGLE(INDEX(样品编号表!Y:Y,_xlfn.SINGLE(MATCH(_xlfn.SINGLE(C:C),样品编号表!H:H,0)))) -> 艺纺 | E66: =_xlfn.SINGLE(INDEX(样品编号表!Z:Z,_xlfn.SINGLE(MATCH(_xlfn.SINGLE(C:C),样品编号表!H:H,0)))) -> 11865-3 | F66: 杏色 | G66: 4 | H66: 米 | I66: 4 | J66: 45950 | K66: 25 | L66: =I66*K66 -> 100 | M66: 微信 | N66: =_xlfn.SINGLE(INDEX(样品编号表!AA:AA,_xlfn.SINGLE(MATCH(_xlfn.SINGLE(C:C),样品编号表!H:H,0)))) -> 12.8 | O66: 18 | P66: =I66*O66 -> 72 | R66: 已对账
A67: 45947 | B67: 万泰 | C67: SY25733 | D67: =_xlfn.SINGLE(INDEX(样品编号表!Y:Y,_xlfn.SINGLE(MATCH(_xlfn.SINGLE(C:C),样品编号表!H:H,0)))) -> 锦地印染 | E67: =_xlfn.SINGLE(INDEX(样品编号表!Z:Z,_xlfn.SINGLE(MATCH(_xlfn.SINGLE(C:C),样品编号表!H:H,0)))) -> 醋酸金銮缎 | F67: 1#米白色 | G67: 5 | H67: 米 | I67: 5 | J67: 45950 | K67: 22 | L67: =I67*K67 -> 110 | M67: 微信 | N67: =_xlfn.SINGLE(INDEX(样品编号表!AA:AA,_xlfn.SINGLE(MATCH(_xlfn.SINGLE(C:C),样品编号表!H:H,0)))) -> 9 | O67: 15 | P67: =I67*O67 -> 75 | R67: 已对账
A68: 45948 | B68: 万泰 | C68: SY25977 | D68: =_xlfn.SINGLE(INDEX(样品编号表!Y:Y,_xlfn.SINGLE(MATCH(_xlfn.SINGLE(C:C),样品编号表!H:H,0)))) -> 健润纺织 | E68: =_xlfn.SINGLE(INDEX(样品编号表!Z:Z,_xlfn.SINGLE(MATCH(_xlfn.SINGLE(C:C),样品编号表!H:H,0)))) -> 逸柔3*2罗纹-RS | F68: 16#灰色 | G68: 2 | H68: 米 | I68: 2 | J68: 45951 | K68: 18 | L68: =I68*K68 -> 36 | M68: 微信 | N68: =_xlfn.SINGLE(INDEX(样品编号表!AA:AA,_xlfn.SINGLE(MATCH(_xlfn.SINGLE(C:C),样品编号表!H:H,0)))) -> 42 | O68: 30 | P68: =I68*O68 -> 60 | R68: 已对账
A69: 45948 | B69: 万泰 | C69: SY25977 | D69: =_xlfn.SINGLE(INDEX(样品编号表!Y:Y,_xlfn.SINGLE(MATCH(_xlfn.SINGLE(C:C),样品编号表!H:H,0)))) -> 健润纺织 | E69: =_xlfn.SINGLE(INDEX(样品编号表!Z:Z,_xlfn.SINGLE(MATCH(_xlfn.SINGLE(C:C),样品编号表!H:H,0)))) -> 逸柔3*2罗纹-RS | F69: 5#米白 | G69: 2 | H69: 米 | I69: 2 | J69: 45950 | K69: 18 | L69: =I69*K69 -> 36 | M69: 微信 | N69: =_xlfn.SINGLE(INDEX(样品编号表!AA:AA,_xlfn.SINGLE(MATCH(_xlfn.SINGLE(C:C),样品编号表!H:H,0)))) -> 42 | O69: 30 | P69: =I69*O69 -> 60 | R69: 已对账
A70: 45948 | B70: 万泰 | C70: SY25977 | D70: =_xlfn.SINGLE(INDEX(样品编号表!Y:Y,_xlfn.SINGLE(MATCH(_xlfn.SINGLE(C:C),样品编号表!H:H,0)))) -> 健润纺织 | E70: =_xlfn.SINGLE(INDEX(样品编号表!Z:Z,_xlfn.SINGLE(MATCH(_xlfn.SINGLE(C:C),样品编号表!H:H,0)))) -> 逸柔3*2罗纹-RS | F70: 22#白色 | G70: 2 | H70: 米 | I70: 2 | J70: 45950 | K70: 18 | L70: =I70*K70 -> 36 | M70: 微信 | N70: =_xlfn.SINGLE(INDEX(样品编号表!AA:AA,_xlfn.SINGLE(MATCH(_xlfn.SINGLE(C:C),样品编号表!H:H,0)))) -> 42 | O70: 30 | P70: =I70*O70 -> 60 | R70: 已对账
A71: 45951 | B71: D&J | C71: SY25544 | D71: =_xlfn.SINGLE(INDEX(样品编号表!Y:Y,_xlfn.SINGLE(MATCH(_xlfn.SINGLE(C:C),样品编号表!H:H,0)))) -> 润森 | E71: =_xlfn.SINGLE(INDEX(样品编号表!Z:Z,_xlfn.SINGLE(MATCH(_xlfn.SINGLE(C:C),样品编号表!H:H,0)))) -> 华尔缎 | F71: 81#朱古力色 | G71: 6 | H71: 米 | I71: 6 | J71: 45952 | K71: 18 | L71: =I71*K71 -> 108 | M71: 微信 | N71: =_xlfn.SINGLE(INDEX(样品编号表!AA:AA,_xlfn.SINGLE(MATCH(_xlfn.SINGLE(C:C),样品编号表!H:H,0)))) -> 10.5 | O71: 15 | P71: =I71*O71 -> 90 | R71: 已对账
... A101: 45964 | B101: BTC | C101: SY251062 | D101: =_xlfn.SINGLE(INDEX(样品编号表!Y:Y,_xlfn.SINGLE(MATCH(_xlfn.SINGLE(C:C),样品编号表!H:H,0)))) -> 万顺纺织 | E101: =_xlfn.SINGLE(INDEX(样品编号表!Z:Z,_xlfn.SINGLE(MATCH(_xlfn.SINGLE(C:C),样品编号表!H:H,0)))) -> A8784 | F101: 48#深蓝色 | G101: 7 | H101: 米 | I101: 7 | J101: 45966 | K101: 21 | L101: =I101*K101 -> 147 | M101: 微信 | N101: =_xlfn.SINGLE(INDEX(样品编号表!AA:AA,_xlfn.SINGLE(MATCH(_xlfn.SINGLE(C:C),样品编号表!H:H,0)))) -> 8.8 | O101: 14 | P101: =I101*O101 -> 98 | R101: 已对账
A102: 45964 | B102: BTC | C102: SY251062 | D102: =_xlfn.SINGLE(INDEX(样品编号表!Y:Y,_xlfn.SINGLE(MATCH(_xlfn.SINGLE(C:C),样品编号表!H:H,0)))) -> 万顺纺织 | E102: =_xlfn.SINGLE(INDEX(样品编号表!Z:Z,_xlfn.SINGLE(MATCH(_xlfn.SINGLE(C:C),样品编号表!H:H,0)))) -> A8784 | F102: 51#绿色 | G102: 19 | I102: 19 | J102: 45966 | K102: 21 | L102: =I102*K102 -> 399 | M102: 微信 | N102: =_xlfn.SINGLE(INDEX(样品编号表!AA:AA,_xlfn.SINGLE(MATCH(_xlfn.SINGLE(C:C),样品编号表!H:H,0)))) -> 8.8 | O102: 14 | P102: =I102*O102 -> 266 | R102: 已对账
A103: 45964 | B103: BTC | C103: SY25419 | D103: =_xlfn.SINGLE(INDEX(样品编号表!Y:Y,_xlfn.SINGLE(MATCH(_xlfn.SINGLE(C:C),样品编号表!H:H,0)))) -> 艺纺 | E103: =_xlfn.SINGLE(INDEX(样品编号表!Z:Z,_xlfn.SINGLE(MATCH(_xlfn.SINGLE(C:C),样品编号表!H:H,0)))) -> 11865-3 | F103: 黑色 | G103: 4 | H103: 米 | I103: 4 | J103: 45966 | K103: 25 | L103: =I103*K103 -> 100 | M103: 微信 | N103: =_xlfn.SINGLE(INDEX(样品编号表!AA:AA,_xlfn.SINGLE(MATCH(_xlfn.SINGLE(C:C),样品编号表!H:H,0)))) -> 12.8 | O103: 18 | P103: =I103*O103 -> 72 | R103: 已对账
A104: 45965 | B104: D&J | C104: SY25016 | D104: =_xlfn.SINGLE(INDEX(样品编号表!Y:Y,_xlfn.SINGLE(MATCH(_xlfn.SINGLE(C:C),样品编号表!H:H,0)))) -> 光大纺织 | E104: =_xlfn.SINGLE(INDEX(样品编号表!Z:Z,_xlfn.SINGLE(MATCH(_xlfn.SINGLE(C:C),样品编号表!H:H,0)))) -> C580 | F104: 白色 | G104: 1 | H104: 米 | I104: 1 | J104: 45966 | N104: =_xlfn.SINGLE(INDEX(样品编号表!AA:AA,_xlfn.SINGLE(MATCH(_xlfn.SINGLE(C:C),样品编号表!H:H,0)))) -> 9.8 | O104: 15 | P104: =I104*O104 -> 15 | Q104: 版布数量不够，补货 | R104: 已对账
A105: 45965 | B105: 锦兰 | C105: SP25028 | D105: =_xlfn.SINGLE(INDEX(样品编号表!Y:Y,_xlfn.SINGLE(MATCH(_xlfn.SINGLE(C:C),样品编号表!H:H,0)))) -> 新合盛布业 | E105: =_xlfn.SINGLE(INDEX(样品编号表!Z:Z,_xlfn.SINGLE(MATCH(_xlfn.SINGLE(C:C),样品编号表!H:H,0)))) -> 6002 | F105: 1#白色 | G105: 3 | H105: 米 | I105: 3 | J105: 45966 | K105: 18 | L105: =I105*K105 -> 54 | M105: 微信 | N105: =_xlfn.SINGLE(INDEX(样品编号表!AA:AA,_xlfn.SINGLE(MATCH(_xlfn.SINGLE(C:C),样品编号表!H:H,0)))) -> 6.6 | O105: 12 | P105: =I105*O105 -> 36 | R105: 已对账
A106: 45965 | B106: 锦兰 | C106: SP25028 | D106: =_xlfn.SINGLE(INDEX(样品编号表!Y:Y,_xlfn.SINGLE(MATCH(_xlfn.SINGLE(C:C),样品编号表!H:H,0)))) -> 新合盛布业 | E106: =_xlfn.SINGLE(INDEX(样品编号表!Z:Z,_xlfn.SINGLE(MATCH(_xlfn.SINGLE(C:C),样品编号表!H:H,0)))) -> 6002 | F106: 33# | G106: 1 | H106: 米 | I106: 1 | J106: 45966 | K106: 18 | L106: =I106*K106 -> 18 | M106: 微信 | N106: =_xlfn.SINGLE(INDEX(样品编号表!AA:AA,_xlfn.SINGLE(MATCH(_xlfn.SINGLE(C:C),样品编号表!H:H,0)))) -> 6.6 | O106: 12 | P106: =I106*O106 -> 12 | R106: 已对账
A107: 45965 | B107: 锦兰 | C107: SP25028 | D107: =_xlfn.SINGLE(INDEX(样品编号表!Y:Y,_xlfn.SINGLE(MATCH(_xlfn.SINGLE(C:C),样品编号表!H:H,0)))) -> 新合盛布业 | E107: =_xlfn.SINGLE(INDEX(样品编号表!Z:Z,_xlfn.SINGLE(MATCH(_xlfn.SINGLE(C:C),样品编号表!H:H,0)))) -> 6002 | F107: 72# | G107: 2 | H107: 米 | I107: 2 | J107: 45966 | K107: 18 | L107: =I107*K107 -> 36 | M107: 微信 | N107: =_xlfn.SINGLE(INDEX(样品编号表!AA:AA,_xlfn.SINGLE(MATCH(_xlfn.SINGLE(C:C),样品编号表!H:H,0)))) -> 6.6 | O107: 12 | P107: =I107*O107 -> 24 | R107: 已对账
A108: 45965 | B108: 万泰 | C108: SY25419 | D108: =_xlfn.SINGLE(INDEX(样品编号表!Y:Y,_xlfn.SINGLE(MATCH(_xlfn.SINGLE(C:C),样品编号表!H:H,0)))) -> 艺纺 | E108: =_xlfn.SINGLE(INDEX(样品编号表!Z:Z,_xlfn.SINGLE(MATCH(_xlfn.SINGLE(C:C),样品编号表!H:H,0)))) -> 11865-3 | F108: 黑色 | G108: 1 | I108: 1 | J108: 45966 | K108: 25 | L108: =I108*K108 -> 25 | M108: 微信 | N108: =_xlfn.SINGLE(INDEX(样品编号表!AA:AA,_xlfn.SINGLE(MATCH(_xlfn.SINGLE(C:C),样品编号表!H:H,0)))) -> 12.8 | O108: 18 | P108: =I108*O108 -> 18 | R108: 已对账
A109: 45966 | B109: BTC | C109: SY251062 | D109: =_xlfn.SINGLE(INDEX(样品编号表!Y:Y,_xlfn.SINGLE(MATCH(_xlfn.SINGLE(C:C),样品编号表!H:H,0)))) -> 万顺纺织 | E109: =_xlfn.SINGLE(INDEX(样品编号表!Z:Z,_xlfn.SINGLE(MATCH(_xlfn.SINGLE(C:C),样品编号表!H:H,0)))) -> A8784 | F109: 黑色 | G109: 12 | H109: 米 | I109: 12 | J109: 45968 | K109: 21 | L109: =I109*K109 -> 252 | M109: 微信 | N109: =_xlfn.SINGLE(INDEX(样品编号表!AA:AA,_xlfn.SINGLE(MATCH(_xlfn.SINGLE(C:C),样品编号表!H:H,0)))) -> 8.8 | O109: 14 | P109: =I109*O109 -> 168 | R109: 已对账
A110: 45966 | B110: BTC | C110: SY251429 | D110: =_xlfn.SINGLE(INDEX(样品编号表!Y:Y,_xlfn.SINGLE(MATCH(_xlfn.SINGLE(C:C),样品编号表!H:H,0)))) -> 粤信布业 | E110: =_xlfn.SINGLE(INDEX(样品编号表!Z:Z,_xlfn.SINGLE(MATCH(_xlfn.SINGLE(C:C),样品编号表!H:H,0)))) -> 32支精棉拉架YX81010 | F110: 6#红色/白条纹 | G110: 4 | H110: 米 | I110: 4 | J110: 45968 | K110: 26 | L110: =I110*K110 -> 104 | M110: 微信 | N110: =_xlfn.SINGLE(INDEX(样品编号表!AA:AA,_xlfn.SINGLE(MATCH(_xlfn.SINGLE(C:C),样品编号表!H:H,0)))) -> 44 | O110: 30 | P110: =I110*O110 -> 120 | R110: 已对账
A111: 45966 | B111: BTC | C111: SY251429 | D111: =_xlfn.SINGLE(INDEX(样品编号表!Y:Y,_xlfn.SINGLE(MATCH(_xlfn.SINGLE(C:C),样品编号表!H:H,0)))) -> 粤信布业 | E111: =_xlfn.SINGLE(INDEX(样品编号表!Z:Z,_xlfn.SINGLE(MATCH(_xlfn.SINGLE(C:C),样品编号表!H:H,0)))) -> 32支精棉拉架YX81010 | F111: 17#蓝色/白条纹 | G111: 8 | H111: 米 | I111: 8 | J111: 45968 | K111: 26 | L111: =I111*K111 -> 208 | M111: 微信 | N111: =_xlfn.SINGLE(INDEX(样品编号表!AA:AA,_xlfn.SINGLE(MATCH(_xlfn.SINGLE(C:C),样品编号表!H:H,0)))) -> 44 | O111: 30 | P111: =I111*O111 -> 240 | R111: 已对账
A112: 45966 | B112: BTC | C112: SY251429 | D112: =_xlfn.SINGLE(INDEX(样品编号表!Y:Y,_xlfn.SINGLE(MATCH(_xlfn.SINGLE(C:C),样品编号表!H:H,0)))) -> 粤信布业 | E112: =_xlfn.SINGLE(INDEX(样品编号表!Z:Z,_xlfn.SINGLE(MATCH(_xlfn.SINGLE(C:C),样品编号表!H:H,0)))) -> 32支精棉拉架YX81010 | F112: 13#褐色/白条纹 | G112: 7 | H112: 米 | I112: 7 | J112: 45968 | K112: 26 | L112: =I112*K112 -> 182 | M112: 微信 | N112: =_xlfn.SINGLE(INDEX(样品编号表!AA:AA,_xlfn.SINGLE(MATCH(_xlfn.SINGLE(C:C),样品编号表!H:H,0)))) -> 44 | O112: 30 | P112: =I112*O112 -> 210 | R112: 已对账
A113: 45967 | B113: D&J | C113: SY25287 | D113: =_xlfn.SINGLE(INDEX(样品编号表!Y:Y,_xlfn.SINGLE(MATCH(_xlfn.SINGLE(C:C),样品编号表!H:H,0)))) -> 宝隆纺织 | E113: =_xlfn.SINGLE(INDEX(样品编号表!Z:Z,_xlfn.SINGLE(MATCH(_xlfn.SINGLE(C:C),样品编号表!H:H,0)))) -> 1562 | F113: 米白色 | G113: 3 | H113: 米 | I113: 3 | J113: 45968 | K113: 21 | L113: =I113*K113 -> 63 | M113: 微信 | N113: =_xlfn.SINGLE(INDEX(样品编号表!AA:AA,_xlfn.SINGLE(MATCH(_xlfn.SINGLE(C:C),样品编号表!H:H,0)))) -> 6.8 | O113: 12 | P113: =I113*O113 -> 36 | R113: 已对账
A114: 45969 | B114: D&J | C114: SP25028 | D114: =_xlfn.SINGLE(INDEX(样品编号表!Y:Y,_xlfn.SINGLE(MATCH(_xlfn.SINGLE(C:C),样品编号表!H:H,0)))) -> 新合盛布业 | E114: =_xlfn.SINGLE(INDEX(样品编号表!Z:Z,_xlfn.SINGLE(MATCH(_xlfn.SINGLE(C:C),样品编号表!H:H,0)))) -> 6002 | F114: V字型印花 | G114: 6 | H114: 米 | I114: 6 | J114: 45973 | K114: 24 | L114: =I114*K114 -> 144 | M114: 微信 | N114: 18 | O114: 18 | P114: =I114*O114 -> 108 | R114: 已对账
A115: 45969 | B115: D&J | C115: SP25028 | D115: =_xlfn.SINGLE(INDEX(样品编号表!Y:Y,_xlfn.SINGLE(MATCH(_xlfn.SINGLE(C:C),样品编号表!H:H,0)))) -> 新合盛布业 | E115: =_xlfn.SINGLE(INDEX(样品编号表!Z:Z,_xlfn.SINGLE(MATCH(_xlfn.SINGLE(C:C),样品编号表!H:H,0)))) -> 6002 | F115: 黑色 | G115: 2 | H115: 米 | I115: 2 | J115: 45972 | K115: 18 | L115: =I115*K115 -> 36 | M115: 微信 | N115: =_xlfn.SINGLE(INDEX(样品编号表!AA:AA,_xlfn.SINGLE(MATCH(_xlfn.SINGLE(C:C),样品编号表!H:H,0)))) -> 6.6 | O115: 12 | P115: =I115*O115 -> 24 | R115: 已对账
A116: 45972 | B116: 妮裳 | C116: SY25419 | D116: =_xlfn.SINGLE(INDEX(样品编号表!Y:Y,_xlfn.SINGLE(MATCH(_xlfn.SINGLE(C:C),样品编号表!H:H,0)))) -> 艺纺 | E116: =_xlfn.SINGLE(INDEX(样品编号表!Z:Z,_xlfn.SINGLE(MATCH(_xlfn.SINGLE(C:C),样品编号表!H:H,0)))) -> 11865-3 | F116: 黑色 | G116: 2 | H116: 米 | I116: 2 | J116: 45974 | K116: 25 | L116: =I116*K116 -> 50 | M116: 微信 | N116: =_xlfn.SINGLE(INDEX(样品编号表!AA:AA,_xlfn.SINGLE(MATCH(_xlfn.SINGLE(C:C),样品编号表!H:H,0)))) -> 12.8 | O116: 18 | P116: =I116*O116 -> 36 | R116: 已对账
A117: 45972 | B117: 妮裳 | C117: SY25419 | D117: =_xlfn.SINGLE(INDEX(样品编号表!Y:Y,_xlfn.SINGLE(MATCH(_xlfn.SINGLE(C:C),样品编号表!H:H,0)))) -> 艺纺 | E117: =_xlfn.SINGLE(INDEX(样品编号表!Z:Z,_xlfn.SINGLE(MATCH(_xlfn.SINGLE(C:C),样品编号表!H:H,0)))) -> 11865-3 | F117: 深棕色 | G117: 3 | H117: 米 | I117: 3 | J117: 45974 | K117: 25 | L117: =I117*K117 -> 75 | M117: 微信 | N117: =_xlfn.SINGLE(INDEX(样品编号表!AA:AA,_xlfn.SINGLE(MATCH(_xlfn.SINGLE(C:C),样品编号表!H:H,0)))) -> 12.8 | O117: 18 | P117: =I117*O117 -> 54 | R117: 已对账
A118: 45972 | B118: 妮裳 | C118: SY25419 | D118: =_xlfn.SINGLE(INDEX(样品编号表!Y:Y,_xlfn.SINGLE(MATCH(_xlfn.SINGLE(C:C),样品编号表!H:H,0)))) -> 艺纺 | E118: =_xlfn.SINGLE(INDEX(样品编号表!Z:Z,_xlfn.SINGLE(MATCH(_xlfn.SINGLE(C:C),样品编号表!H:H,0)))) -> 11865-3 | F118: 黑色 | G118: 3 | H118: 米 | I118: 3 | J118: 45974 | K118: 25 | L118: =I118*K118 -> 75 | M118: 微信 | N118: =_xlfn.SINGLE(INDEX(样品编号表!AA:AA,_xlfn.SINGLE(MATCH(_xlfn.SINGLE(C:C),样品编号表!H:H,0)))) -> 12.8 | O118: 18 | P118: =I118*O118 -> 54 | R118: 已对账
A119: 45972 | B119: 扑喜 | C119: SY25544 | D119: =_xlfn.SINGLE(INDEX(样品编号表!Y:Y,_xlfn.SINGLE(MATCH(_xlfn.SINGLE(C:C),样品编号表!H:H,0)))) -> 润森 | E119: =_xlfn.SINGLE(INDEX(样品编号表!Z:Z,_xlfn.SINGLE(MATCH(_xlfn.SINGLE(C:C),样品编号表!H:H,0)))) -> 华尔缎 | F119: 98#深绿色 | G119: 2 | H119: 米 | I119: 2 | J119: 45974 | K119: 18 | L119: =I119*K119 -> 36 | M119: 微信 | N119: =_xlfn.SINGLE(INDEX(样品编号表!AA:AA,_xlfn.SINGLE(MATCH(_xlfn.SINGLE(C:C),样品编号表!H:H,0)))) -> 10.5 | O119: 15 | P119: =I119*O119 -> 30 | R119: 已对账
A120: 45973 | B120: D&J | C120: SP25050 | D120: =_xlfn.SINGLE(INDEX(样品编号表!Y:Y,_xlfn.SINGLE(MATCH(_xlfn.SINGLE(C:C),样品编号表!H:H,0)))) -> 光大纺织 | E120: =_xlfn.SINGLE(INDEX(样品编号表!Z:Z,_xlfn.SINGLE(MATCH(_xlfn.SINGLE(C:C),样品编号表!H:H,0)))) -> TR439 | F120: 30#蓝色 | G120: 3 | H120: 米 | I120: 3 | J120: 45975 | K120: 26 | L120: =I120*K120 -> 78 | M120: 微信 | N120: =_xlfn.SINGLE(INDEX(样品编号表!AA:AA,_xlfn.SINGLE(MATCH(_xlfn.SINGLE(C:C),样品编号表!H:H,0)))) -> 12.3 | O120: 17 | P120: =I120*O120 -> 51 | R120: 已对账
A121: 45973 | B121: D&J | C121: SP25050 | D121: =_xlfn.SINGLE(INDEX(样品编号表!Y:Y,_xlfn.SINGLE(MATCH(_xlfn.SINGLE(C:C),样品编号表!H:H,0)))) -> 光大纺织 | E121: =_xlfn.SINGLE(INDEX(样品编号表!Z:Z,_xlfn.SINGLE(MATCH(_xlfn.SINGLE(C:C),样品编号表!H:H,0)))) -> TR439 | F121: 2#米白色 | G121: 2 | H121: 米 | I121: 2 | J121: 45975 | K121: 26 | L121: =I121*K121 -> 52 | M121: 微信 | N121: =_xlfn.SINGLE(INDEX(样品编号表!AA:AA,_xlfn.SINGLE(MATCH(_xlfn.SINGLE(C:C),样品编号表!H:H,0)))) -> 12.3 | O121: 17 | P121: =I121*O121 -> 34 | R121: 已对账
A122: 45973 | B122: D&J | C122: SP25050 | D122: =_xlfn.SINGLE(INDEX(样品编号表!Y:Y,_xlfn.SINGLE(MATCH(_xlfn.SINGLE(C:C),样品编号表!H:H,0)))) -> 光大纺织 | E122: =_xlfn.SINGLE(INDEX(样品编号表!Z:Z,_xlfn.SINGLE(MATCH(_xlfn.SINGLE(C:C),样品编号表!H:H,0)))) -> TR439 | F122: 121#灰色 | G122: 1 | H122: 米 | I122: 1 | J122: 45975 | K122: 26 | L122: =I122*K122 -> 26 | M122: 微信 | N122: =_xlfn.SINGLE(INDEX(样品编号表!AA:AA,_xlfn.SINGLE(MATCH(_xlfn.SINGLE(C:C),样品编号表!H:H,0)))) -> 12.3 | O122: 17 | P122: =I122*O122 -> 17 | R122: 已对账
A123: 45973 | B123: D&J | C123: SP25050 | D123: =_xlfn.SINGLE(INDEX(样品编号表!Y:Y,_xlfn.SINGLE(MATCH(_xlfn.SINGLE(C:C),样品编号表!H:H,0)))) -> 光大纺织 | E123: =_xlfn.SINGLE(INDEX(样品编号表!Z:Z,_xlfn.SINGLE(MATCH(_xlfn.SINGLE(C:C),样品编号表!H:H,0)))) -> TR439 | F123: 25#卡其 | G123: 7 | H123: 米 | I123: 7 | J123: 45975 | K123: 26 | L123: =I123*K123 -> 182 | M123: 微信 | N123: =_xlfn.SINGLE(INDEX(样品编号表!AA:AA,_xlfn.SINGLE(MATCH(_xlfn.SINGLE(C:C),样品编号表!H:H,0)))) -> 12.3 | O123: 17 | P123: =I123*O123 -> 119 | R123: 已对账
A124: 45973 | B124: D&J | C124: SP25050 | D124: =_xlfn.SINGLE(INDEX(样品编号表!Y:Y,_xlfn.SINGLE(MATCH(_xlfn.SINGLE(C:C),样品编号表!H:H,0)))) -> 光大纺织 | E124: =_xlfn.SINGLE(INDEX(样品编号表!Z:Z,_xlfn.SINGLE(MATCH(_xlfn.SINGLE(C:C),样品编号表!H:H,0)))) -> TR439 | F124: 31#棕色 | G124: 3 | H124: 米 | I124: 3 | J124: 45975 | K124: 26 | L124: =I124*K124 -> 78 | M124: 微信 | N124: =_xlfn.SINGLE(INDEX(样品编号表!AA:AA,_xlfn.SINGLE(MATCH(_xlfn.SINGLE(C:C),样品编号表!H:H,0)))) -> 12.3 | O124: 17 | P124: =I124*O124 -> 51 | R124: 已对账
A125: 45973 | B125: D&J | C125: SY25776 | D125: =_xlfn.SINGLE(INDEX(样品编号表!Y:Y,_xlfn.SINGLE(MATCH(_xlfn.SINGLE(C:C),样品编号表!H:H,0)))) -> 新合盛布业 | E125: =_xlfn.SINGLE(INDEX(样品编号表!Z:Z,_xlfn.SINGLE(MATCH(_xlfn.SINGLE(C:C),样品编号表!H:H,0)))) -> 8112 | F125: 黑色 | G125: 1 | H125: 米 | I125: 1 | J125: 45974 | K125: 17 | L125: =I125*K125 -> 17 | M125: 微信 | N125: =_xlfn.SINGLE(INDEX(样品编号表!AA:AA,_xlfn.SINGLE(MATCH(_xlfn.SINGLE(C:C),样品编号表!H:H,0)))) -> 9.6 | O125: 15 | P125: =I125*O125 -> 15 | R125: 已对账
A126: 45973 | B126: D&J | C126: SY25839 | D126: =_xlfn.SINGLE(INDEX(样品编号表!Y:Y,_xlfn.SINGLE(MATCH(_xlfn.SINGLE(C:C),样品编号表!H:H,0)))) -> 凯盛亨 | E126: =_xlfn.SINGLE(INDEX(样品编号表!Z:Z,_xlfn.SINGLE(MATCH(_xlfn.SINGLE(C:C),样品编号表!H:H,0)))) -> 1009# | F126: 黑色 | G126: 2 | H126: 米 | I126: 2 | J126: 45974 | K126: 29 | L126: =I126*K126 -> 58 | M126: 微信 | N126: =_xlfn.SINGLE(INDEX(样品编号表!AA:AA,_xlfn.SINGLE(MATCH(_xlfn.SINGLE(C:C),样品编号表!H:H,0)))) -> 13.9 | O126: 18 | P126: =I126*O126 -> 36 | R126: 已对账
A127: 45975 | B127: 万泰 | C127: SP25048 | D127: =_xlfn.SINGLE(INDEX(样品编号表!Y:Y,_xlfn.SINGLE(MATCH(_xlfn.SINGLE(C:C),样品编号表!H:H,0)))) -> 三好纺织 | E127: =_xlfn.SINGLE(INDEX(样品编号表!Z:Z,_xlfn.SINGLE(MATCH(_xlfn.SINGLE(C:C),样品编号表!H:H,0)))) -> 0953# | F127: 黑色 | G127: 6 | H127: 米 | J127: 45980 | K127: 25 | L127: =I127*K127 -> 0 | M127: 微信 | N127: =_xlfn.SINGLE(INDEX(样品编号表!AA:AA,_xlfn.SINGLE(MATCH(_xlfn.SINGLE(C:C),样品编号表!H:H,0)))) -> 11.5 | O127: 17 | P127: =I127*O127 -> 0 | R127: 已对账
A128: 45975 | B128: 万泰 | C128: SY251414 | D128: =_xlfn.SINGLE(INDEX(样品编号表!Y:Y,_xlfn.SINGLE(MATCH(_xlfn.SINGLE(C:C),样品编号表!H:H,0)))) -> 八方染织 | E128: =_xlfn.SINGLE(INDEX(样品编号表!Z:Z,_xlfn.SINGLE(MATCH(_xlfn.SINGLE(C:C),样品编号表!H:H,0)))) -> A7061# 60s锦棉罗马 | F128: 28#酒红色 | G128: 1 | H128: 米 | I128: 1 | J128: 45980 | K128: 35 | L128: =I128*K128 -> 35 | M128: 微信 | N128: =_xlfn.SINGLE(INDEX(样品编号表!AA:AA,_xlfn.SINGLE(MATCH(_xlfn.SINGLE(C:C),样品编号表!H:H,0)))) -> 42.3 | O128: 30 | P128: =I128*O128 -> 30 | R128: 已对账
A129: 45975 | B129: 家棋服饰 | C129: SY251479 | D129: =_xlfn.SINGLE(INDEX(样品编号表!Y:Y,_xlfn.SINGLE(MATCH(_xlfn.SINGLE(C:C),样品编号表!H:H,0)))) -> 星海纺织 | E129: =_xlfn.SINGLE(INDEX(样品编号表!Z:Z,_xlfn.SINGLE(MATCH(_xlfn.SINGLE(C:C),样品编号表!H:H,0)))) -> 1L1010 酷丝绵罗纹 | F129: 17# | G129: 2 | H129: 米 | I129: 2 | J129: 45979 | K129: 28 | L129: =I129*K129 -> 56 | M129: 微信 | N129: =_xlfn.SINGLE(INDEX(样品编号表!AA:AA,_xlfn.SINGLE(MATCH(_xlfn.SINGLE(C:C),样品编号表!H:H,0)))) -> 30.5 | O129: 25 | P129: =I129*O129 -> 50 | R129: 已对账
A130: 45975 | B130: 妮裳 | C130: SY25419 | D130: =_xlfn.SINGLE(INDEX(样品编号表!Y:Y,_xlfn.SINGLE(MATCH(_xlfn.SINGLE(C:C),样品编号表!H:H,0)))) -> 艺纺 | E130: =_xlfn.SINGLE(INDEX(样品编号表!Z:Z,_xlfn.SINGLE(MATCH(_xlfn.SINGLE(C:C),样品编号表!H:H,0)))) -> 11865-3 | F130: 2#杏色 | G130: 2 | H130: 米 | I130: 2 | J130: 45978 | K130: 25 | L130: =I130*K130 -> 50 | M130: 微信 | N130: =_xlfn.SINGLE(INDEX(样品编号表!AA:AA,_xlfn.SINGLE(MATCH(_xlfn.SINGLE(C:C),样品编号表!H:H,0)))) -> 12.8 | O130: 18 | P130: =I130*O130 -> 36 | R130: 已对账
A131: 45975 | B131: 正恒 | C131: SY25531 | D131: =_xlfn.SINGLE(INDEX(样品编号表!Y:Y,_xlfn.SINGLE(MATCH(_xlfn.SINGLE(C:C),样品编号表!H:H,0)))) -> 凯盛亨 | E131: =_xlfn.SINGLE(INDEX(样品编号表!Z:Z,_xlfn.SINGLE(MATCH(_xlfn.SINGLE(C:C),样品编号表!H:H,0)))) -> 839# | F131: 巧克力野花 | G131: 5 | H131: 米 | I131: 5 | J131: 45978 | K131: 37 | L131: =I131*K131 -> 185 | M131: 微信 | N131: =_xlfn.SINGLE(INDEX(样品编号表!AA:AA,_xlfn.SINGLE(MATCH(_xlfn.SINGLE(C:C),样品编号表!H:H,0)))) -> 11.3 | O131: 19.9 | P131: =I131*O131 -> 99.5 | Q131: 顺亚印花 | R131: 已对账
A132: 45976 | B132: 橙爱 | C132: SP25028 | D132: =_xlfn.SINGLE(INDEX(样品编号表!Y:Y,_xlfn.SINGLE(MATCH(_xlfn.SINGLE(C:C),样品编号表!H:H,0)))) -> 新合盛布业 | E132: =_xlfn.SINGLE(INDEX(样品编号表!Z:Z,_xlfn.SINGLE(MATCH(_xlfn.SINGLE(C:C),样品编号表!H:H,0)))) -> 6002 | F132: 印花底布 | G132: 1 | H132: 米 | I132: 1 | J132: 45978 | K132: 18 | L132: =I132*K132 -> 18 | M132: 微信 | N132: =_xlfn.SINGLE(INDEX(样品编号表!AA:AA,_xlfn.SINGLE(MATCH(_xlfn.SINGLE(C:C),样品编号表!H:H,0)))) -> 6.6 | O132: 12 | P132: =I132*O132 -> 12 | R132: 已对账
A133: 45978 | B133: D&J | C133: SY251409 | D133: =_xlfn.SINGLE(INDEX(样品编号表!Y:Y,_xlfn.SINGLE(MATCH(_xlfn.SINGLE(C:C),样品编号表!H:H,0)))) -> 佳鸿布行 | E133: =_xlfn.SINGLE(INDEX(样品编号表!Z:Z,_xlfn.SINGLE(MATCH(_xlfn.SINGLE(C:C),样品编号表!H:H,0)))) -> 密根日本棉 | F133: 60# | G133: 1 | H133: 米 | I133: 1 | J133: 45979 | K133: 26 | L133: =I133*K133 -> 26 | M133: 微信 | N133: =_xlfn.SINGLE(INDEX(样品编号表!AA:AA,_xlfn.SINGLE(MATCH(_xlfn.SINGLE(C:C),样品编号表!H:H,0)))) -> 39.5 | O133: 25 | P133: =I133*O133 -> 25 | R133: 已对账
A134: 45978 | B134: D&J | C134: SY251409 | D134: =_xlfn.SINGLE(INDEX(样品编号表!Y:Y,_xlfn.SINGLE(MATCH(_xlfn.SINGLE(C:C),样品编号表!H:H,0)))) -> 佳鸿布行 | E134: =_xlfn.SINGLE(INDEX(样品编号表!Z:Z,_xlfn.SINGLE(MATCH(_xlfn.SINGLE(C:C),样品编号表!H:H,0)))) -> 密根日本棉 | F134: 5# | G134: 1 | H134: 米 | I134: 1 | J134: 45979 | K134: 26 | L134: =I134*K134 -> 26 | M134: 微信 | N134: =_xlfn.SINGLE(INDEX(样品编号表!AA:AA,_xlfn.SINGLE(MATCH(_xlfn.SINGLE(C:C),样品编号表!H:H,0)))) -> 39.5 | O134: 25 | P134: =I134*O134 -> 25 | R134: 已对账
A135: 45979 | B135: 夜色 | C135: SP25031 | D135: =_xlfn.SINGLE(INDEX(样品编号表!Y:Y,_xlfn.SINGLE(MATCH(_xlfn.SINGLE(C:C),样品编号表!H:H,0)))) -> 凯盛亨 | E135: =_xlfn.SINGLE(INDEX(样品编号表!Z:Z,_xlfn.SINGLE(MATCH(_xlfn.SINGLE(C:C),样品编号表!H:H,0)))) -> 262# | F135: 37# | G135: 2 | H135: 米 | I135: 2 | J135: 45980 | K135: 23 | L135: =I135*K135 -> 46 | M135: 微信 | N135: =_xlfn.SINGLE(INDEX(样品编号表!AA:AA,_xlfn.SINGLE(MATCH(_xlfn.SINGLE(C:C),样品编号表!H:H,0)))) -> 10.5 | O135: 16 | P135: =I135*O135 -> 32 | R135: 已对账
A136: 45979 | B136: 夜色 | C136: SP25031 | D136: =_xlfn.SINGLE(INDEX(样品编号表!Y:Y,_xlfn.SINGLE(MATCH(_xlfn.SINGLE(C:C),样品编号表!H:H,0)))) -> 凯盛亨 | E136: =_xlfn.SINGLE(INDEX(样品编号表!Z:Z,_xlfn.SINGLE(MATCH(_xlfn.SINGLE(C:C),样品编号表!H:H,0)))) -> 262# | F136: 18# | G136: 2 | H136: 米 | I136: 2 | J136: 45980 | K136: 23 | L136: =I136*K136 -> 46 | M136: 微信 | N136: =_xlfn.SINGLE(INDEX(样品编号表!AA:AA,_xlfn.SINGLE(MATCH(_xlfn.SINGLE(C:C),样品编号表!H:H,0)))) -> 10.5 | O136: 16 | P136: =I136*O136 -> 32 | R136: 已对账
A137: 45979 | B137: 夜色 | C137: SP25031 | D137: =_xlfn.SINGLE(INDEX(样品编号表!Y:Y,_xlfn.SINGLE(MATCH(_xlfn.SINGLE(C:C),样品编号表!H:H,0)))) -> 凯盛亨 | E137: =_xlfn.SINGLE(INDEX(样品编号表!Z:Z,_xlfn.SINGLE(MATCH(_xlfn.SINGLE(C:C),样品编号表!H:H,0)))) -> 262# | F137: 27# | G137: 2 | H137: 米 | I137: 2 | J137: 45980 | K137: 23 | L137: =I137*K137 -> 46 | M137: 微信 | N137: =_xlfn.SINGLE(INDEX(样品编号表!AA:AA,_xlfn.SINGLE(MATCH(_xlfn.SINGLE(C:C),样品编号表!H:H,0)))) -> 10.5 | O137: 16 | P137: =I137*O137 -> 32 | R137: 已对账
A138: 45979 | B138: D&J | C138: SY251409 | D138: =_xlfn.SINGLE(INDEX(样品编号表!Y:Y,_xlfn.SINGLE(MATCH(_xlfn.SINGLE(C:C),样品编号表!H:H,0)))) -> 佳鸿布行 | E138: =_xlfn.SINGLE(INDEX(样品编号表!Z:Z,_xlfn.SINGLE(MATCH(_xlfn.SINGLE(C:C),样品编号表!H:H,0)))) -> 密根日本棉 | F138: 60# | G138: 1 | H138: 米 | I138: 1 | J138: 45981 | K138: 26 | L138: =I138*K138 -> 26 | M138: 微信 | N138: =_xlfn.SINGLE(INDEX(样品编号表!AA:AA,_xlfn.SINGLE(MATCH(_xlfn.SINGLE(C:C),样品编号表!H:H,0)))) -> 39.5 | O138: 25 | P138: =I138*O138 -> 25 | R138: 已对账
A139: 45979 | B139: D&J | C139: SY251409 | D139: =_xlfn.SINGLE(INDEX(样品编号表!Y:Y,_xlfn.SINGLE(MATCH(_xlfn.SINGLE(C:C),样品编号表!H:H,0)))) -> 佳鸿布行 | E139: =_xlfn.SINGLE(INDEX(样品编号表!Z:Z,_xlfn.SINGLE(MATCH(_xlfn.SINGLE(C:C),样品编号表!H:H,0)))) -> 密根日本棉 | F139: 5# | G139: 1 | H139: 米 | I139: 1 | J139: 45981 | K139: 26 | L139: =I139*K139 -> 26 | M139: 微信 | N139: =_xlfn.SINGLE(INDEX(样品编号表!AA:AA,_xlfn.SINGLE(MATCH(_xlfn.SINGLE(C:C),样品编号表!H:H,0)))) -> 39.5 | O139: 25 | P139: =I139*O139 -> 25 | R139: 已对账
A140: 45979 | B140: 夜色 | C140: SY25419 | D140: =_xlfn.SINGLE(INDEX(样品编号表!Y:Y,_xlfn.SINGLE(MATCH(_xlfn.SINGLE(C:C),样品编号表!H:H,0)))) -> 艺纺 | E140: =_xlfn.SINGLE(INDEX(样品编号表!Z:Z,_xlfn.SINGLE(MATCH(_xlfn.SINGLE(C:C),样品编号表!H:H,0)))) -> 11865-3 | F140: 25# | G140: 4 | H140: 米 | I140: 4 | J140: 45980 | K140: 25 | L140: =I140*K140 -> 100 | M140: 微信 | N140: =_xlfn.SINGLE(INDEX(样品编号表!AA:AA,_xlfn.SINGLE(MATCH(_xlfn.SINGLE(C:C),样品编号表!H:H,0)))) -> 12.8 | O140: 18 | P140: =I140*O140 -> 72 | R140: 已对账
A141: 45979 | B141: D&J | C141: SY25773 | D141: =_xlfn.SINGLE(INDEX(样品编号表!Y:Y,_xlfn.SINGLE(MATCH(_xlfn.SINGLE(C:C),样品编号表!H:H,0)))) -> 新合盛布业 | E141: =_xlfn.SINGLE(INDEX(样品编号表!Z:Z,_xlfn.SINGLE(MATCH(_xlfn.SINGLE(C:C),样品编号表!H:H,0)))) -> 6002 | F141: 印花底布 | G141: 3 | H141: 米 | I141: 3 | J141: 45980 | K141: 18 | L141: =I141*K141 -> 54 | M141: 微信 | N141: =_xlfn.SINGLE(INDEX(样品编号表!AA:AA,_xlfn.SINGLE(MATCH(_xlfn.SINGLE(C:C),样品编号表!H:H,0)))) -> 6.2 | O141: 12 | P141: =I141*O141 -> 36 | R141: 已对账
A142: 45980 | B142: 扑喜 | C142: SY25419 | D142: =_xlfn.SINGLE(INDEX(样品编号表!Y:Y,_xlfn.SINGLE(MATCH(_xlfn.SINGLE(C:C),样品编号表!H:H,0)))) -> 艺纺 | E142: =_xlfn.SINGLE(INDEX(样品编号表!Z:Z,_xlfn.SINGLE(MATCH(_xlfn.SINGLE(C:C),样品编号表!H:H,0)))) -> 11865-3 | F142: 黑色 | G142: 2 | H142: 米 | I142: 2 | J142: 45982 | K142: 25 | L142: =I142*K142 -> 50 | M142: 微信 | N142: =_xlfn.SINGLE(INDEX(样品编号表!AA:AA,_xlfn.SINGLE(MATCH(_xlfn.SINGLE(C:C),样品编号表!H:H,0)))) -> 12.8 | O142: 18 | P142: =I142*O142 -> 36 | R142: 已对账
A143: 45980 | B143: 越安 | C143: SY25776 | D143: =_xlfn.SINGLE(INDEX(样品编号表!Y:Y,_xlfn.SINGLE(MATCH(_xlfn.SINGLE(C:C),样品编号表!H:H,0)))) -> 新合盛布业 | E143: =_xlfn.SINGLE(INDEX(样品编号表!Z:Z,_xlfn.SINGLE(MATCH(_xlfn.SINGLE(C:C),样品编号表!H:H,0)))) -> 8112 | F143: 黑色 | G143: 2 | H143: 米 | I143: 2 | J143: 45983 | K143: 17 | L143: =I143*K143 -> 34 | M143: 微信 | N143: =_xlfn.SINGLE(INDEX(样品编号表!AA:AA,_xlfn.SINGLE(MATCH(_xlfn.SINGLE(C:C),样品编号表!H:H,0)))) -> 9.6 | O143: 15 | P143: =I143*O143 -> 30 | R143: 已对账
... A171: 45989 | B171: BTC | C171: SY25287 | D171: =_xlfn.SINGLE(INDEX(样品编号表!Y:Y,_xlfn.SINGLE(MATCH(_xlfn.SINGLE(C:C),样品编号表!H:H,0)))) -> 宝隆纺织 | E171: =_xlfn.SINGLE(INDEX(样品编号表!Z:Z,_xlfn.SINGLE(MATCH(_xlfn.SINGLE(C:C),样品编号表!H:H,0)))) -> 1562 | F171: 米白色 | G171: 5 | H171: 米 | I171: 5 | J171: 45992 | K171: 21 | L171: =I171*K171 -> 105 | M171: 微信 | N171: =_xlfn.SINGLE(INDEX(样品编号表!AA:AA,_xlfn.SINGLE(MATCH(_xlfn.SINGLE(C:C),样品编号表!H:H,0)))) -> 6.8 | O171: 12 | P171: =I171*O171 -> 60 | R171: 已对账
...

Sheet 大货
A1: 日期 | B1: 加工厂 | C1: 订单号 | D1: 款号 | E1: 布种编号 | F1: 供应商 | G1: 编号 | H1: 颜色 | I1: 数量 | J1: 单位 | K1: 实际出货数量 | L1: 出货日期 | M1: 销售价 | N1: 销售金额 | O1: 付款方式 | P1: 是否需要证书 | Q1: 证书类型 | R1: 最迟开证时间 | S1: 实际开证时间 | T1: 采购价 | U1: 采购金额 | V1: 备注
A2: 45863 | B2: 乐力 | C2: XXL2507001 | E2: AB2364 | F2: 欧纺时尚 | G2: B364 | H2: 白色 | I2: 1700 | J2: 米 | K2: 1635 | L2: 45882 | M2: 15.6 | N2: =K2*M2 -> 25506 | O2: 现金+TC | T2: 8.1 | U2: =K2*T2 -> 13243.5 | V2: 待出证书
A3: 45869 | B3: 无锡美盛 | C3: XXL2507002 | E3: SY25063 | F3: =_xlfn.SINGLE(INDEX(样品编号表!Y:Y,_xlfn.SINGLE(MATCH(_xlfn.SINGLE(E:E),样品编号表!H:H,0)))) -> 年年发纺织 | G3: =_xlfn.SINGLE(INDEX(样品编号表!Z:Z,_xlfn.SINGLE(MATCH(_xlfn.SINGLE(E:E),样品编号表!H:H,0)))) -> 303# | H3: 35#绿色 | I3: 270 | J3: 米 | K3: 287 | L3: 45874 | M3: 15.3 | N3: =K3*M3 -> 4391.1 | O3: 现金转账 | T3: 11.3 | U3: =K3*T3 -> 3243.1
A4: 45887 | B4: 乐力 | C4: XXL2507001 | E4: AB2364 | F4: 欧纺时尚 | G4: B364 | H4: 白色 | I4: 310 | J4: 米 | K4: 351 | L4: 45889 | M4: 15.6 | N4: =K4*M4 -> 5475.6 | O4: 现金+TC | T4: 8.1 | U4: =K4*T4 -> 2843.1 | V4: 待出证书
A5: 45892 | B5: 圣德 | C5: SYL-SD2508001 | E5: SY25531 | F5: =_xlfn.SINGLE(INDEX(样品编号表!Y:Y,_xlfn.SINGLE(MATCH(_xlfn.SINGLE(E:E),样品编号表!H:H,0)))) -> 凯盛亨 | G5: =_xlfn.SINGLE(INDEX(样品编号表!Z:Z,_xlfn.SINGLE(MATCH(_xlfn.SINGLE(E:E),样品编号表!H:H,0)))) -> 839# | H5: 43#黄油色 | I5: 544 | J5: 米 | K5: 589 | L5: 45892 | M5: 14.7 | N5: =K5*M5 -> 8658.3 | O5: 现金转账 | T5: 11.3 | U5: =K5*T5 -> 6655.7
A6: 45898 | B6: 圣德 | E6: SY25531 | F6: =_xlfn.SINGLE(INDEX(样品编号表!Y:Y,_xlfn.SINGLE(MATCH(_xlfn.SINGLE(E:E),样品编号表!H:H,0)))) -> 凯盛亨 | G6: =_xlfn.SINGLE(INDEX(样品编号表!Z:Z,_xlfn.SINGLE(MATCH(_xlfn.SINGLE(E:E),样品编号表!H:H,0)))) -> 839# | H6: 43#黄油色 | I6: 205 | J6: 米 | K6: 227 | L6: 45912 | M6: 14.7 | N6: =K6*M6 -> 3336.9 | O6: 现金转账 | T6: 11.3 | U6: =K6*T6 -> 2565.1
A7: 45898 | B7: 韦欣 | E7: SY25016 | F7: =_xlfn.SINGLE(INDEX(样品编号表!Y:Y,_xlfn.SINGLE(MATCH(_xlfn.SINGLE(E:E),样品编号表!H:H,0)))) -> 光大纺织 | G7: =_xlfn.SINGLE(INDEX(样品编号表!Z:Z,_xlfn.SINGLE(MATCH(_xlfn.SINGLE(E:E),样品编号表!H:H,0)))) -> C580 | H7: 2#白色 | I7: 190 | J7: 米 | K7: 217 | L7: 45912 | M7: 14.4 | N7: =K7*M7 -> 3124.8 | O7: 发票+BCI | T7: 9.8 | U7: =K7*T7 -> 2126.6 | V7: 开票+BCI证书
A8: 45898 | B8: 韦欣 | E8: SY25016 | F8: =_xlfn.SINGLE(INDEX(样品编号表!Y:Y,_xlfn.SINGLE(MATCH(_xlfn.SINGLE(E:E),样品编号表!H:H,0)))) -> 光大纺织 | G8: =_xlfn.SINGLE(INDEX(样品编号表!Z:Z,_xlfn.SINGLE(MATCH(_xlfn.SINGLE(E:E),样品编号表!H:H,0)))) -> C580 | H8: 40#粉色 | I8: 190 | J8: 米 | K8: 215 | L8: 45912 | M8: 14.4 | N8: =K8*M8 -> 3096 | O8: 发票+BCI | T8: 9.8 | U8: =K8*T8 -> 2107 | V8: 开票+BCI证书
A9: 45918 | B9: 圣德 | E9: SY25531 | F9: =_xlfn.SINGLE(INDEX(样品编号表!Y:Y,_xlfn.SINGLE(MATCH(_xlfn.SINGLE(E:E),样品编号表!H:H,0)))) -> 凯盛亨 | G9: =_xlfn.SINGLE(INDEX(样品编号表!Z:Z,_xlfn.SINGLE(MATCH(_xlfn.SINGLE(E:E),样品编号表!H:H,0)))) -> 839# | H9: 白底咖兰花 | I9: 122 | J9: 米 | K9: 118 | L9: 45945 | M9: 27.1 | N9: =K9*M9 -> 3197.8 | O9: 现金 | T9: =9+10.9 -> 19.9 | U9: =K9*T9 -> 2348.2
A10: 45919 | B10: 韦恩 | E10: SY25016 | F10: =_xlfn.SINGLE(INDEX(样品编号表!Y:Y,_xlfn.SINGLE(MATCH(_xlfn.SINGLE(E:E),样品编号表!H:H,0)))) -> 光大纺织 | G10: =_xlfn.SINGLE(INDEX(样品编号表!Z:Z,_xlfn.SINGLE(MATCH(_xlfn.SINGLE(E:E),样品编号表!H:H,0)))) -> C580 | H10: 154#黑色 | I10: 300 | J10: 米 | K10: 306 | L10: 45922 | M10: 14.4 | N10: =K10*M10 -> 4406.4 | O10: 发票+BCI | T10: 9.8 | U10: =K10*T10 -> 2998.8 | V10: 退109米，补发90米，19*14.4=273.6元待后续订单抵扣，开票+BCI证书
A11: 45919 | B11: 杰登 | E11: SY25531 | F11: =_xlfn.SINGLE(INDEX(样品编号表!Y:Y,_xlfn.SINGLE(MATCH(_xlfn.SINGLE(E:E),样品编号表!H:H,0)))) -> 凯盛亨 | G11: =_xlfn.SINGLE(INDEX(样品编号表!Z:Z,_xlfn.SINGLE(MATCH(_xlfn.SINGLE(E:E),样品编号表!H:H,0)))) -> 839# | H11: 白底咖兰花 | I11: 290 | J11: 米 | K11: 288 | L11: 45945 | M11: 27.1 | N11: =K11*M11 -> 7804.8 | O11: 现金 | T11: =9+10.9 -> 19.9 | U11: =K11*T11 -> 5731.2
A12: 45919 | B12: 杰登 | E12: SY25531 | F12: =_xlfn.SINGLE(INDEX(样品编号表!Y:Y,_xlfn.SINGLE(MATCH(_xlfn.SINGLE(E:E),样品编号表!H:H,0)))) -> 凯盛亨 | G12: =_xlfn.SINGLE(INDEX(样品编号表!Z:Z,_xlfn.SINGLE(MATCH(_xlfn.SINGLE(E:E),样品编号表!H:H,0)))) -> 839# | H12: 白底咖兰花 | I12: 260 | J12: 米 | K12: 260 | L12: 45945 | M12: 27.1 | N12: =K12*M12 -> 7046 | O12: 现金 | T12: =9+10.9 -> 19.9 | U12: =K12*T12 -> 5174
A13: 45919 | B13: 杰登 | E13: SY25531 | F13: =_xlfn.SINGLE(INDEX(样品编号表!Y:Y,_xlfn.SINGLE(MATCH(_xlfn.SINGLE(E:E),样品编号表!H:H,0)))) -> 凯盛亨 | G13: =_xlfn.SINGLE(INDEX(样品编号表!Z:Z,_xlfn.SINGLE(MATCH(_xlfn.SINGLE(E:E),样品编号表!H:H,0)))) -> 839# | H13: 黑色 | I13: 260 | J13: 米 | K13: 265 | L13: 45947 | M13: 14.7 | N13: =K13*M13 -> 3895.5 | O13: 现金 | T13: 11.3 | U13: =K13*T13 -> 2994.5
A14: 45947 | B14: 杰登 | E14: SY25531 | F14: =_xlfn.SINGLE(INDEX(样品编号表!Y:Y,_xlfn.SINGLE(MATCH(_xlfn.SINGLE(E:E),样品编号表!H:H,0)))) -> 凯盛亨 | G14: =_xlfn.SINGLE(INDEX(样品编号表!Z:Z,_xlfn.SINGLE(MATCH(_xlfn.SINGLE(E:E),样品编号表!H:H,0)))) -> 839# | H14: 白底咖兰花 | I14: 65 | J14: 米 | K14: 65 | L14: 45951 | M14: 27.1 | N14: =K14*M14 -> 1761.5 | O14: 现金 | T14: =9+10.9 -> 19.9 | U14: =K14*T14 -> 1293.5
A15: 45947 | B15: 万泰 | E15: SY25824 | F15: =_xlfn.SINGLE(INDEX(样品编号表!Y:Y,_xlfn.SINGLE(MATCH(_xlfn.SINGLE(E:E),样品编号表!H:H,0)))) -> 合泰隆纺织 | G15: =_xlfn.SINGLE(INDEX(样品编号表!Z:Z,_xlfn.SINGLE(MATCH(_xlfn.SINGLE(E:E),样品编号表!H:H,0)))) -> T985 | H15: 5#浅绿色&白色 | I15: 210 | J15: 米 | K15: 218.5 | L15: 45947 | M15: 15.1 | N15: =K15*M15 -> 3299.35 | O15: 发票 | T15: 10.8 | U15: =K15*T15 -> 2359.8 | V15: 待开票 布小帮
A16: 45948 | B16: 万泰 | E16: SY25824 | F16: =_xlfn.SINGLE(INDEX(样品编号表!Y:Y,_xlfn.SINGLE(MATCH(_xlfn.SINGLE(E:E),样品编号表!H:H,0)))) -> 合泰隆纺织 | G16: =_xlfn.SINGLE(INDEX(样品编号表!Z:Z,_xlfn.SINGLE(MATCH(_xlfn.SINGLE(E:E),样品编号表!H:H,0)))) -> T985 | H16: #21藏青&白色 | I16: 305 | J16: 米 | K16: 319 | L16: 45950 | M16: 15.1 | N16: =K16*M16 -> 4816.9 | O16: 发票 | T16: 10.8 | U16: =K16*T16 -> 3445.2 | V16: 待开票 布小帮
A17: 45950 | B17: BTC | E17: SY25738 | F17: =_xlfn.SINGLE(INDEX(样品编号表!Y:Y,_xlfn.SINGLE(MATCH(_xlfn.SINGLE(E:E),样品编号表!H:H,0)))) -> 新嘉彩 | G17: =_xlfn.SINGLE(INDEX(样品编号表!Z:Z,_xlfn.SINGLE(MATCH(_xlfn.SINGLE(E:E),样品编号表!H:H,0)))) -> 938 | H17: 2#黑色 | I17: 690 | J17: 米 | K17: 691 | L17: 45952 | M17: 14.4 | N17: =K17*M17 -> 9950.4 | O17: 发票+TC | T17: 10.3 | U17: =K17*T17 -> 7117.3
A18: 45950 | B18: BTC | E18: SY25738 | F18: =_xlfn.SINGLE(INDEX(样品编号表!Y:Y,_xlfn.SINGLE(MATCH(_xlfn.SINGLE(E:E),样品编号表!H:H,0)))) -> 新嘉彩 | G18: =_xlfn.SINGLE(INDEX(样品编号表!Z:Z,_xlfn.SINGLE(MATCH(_xlfn.SINGLE(E:E),样品编号表!H:H,0)))) -> 938 | H18: 32#黄色 | I18: 90 | J18: 米 | K18: 112 | L18: 45952 | M18: 14.4 | N18: =K18*M18 -> 1612.8 | O18: 发票+TC | T18: 10.3 | U18: =K18*T18 -> 1153.6
A19: 45950 | B19: BTC | E19: SY25738 | F19: =_xlfn.SINGLE(INDEX(样品编号表!Y:Y,_xlfn.SINGLE(MATCH(_xlfn.SINGLE(E:E),样品编号表!H:H,0)))) -> 新嘉彩 | G19: =_xlfn.SINGLE(INDEX(样品编号表!Z:Z,_xlfn.SINGLE(MATCH(_xlfn.SINGLE(E:E),样品编号表!H:H,0)))) -> 938 | H19: 77#蓝色 | I19: 90 | J19: 米 | K19: 108 | L19: 45952 | M19: 14.4 | N19: =K19*M19 -> 1555.2 | O19: 发票+TC | T19: 10.3 | U19: =K19*T19 -> 1112.4
A20: 45950 | B20: BTC | E20: SP25051 | F20: =_xlfn.SINGLE(INDEX(样品编号表!Y:Y,_xlfn.SINGLE(MATCH(_xlfn.SINGLE(E:E),样品编号表!H:H,0)))) -> 马利布行 | G20: =_xlfn.SINGLE(INDEX(样品编号表!Z:Z,_xlfn.SINGLE(MATCH(_xlfn.SINGLE(E:E),样品编号表!H:H,0)))) -> 10172# | H20: 黑色 | I20: 60 | J20: 米 | K20: 67 | L20: 45958 | M20: 18.7 | N20: =K20*M20 -> 1252.9 | O20: 发票+TC | T20: 12.2 | U20: =K20*T20 -> 817.4 | V20: 开票+证书
A21: 45952 | B21: 圣德 | E21: SY25531 | F21: =_xlfn.SINGLE(INDEX(样品编号表!Y:Y,_xlfn.SINGLE(MATCH(_xlfn.SINGLE(E:E),样品编号表!H:H,0)))) -> 凯盛亨 | G21: =_xlfn.SINGLE(INDEX(样品编号表!Z:Z,_xlfn.SINGLE(MATCH(_xlfn.SINGLE(E:E),样品编号表!H:H,0)))) -> 839# | H21: 9#淡紫色 | I21: 382 | J21: 米 | K21: 378 | L21: 45966 | M21: 14.7 | N21: =K21*M21 -> 5556.6 | O21: 现金 | U21: =K21*T21 -> 0 | V21: 不需要开票/证书
A22: 45955 | B22: 杰登 | D22: TUS0358-A | E22: SY25544 | F22: =_xlfn.SINGLE(INDEX(样品编号表!Y:Y,_xlfn.SINGLE(MATCH(_xlfn.SINGLE(E:E),样品编号表!H:H,0)))) -> 润森 | G22: =_xlfn.SINGLE(INDEX(样品编号表!Z:Z,_xlfn.SINGLE(MATCH(_xlfn.SINGLE(E:E),样品编号表!H:H,0)))) -> 华尔缎 | H22: 108#黑色 | I22: 265 | J22: 米 | K22: 265 | L22: 45963 | M22: 16.1 | N22: =K22*M22 -> 4266.5 | O22: 开票+TC
A23: 45955 | B23: 杰登 | D23: TUS0287-A | E23: SY25544 | F23: =_xlfn.SINGLE(INDEX(样品编号表!Y:Y,_xlfn.SINGLE(MATCH(_xlfn.SINGLE(E:E),样品编号表!H:H,0)))) -> 润森 | G23: =_xlfn.SINGLE(INDEX(样品编号表!Z:Z,_xlfn.SINGLE(MATCH(_xlfn.SINGLE(E:E),样品编号表!H:H,0)))) -> 华尔缎 | H23: 108#黑色 | I23: 200 | J23: 米 | K23: 200 | L23: 45963 | M23: 16.1 | N23: =K23*M23 -> 3220 | O23: 开票+TC
A24: 45958 | B24: 杰登 | D24: TUS0303-A | E24: SY25544 | F24: =_xlfn.SINGLE(INDEX(样品编号表!Y:Y,_xlfn.SINGLE(MATCH(_xlfn.SINGLE(E:E),样品编号表!H:H,0)))) -> 润森 | G24: =_xlfn.SINGLE(INDEX(样品编号表!Z:Z,_xlfn.SINGLE(MATCH(_xlfn.SINGLE(E:E),样品编号表!H:H,0)))) -> 华尔缎 | H24: 108#黑色 | I24: 185 | J24: 米 | K24: 185 | L24: 45963 | M24: 16.1 | N24: =K24*M24 -> 2978.5 | O24: 开票+TC
A25: 45958 | B25: 杰登 | D25: TUS0316-A | E25: SY25544 | F25: =_xlfn.SINGLE(INDEX(样品编号表!Y:Y,_xlfn.SINGLE(MATCH(_xlfn.SINGLE(E:E),样品编号表!H:H,0)))) -> 润森 | G25: =_xlfn.SINGLE(INDEX(样品编号表!Z:Z,_xlfn.SINGLE(MATCH(_xlfn.SINGLE(E:E),样品编号表!H:H,0)))) -> 华尔缎 | H25: 108#黑色 | I25: 305 | J25: 米 | K25: 328 | L25: 45963 | M25: 16.1 | N25: =K25*M25 -> 5280.8 | O25: 开票+TC
A26: 45955 | B26: 杰登 | D26: TUS0358-B | E26: SY25544 | F26: =_xlfn.SINGLE(INDEX(样品编号表!Y:Y,_xlfn.SINGLE(MATCH(_xlfn.SINGLE(E:E),样品编号表!H:H,0)))) -> 润森 | G26: =_xlfn.SINGLE(INDEX(样品编号表!Z:Z,_xlfn.SINGLE(MATCH(_xlfn.SINGLE(E:E),样品编号表!H:H,0)))) -> 华尔缎 | H26: 117#浅兰色 | I26: 265 | J26: 米 | K26: 273 | L26: 45963 | M26: 16.1 | N26: =K26*M26 -> 4395.3 | O26: 开票+TC
A27: 45958 | B27: 杰登 | D27: TUS0480-A | E27: SY25544 | F27: =_xlfn.SINGLE(INDEX(样品编号表!Y:Y,_xlfn.SINGLE(MATCH(_xlfn.SINGLE(E:E),样品编号表!H:H,0)))) -> 润森 | G27: =_xlfn.SINGLE(INDEX(样品编号表!Z:Z,_xlfn.SINGLE(MATCH(_xlfn.SINGLE(E:E),样品编号表!H:H,0)))) -> 华尔缎 | H27: 117#浅兰色 | I27: 90 | J27: 米 | K27: 90 | L27: 45963 | M27: 16.1 | N27: =K27*M27 -> 1449 | O27: 开票+TC
A28: 45955 | B28: 杰登 | D28: TUS0287-B | E28: SY25544 | F28: =_xlfn.SINGLE(INDEX(样品编号表!Y:Y,_xlfn.SINGLE(MATCH(_xlfn.SINGLE(E:E),样品编号表!H:H,0)))) -> 润森 | G28: =_xlfn.SINGLE(INDEX(样品编号表!Z:Z,_xlfn.SINGLE(MATCH(_xlfn.SINGLE(E:E),样品编号表!H:H,0)))) -> 华尔缎 | H28: 1#白色 | I28: 200 | J28: 米 | K28: 221 | L28: 45963 | M28: 16.1 | N28: =K28*M28 -> 3558.1 | O28: 开票+TC
A29: 45958 | B29: 杰登 | D29: TUS0316-B | E29: SY25544 | F29: =_xlfn.SINGLE(INDEX(样品编号表!Y:Y,_xlfn.SINGLE(MATCH(_xlfn.SINGLE(E:E),样品编号表!H:H,0)))) -> 润森 | G29: =_xlfn.SINGLE(INDEX(样品编号表!Z:Z,_xlfn.SINGLE(MATCH(_xlfn.SINGLE(E:E),样品编号表!H:H,0)))) -> 华尔缎 | H29: 91#米黄色 | I29: 200 | J29: 米 | K29: 236 | L29: 45963 | M29: 16.1 | N29: =K29*M29 -> 3799.6 | O29: 开票+TC
A30: 45958 | B30: 杰登 | D30: TUS0315-A | E30: SY25544 | F30: =_xlfn.SINGLE(INDEX(样品编号表!Y:Y,_xlfn.SINGLE(MATCH(_xlfn.SINGLE(E:E),样品编号表!H:H,0)))) -> 润森 | G30: =_xlfn.SINGLE(INDEX(样品编号表!Z:Z,_xlfn.SINGLE(MATCH(_xlfn.SINGLE(E:E),样品编号表!H:H,0)))) -> 华尔缎 | H30: 85#墨绿色 | I30: 255 | J30: 米 | K30: 267 | L30: 45965 | M30: 16.1 | N30: =K30*M30 -> 4298.7 | O30: 开票+TC
A31: 45958 | B31: 杰登 | D31: TUS0480-B | E31: SY25544 | F31: =_xlfn.SINGLE(INDEX(样品编号表!Y:Y,_xlfn.SINGLE(MATCH(_xlfn.SINGLE(E:E),样品编号表!H:H,0)))) -> 润森 | G31: =_xlfn.SINGLE(INDEX(样品编号表!Z:Z,_xlfn.SINGLE(MATCH(_xlfn.SINGLE(E:E),样品编号表!H:H,0)))) -> 华尔缎 | H31: 85#墨绿色 | I31: 90 | J31: 米 | K31: 90 | L31: 45965 | M31: 16.1 | N31: =K31*M31 -> 1449 | O31: 开票+TC
A32: 45966 | B32: 杰登 | E32: SY25544 | F32: =_xlfn.SINGLE(INDEX(样品编号表!Y:Y,_xlfn.SINGLE(MATCH(_xlfn.SINGLE(E:E),样品编号表!H:H,0)))) -> 润森 | G32: =_xlfn.SINGLE(INDEX(样品编号表!Z:Z,_xlfn.SINGLE(MATCH(_xlfn.SINGLE(E:E),样品编号表!H:H,0)))) -> 华尔缎 | H32: 117#浅兰色 | I32: 40 | J32: 米 | K32: 40 | L32: 45968 | M32: 16.1 | N32: =K32*M32 -> 644 | O32: 开票+TC
A33: 45969 | B33: 杰登 | D33: TUS0322-A/1390 | E33: SY25544 | F33: =_xlfn.SINGLE(INDEX(样品编号表!Y:Y,_xlfn.SINGLE(MATCH(_xlfn.SINGLE(E:E),样品编号表!H:H,0)))) -> 润森 | G33: =_xlfn.SINGLE(INDEX(样品编号表!Z:Z,_xlfn.SINGLE(MATCH(_xlfn.SINGLE(E:E),样品编号表!H:H,0)))) -> 华尔缎 | H33: 108#黑色 | I33: 235 | J33: 米 | K33: 253 | L33: 45979 | M33: 16.1 | N33: =K33*M33 -> 4073.3 | O33: 开票+TC | T33: 10.3 | U33: =K33*T33 -> 2605.9
A34: 45971 | B34: 圣德 | C34: WACA001297 | D34: CAL0223-A | E34: SP25028 | F34: =_xlfn.SINGLE(INDEX(样品编号表!Y:Y,_xlfn.SINGLE(MATCH(_xlfn.SINGLE(E:E),样品编号表!H:H,0)))) -> 新合盛布业 | G34: =_xlfn.SINGLE(INDEX(样品编号表!Z:Z,_xlfn.SINGLE(MATCH(_xlfn.SINGLE(E:E),样品编号表!H:H,0)))) -> 6002 | H34: 黑色 | I34: 331 | J34: 米 | K34: 339 | L34: 45978 | M34: 10.3 | N34: =K34*M34 -> 3491.7 | O34: 开票+TC | T34: 6.6 | U34: =K34*T34 -> 2237.4
A35: 45971 | B35: BTC | E35: SP25051 | F35: =_xlfn.SINGLE(INDEX(样品编号表!Y:Y,_xlfn.SINGLE(MATCH(_xlfn.SINGLE(E:E),样品编号表!H:H,0)))) -> 马利布行 | G35: =_xlfn.SINGLE(INDEX(样品编号表!Z:Z,_xlfn.SINGLE(MATCH(_xlfn.SINGLE(E:E),样品编号表!H:H,0)))) -> 10172# | H35: 16#酒红色 | I35: 38 | J35: 米 | K35: 38 | L35: 45985 | M35: 18.7 | N35: =K35*M35 -> 710.6 | O35: 发票+TC | V35: 开票+证书
A36: 45971 | B36: BTC | E36: SY25738 | F36: =_xlfn.SINGLE(INDEX(样品编号表!Y:Y,_xlfn.SINGLE(MATCH(_xlfn.SINGLE(E:E),样品编号表!H:H,0)))) -> 新嘉彩 | G36: =_xlfn.SINGLE(INDEX(样品编号表!Z:Z,_xlfn.SINGLE(MATCH(_xlfn.SINGLE(E:E),样品编号表!H:H,0)))) -> 938 | H36: 63#白色 | I36: 106 | J36: 米 | K36: 106 | L36: 45985 | M36: 14.5 | N36: =K36*M36 -> 1537 | O36: 发票+TC | T36: 10.3 | U36: =K36*T36 -> 1091.8 | V36: 开票+证书
A37: 45971 | B37: BTC | E37: SY25738 | F37: =_xlfn.SINGLE(INDEX(样品编号表!Y:Y,_xlfn.SINGLE(MATCH(_xlfn.SINGLE(E:E),样品编号表!H:H,0)))) -> 新嘉彩 | G37: =_xlfn.SINGLE(INDEX(样品编号表!Z:Z,_xlfn.SINGLE(MATCH(_xlfn.SINGLE(E:E),样品编号表!H:H,0)))) -> 938 | H37: 63#白色 | I37: 341 | J37: 米 | K37: 366 | L37: 45985 | M37: 14.5 | N37: =K37*M37 -> 5307 | O37: 发票+TC | T37: 10.3 | U37: =K37*T37 -> 3769.8 | V37: 开票+证书
A38: 45974 | B38: BTC | E38: SY251062 | F38: =_xlfn.SINGLE(INDEX(样品编号表!Y:Y,_xlfn.SINGLE(MATCH(_xlfn.SINGLE(E:E),样品编号表!H:H,0)))) -> 万顺纺织 | G38: =_xlfn.SINGLE(INDEX(样品编号表!Z:Z,_xlfn.SINGLE(MATCH(_xlfn.SINGLE(E:E),样品编号表!H:H,0)))) -> A8784 | H38: 50#黑色 | I38: 1646 | J38: 米 | K38: 1653 | L38: 45985 | M38: 13.4 | N38: =K38*M38 -> 22150.2 | O38: 发票+TC | V38: 开票+证书
A39: 45974 | B39: BTC | E39: SY251062 | F39: =_xlfn.SINGLE(INDEX(样品编号表!Y:Y,_xlfn.SINGLE(MATCH(_xlfn.SINGLE(E:E),样品编号表!H:H,0)))) -> 万顺纺织 | G39: =_xlfn.SINGLE(INDEX(样品编号表!Z:Z,_xlfn.SINGLE(MATCH(_xlfn.SINGLE(E:E),样品编号表!H:H,0)))) -> A8784 | H39: 58#巧克力色 | I39: 1441 | J39: 米 | K39: 1433 | L39: 45985 | M39: 13.4 | N39: =K39*M39 -> 19202.2 | O39: 发票+TC | V39: 开票+证书
A40: 45974 | B40: BTC | E40: SY251062 | F40: =_xlfn.SINGLE(INDEX(样品编号表!Y:Y,_xlfn.SINGLE(MATCH(_xlfn.SINGLE(E:E),样品编号表!H:H,0)))) -> 万顺纺织 | G40: =_xlfn.SINGLE(INDEX(样品编号表!Z:Z,_xlfn.SINGLE(MATCH(_xlfn.SINGLE(E:E),样品编号表!H:H,0)))) -> A8784 | H40: 4#柠檬黄 | I40: 828 | J40: 米 | K40: 818 | L40: 45985 | M40: 13.9 | N40: =K40*M40 -> 11370.2 | O40: 发票+TC | V40: 开票+证书
A41: 45974 | B41: BTC | E41: SY251062 | F41: =_xlfn.SINGLE(INDEX(样品编号表!Y:Y,_xlfn.SINGLE(MATCH(_xlfn.SINGLE(E:E),样品编号表!H:H,0)))) -> 万顺纺织 | G41: =_xlfn.SINGLE(INDEX(样品编号表!Z:Z,_xlfn.SINGLE(MATCH(_xlfn.SINGLE(E:E),样品编号表!H:H,0)))) -> A8784 | H41: 136#奶白色 | I41: 591 | J41: 米 | K41: 600 | L41: 45985 | M41: 13.9 | N41: =K41*M41 -> 8340 | O41: 发票+TC | V41: 开票+证书
A42: 45974 | B42: BTC | E42: SY251062 | F42: =_xlfn.SINGLE(INDEX(样品编号表!Y:Y,_xlfn.SINGLE(MATCH(_xlfn.SINGLE(E:E),样品编号表!H:H,0)))) -> 万顺纺织 | G42: =_xlfn.SINGLE(INDEX(样品编号表!Z:Z,_xlfn.SINGLE(MATCH(_xlfn.SINGLE(E:E),样品编号表!H:H,0)))) -> A8784 | H42: 14#浅粉色 | I42: 182 | J42: 米 | K42: 187 | L42: 45985 | M42: 13.9 | N42: =K42*M42 -> 2599.3 | O42: 发票+TC | V42: 开票+证书
A43: 45974 | B43: BTC | E43: SY251062 | F43: =_xlfn.SINGLE(INDEX(样品编号表!Y:Y,_xlfn.SINGLE(MATCH(_xlfn.SINGLE(E:E),样品编号表!H:H,0)))) -> 万顺纺织 | G43: =_xlfn.SINGLE(INDEX(样品编号表!Z:Z,_xlfn.SINGLE(MATCH(_xlfn.SINGLE(E:E),样品编号表!H:H,0)))) -> A8784 | H43: 15#灰蓝色 | I43: 196 | J43: 米 | K43: 216 | L43: 45985 | M43: 13.9 | N43: =K43*M43 -> 3002.4 | O43: 发票+TC | V43: 开票+证书
A44: 45976 | B44: BTC | E44: SY25419 | F44: =_xlfn.SINGLE(INDEX(样品编号表!Y:Y,_xlfn.SINGLE(MATCH(_xlfn.SINGLE(E:E),样品编号表!H:H,0)))) -> 艺纺 | G44: =_xlfn.SINGLE(INDEX(样品编号表!Z:Z,_xlfn.SINGLE(MATCH(_xlfn.SINGLE(E:E),样品编号表!H:H,0)))) -> 11865-3 | H44: 黑色 | I44: 250 | J44: 米 | K44: 231 | L44: 45997 | M44: 19.6 | N44: =K44*M44 -> 4527.6 | O44: 发票+TC | T44: 12.8 | U44: =K44*T44 -> 2956.8
A45: 45976 | B45: BTC | E45: SY25419 | F45: =_xlfn.SINGLE(INDEX(样品编号表!Y:Y,_xlfn.SINGLE(MATCH(_xlfn.SINGLE(E:E),样品编号表!H:H,0)))) -> 艺纺 | G45: =_xlfn.SINGLE(INDEX(样品编号表!Z:Z,_xlfn.SINGLE(MATCH(_xlfn.SINGLE(E:E),样品编号表!H:H,0)))) -> 11865-3 | H45: 7#石头色 | I45: 201 | J45: 米 | K45: 220 | L45: 45997 | M45: 19.6 | N45: =K45*M45 -> 4312 | O45: 发票+TC | T45: 12.8 | U45: =K45*T45 -> 2816 | V45: 原出货216米退回，重新出220米
A46: 45980 | B46: 韦欣-蔡生 | D46: TFA0221 | E46: SY25287 | F46: =_xlfn.SINGLE(INDEX(样品编号表!Y:Y,_xlfn.SINGLE(MATCH(_xlfn.SINGLE(E:E),样品编号表!H:H,0)))) -> 宝隆纺织 | G46: =_xlfn.SINGLE(INDEX(样品编号表!Z:Z,_xlfn.SINGLE(MATCH(_xlfn.SINGLE(E:E),样品编号表!H:H,0)))) -> 1562 | H46: 9#黑色 | I46: 270 | J46: 米 | K46: 292 | L46: 46004 | M46: 10.6 | N46: =K46*M46 -> 3095.2 | O46: 发票+TC | T46: 6.8 | U46: =K46*T46 -> 1985.6
A47: 45980 | B47: 韦欣-蔡生 | D47: TFA0221 | E47: SY25287 | F47: =_xlfn.SINGLE(INDEX(样品编号表!Y:Y,_xlfn.SINGLE(MATCH(_xlfn.SINGLE(E:E),样品编号表!H:H,0)))) -> 宝隆纺织 | G47: =_xlfn.SINGLE(INDEX(样品编号表!Z:Z,_xlfn.SINGLE(MATCH(_xlfn.SINGLE(E:E),样品编号表!H:H,0)))) -> 1562 | H47: 51#淡蓝色 | I47: 320 | J47: 米 | K47: 363 | L47: 46003 | M47: 10.6 | N47: =K47*M47 -> 3847.8 | O47: 发票+TC | T47: 6.8 | U47: =K47*T47 -> 2468.4
A48: 45980 | B48: 韦欣-小助 | D48: TFA0220 | E48: SY25287 | F48: =_xlfn.SINGLE(INDEX(样品编号表!Y:Y,_xlfn.SINGLE(MATCH(_xlfn.SINGLE(E:E),样品编号表!H:H,0)))) -> 宝隆纺织 | G48: =_xlfn.SINGLE(INDEX(样品编号表!Z:Z,_xlfn.SINGLE(MATCH(_xlfn.SINGLE(E:E),样品编号表!H:H,0)))) -> 1562 | H48: 9#黑色 | I48: 170 | J48: 米 | K48: 148 | L48: 46004 | M48: 10.6 | N48: =K48*M48 -> 1568.8 | O48: 发票+TC | T48: 6.8 | U48: =K48*T48 -> 1006.4
A49: 45980 | B49: 韦欣-小助 | D49: TFA0220 | E49: SY25287 | F49: =_xlfn.SINGLE(INDEX(样品编号表!Y:Y,_xlfn.SINGLE(MATCH(_xlfn.SINGLE(E:E),样品编号表!H:H,0)))) -> 宝隆纺织 | G49: =_xlfn.SINGLE(INDEX(样品编号表!Z:Z,_xlfn.SINGLE(MATCH(_xlfn.SINGLE(E:E),样品编号表!H:H,0)))) -> 1562 | H49: 66#米白色 | I49: 135 | J49: 米 | K49: 137 | L49: 46004 | M49: 10.6 | N49: =K49*M49 -> 1452.2 | O49: 发票+TC | T49: 6.8 | U49: =K49*T49 -> 931.6
A50: 45985 | B50: 韦欣-小助 | E50: SY25773 | F50: =_xlfn.SINGLE(INDEX(样品编号表!Y:Y,_xlfn.SINGLE(MATCH(_xlfn.SINGLE(E:E),样品编号表!H:H,0)))) -> 新合盛布业 | G50: =_xlfn.SINGLE(INDEX(样品编号表!Z:Z,_xlfn.SINGLE(MATCH(_xlfn.SINGLE(E:E),样品编号表!H:H,0)))) -> 6002 | H50: 黑色 | I50: 440 | J50: 米 | K50: 460 | L50: 46004 | M50: 9.2 | N50: =K50*M50 -> 4232 | O50: 发票+TC | T50: 6.6 | U50: =K50*T50 -> 3036
A51: 45986 | B51: 三佰-妮裳 | E51: SY25419 | F51: =_xlfn.SINGLE(INDEX(样品编号表!Y:Y,_xlfn.SINGLE(MATCH(_xlfn.SINGLE(E:E),样品编号表!H:H,0)))) -> 艺纺 | G51: =_xlfn.SINGLE(INDEX(样品编号表!Z:Z,_xlfn.SINGLE(MATCH(_xlfn.SINGLE(E:E),样品编号表!H:H,0)))) -> 11865-3 | H51: 31#黑色 | I51: 1000 | J51: 米 | K51: 996 | L51: 46002 | M51: 19.6 | N51: =K51*M51 -> 19521.6 | O51: 发票+TC | T51: 12.8 | U51: =K51*T51 -> 12748.8
A52: 45986 | B52: 三佰-妮裳 | E52: SY25419 | F52: =_xlfn.SINGLE(INDEX(样品编号表!Y:Y,_xlfn.SINGLE(MATCH(_xlfn.SINGLE(E:E),样品编号表!H:H,0)))) -> 艺纺 | G52: =_xlfn.SINGLE(INDEX(样品编号表!Z:Z,_xlfn.SINGLE(MATCH(_xlfn.SINGLE(E:E),样品编号表!H:H,0)))) -> 11865-3 | H52: 28#巧克力色 | I52: 280 | J52: 米 | K52: 304 | L52: 46002 | M52: 19.6 | N52: =K52*M52 -> 5958.4 | O52: 发票+TC | T52: 12.8 | U52: =K52*T52 -> 3891.2
A53: 45986 | B53: 三佰-妮裳 | E53: SY25419 | F53: =_xlfn.SINGLE(INDEX(样品编号表!Y:Y,_xlfn.SINGLE(MATCH(_xlfn.SINGLE(E:E),样品编号表!H:H,0)))) -> 艺纺 | G53: =_xlfn.SINGLE(INDEX(样品编号表!Z:Z,_xlfn.SINGLE(MATCH(_xlfn.SINGLE(E:E),样品编号表!H:H,0)))) -> 11865-3 | H53: 2#奶油黄 | I53: 200 | J53: 米 | K53: 196 | L53: 46002 | M53: 19.6 | N53: =K53*M53 -> 3841.6 | O53: 发票+TC | T53: 12.8 | U53: =K53*T53 -> 2508.8 | V53: 短码20米，已扣损
A54: 45986 | B54: 三佰-妮裳 | E54: SY25419 | F54: =_xlfn.SINGLE(INDEX(样品编号表!Y:Y,_xlfn.SINGLE(MATCH(_xlfn.SINGLE(E:E),样品编号表!H:H,0)))) -> 艺纺 | G54: =_xlfn.SINGLE(INDEX(样品编号表!Z:Z,_xlfn.SINGLE(MATCH(_xlfn.SINGLE(E:E),样品编号表!H:H,0)))) -> 11865-3 | H54: 22#灰色 | I54: 250 | J54: 米 | K54: 290 | L54: 46002 | M54: 19.6 | N54: =K54*M54 -> 5684 | O54: 发票+TC | T54: 12.8 | U54: =K54*T54 -> 3712
A55: 45987 | B55: 三佰-正恒 | E55: SY25531 | F55: =_xlfn.SINGLE(INDEX(样品编号表!Y:Y,_xlfn.SINGLE(MATCH(_xlfn.SINGLE(E:E),样品编号表!H:H,0)))) -> 凯盛亨 | G55: =_xlfn.SINGLE(INDEX(样品编号表!Z:Z,_xlfn.SINGLE(MATCH(_xlfn.SINGLE(E:E),样品编号表!H:H,0)))) -> 839# | H55: 22#黑色 | I55: 130 | J55: 米 | K55: 135 | L55: 45999 | M55: 15.5 | N55: =K55*M55 -> 2092.5 | O55: 现金+BCI | T55: 11.3 | U55: =K55*T55 -> 1525.5
A56: 45987 | B56: 三佰-正恒 | E56: SY25531 | F56: =_xlfn.SINGLE(INDEX(样品编号表!Y:Y,_xlfn.SINGLE(MATCH(_xlfn.SINGLE(E:E),样品编号表!H:H,0)))) -> 凯盛亨 | G56: =_xlfn.SINGLE(INDEX(样品编号表!Z:Z,_xlfn.SINGLE(MATCH(_xlfn.SINGLE(E:E),样品编号表!H:H,0)))) -> 839# | H56: 9#淡紫色 | I56: 85 | J56: 米 | K56: 87 | L56: 45999 | M56: 15.5 | N56: =K56*M56 -> 1348.5 | O56: 现金+BCI | T56: 11.3 | U56: =K56*T56 -> 983.1
A57: 45987 | B57: 三佰-正恒 | E57: SY25531 | F57: =_xlfn.SINGLE(INDEX(样品编号表!Y:Y,_xlfn.SINGLE(MATCH(_xlfn.SINGLE(E:E),样品编号表!H:H,0)))) -> 凯盛亨 | G57: =_xlfn.SINGLE(INDEX(样品编号表!Z:Z,_xlfn.SINGLE(MATCH(_xlfn.SINGLE(E:E),样品编号表!H:H,0)))) -> 839# | H57: 印花 | I57: 130 | J57: 米 | K57: 125 | L57: 46009 | M57: 27.3 | N57: =K57*M57 -> 3412.5 | O57: 现金+BCI | U57: =K57*T57 -> 0 | V57: 已出货
A58: 45987 | B58: 扑喜 | E58: SY25419 | F58: =_xlfn.SINGLE(INDEX(样品编号表!Y:Y,_xlfn.SINGLE(MATCH(_xlfn.SINGLE(E:E),样品编号表!H:H,0)))) -> 艺纺 | G58: =_xlfn.SINGLE(INDEX(样品编号表!Z:Z,_xlfn.SINGLE(MATCH(_xlfn.SINGLE(E:E),样品编号表!H:H,0)))) -> 11865-3 | H58: 黑色 | I58: 200 | J58: 米 | K58: 199 | L58: 46011 | M58: 19.6 | N58: =K58*M58 -> 3900.4 | O58: 发票+TC | T58: 12.8 | U58: =K58*T58 -> 2547.2
A59: 45987 | B59: 扑喜 | E59: SY25419 | F59: =_xlfn.SINGLE(INDEX(样品编号表!Y:Y,_xlfn.SINGLE(MATCH(_xlfn.SINGLE(E:E),样品编号表!H:H,0)))) -> 艺纺 | G59: =_xlfn.SINGLE(INDEX(样品编号表!Z:Z,_xlfn.SINGLE(MATCH(_xlfn.SINGLE(E:E),样品编号表!H:H,0)))) -> 11865-3 | H59: 22#灰色 | I59: 130 | J59: 米 | K59: 140 | L59: 46011 | M59: 19.6 | N59: =K59*M59 -> 2744 | O59: 发票+TC | T59: 12.8 | U59: =K59*T59 -> 1792
A60: 45988 | B60: 韦欣-小助 | E60: SY25773 | F60: =_xlfn.SINGLE(INDEX(样品编号表!Y:Y,_xlfn.SINGLE(MATCH(_xlfn.SINGLE(E:E),样品编号表!H:H,0)))) -> 新合盛布业 | G60: =_xlfn.SINGLE(INDEX(样品编号表!Z:Z,_xlfn.SINGLE(MATCH(_xlfn.SINGLE(E:E),样品编号表!H:H,0)))) -> 6002 | H60: #248酒红色 | I60: 345 | J60: 米 | K60: 367 | L60: 46010 | M60: 9.2 | N60: =K60*M60 -> 3376.4 | O60: 发票+TC | T60: 6.6 | U60: =T60*K60 -> 2422.2
A61: 45989 | B61: 韦欣-怡鑫 | E61: SY25419 | F61: =_xlfn.SINGLE(INDEX(样品编号表!Y:Y,_xlfn.SINGLE(MATCH(_xlfn.SINGLE(E:E),样品编号表!H:H,0)))) -> 艺纺 | G61: =_xlfn.SINGLE(INDEX(样品编号表!Z:Z,_xlfn.SINGLE(MATCH(_xlfn.SINGLE(E:E),样品编号表!H:H,0)))) -> 11865-3 | H61: 7# | I61: 378 | J61: 米 | K61: 402 | L61: 46009 | M61: 19.6 | N61: =K61*M61 -> 7879.2 | O61: 发票+TC | T61: 12.8 | U61: =K61*T61 -> 5145.6
A62: 45989 | B62: 韦欣-怡鑫 | E62: SY25419 | F62: =_xlfn.SINGLE(INDEX(样品编号表!Y:Y,_xlfn.SINGLE(MATCH(_xlfn.SINGLE(E:E),样品编号表!H:H,0)))) -> 艺纺 | G62: =_xlfn.SINGLE(INDEX(样品编号表!Z:Z,_xlfn.SINGLE(MATCH(_xlfn.SINGLE(E:E),样品编号表!H:H,0)))) -> 11865-3 | H62: 26#酒红色 | I62: 497 | J62: 米 | K62: 542 | L62: 46014 | M62: 19.6 | N62: =K62*M62 -> 10623.2 | O62: 发票+TC | T62: 12.8 | U62: =K62*T62 -> 6937.6
A63: 45989 | B63: 韦欣-怡鑫 | E63: SY25419 | F63: =_xlfn.SINGLE(INDEX(样品编号表!Y:Y,_xlfn.SINGLE(MATCH(_xlfn.SINGLE(E:E),样品编号表!H:H,0)))) -> 艺纺 | G63: =_xlfn.SINGLE(INDEX(样品编号表!Z:Z,_xlfn.SINGLE(MATCH(_xlfn.SINGLE(E:E),样品编号表!H:H,0)))) -> 11865-3 | H63: 31#黑色 | I63: 1078 | J63: 米 | K63: 1063 | L63: 46009 | M63: 19.6 | N63: =K63*M63 -> 20834.8 | O63: 发票+TC | T63: 12.8 | U63: =K63*T63 -> 13606.4 | V63: 2026/1/11反馈2025/12/16出货有一支148米布边异常要退货 2026/1/12重新出货164米，多出的16米付现金
A64: 45993 | B64: 万泰 | E64: SY25733 | F64: =_xlfn.SINGLE(INDEX(样品编号表!Y:Y,_xlfn.SINGLE(MATCH(_xlfn.SINGLE(E:E),样品编号表!H:H,0)))) -> 锦地印染 | G64: =_xlfn.SINGLE(INDEX(样品编号表!Z:Z,_xlfn.SINGLE(MATCH(_xlfn.SINGLE(E:E),样品编号表!H:H,0)))) -> 醋酸金銮缎 | H64: 67#酒红色 | I64: 210 | J64: 米 | K64: 221 | L64: 46017 | M64: 14.2 | N64: =K64*M64 -> 3138.2 | O64: 发票+TC | T64: 10.6 | U64: =K64*T64 -> 2342.6
A65: 45993 | B65: 万泰 | E65: SY25733 | F65: =_xlfn.SINGLE(INDEX(样品编号表!Y:Y,_xlfn.SINGLE(MATCH(_xlfn.SINGLE(E:E),样品编号表!H:H,0)))) -> 锦地印染 | G65: =_xlfn.SINGLE(INDEX(样品编号表!Z:Z,_xlfn.SINGLE(MATCH(_xlfn.SINGLE(E:E),样品编号表!H:H,0)))) -> 醋酸金銮缎 | H65: 38#咖色 | I65: 235 | J65: 米 | K65: 233 | L65: 46017 | M65: 14.2 | N65: =K65*M65 -> 3308.6 | O65: 发票+TC | T65: 10.6 | U65: =K65*T65 -> 2469.8
A66: 45994 | B66: 万泰 | E66: SY251062 | F66: =_xlfn.SINGLE(INDEX(样品编号表!Y:Y,_xlfn.SINGLE(MATCH(_xlfn.SINGLE(E:E),样品编号表!H:H,0)))) -> 万顺纺织 | G66: =_xlfn.SINGLE(INDEX(样品编号表!Z:Z,_xlfn.SINGLE(MATCH(_xlfn.SINGLE(E:E),样品编号表!H:H,0)))) -> A8784 | H66: 黑色 | I66: 300 | J66: 米 | M66: 13.9 | N66: =K66*M66 -> 0 | O66: 发票+TC | V66: 已寄大货样
A67: 45994 | B67: 韦欣-蔡生 | D67: TUS0345 | E67: SY25544 | F67: =_xlfn.SINGLE(INDEX(样品编号表!Y:Y,_xlfn.SINGLE(MATCH(_xlfn.SINGLE(E:E),样品编号表!H:H,0)))) -> 润森 | G67: =_xlfn.SINGLE(INDEX(样品编号表!Z:Z,_xlfn.SINGLE(MATCH(_xlfn.SINGLE(E:E),样品编号表!H:H,0)))) -> 华尔缎 | H67: 61#草绿色 | I67: 250 | J67: 米 | K67: 235 | L67: 46009 | M67: 16.1 | N67: =K67*M67 -> 3783.5 | O67: 发票+TC | T67: 10.3 | U67: =T67*K67 -> 2420.5
A68: 45994 | B68: 韦欣-蔡生 | D68: TUS0346 | E68: SY25544 | F68: =_xlfn.SINGLE(INDEX(样品编号表!Y:Y,_xlfn.SINGLE(MATCH(_xlfn.SINGLE(E:E),样品编号表!H:H,0)))) -> 润森 | G68: =_xlfn.SINGLE(INDEX(样品编号表!Z:Z,_xlfn.SINGLE(MATCH(_xlfn.SINGLE(E:E),样品编号表!H:H,0)))) -> 华尔缎 | H68: 108#黑色 | I68: 170 | J68: 米 | K68: 228 | L68: 46009 | M68: 16.1 | N68: =K68*M68 -> 3670.8 | O68: 发票+TC | T68: 10.3 | U68: =T68*K68 -> 2348.4
A69: 45994 | B69: 韦欣-蔡生 | D69: TUS0346 | E69: SY25544 | F69: =_xlfn.SINGLE(INDEX(样品编号表!Y:Y,_xlfn.SINGLE(MATCH(_xlfn.SINGLE(E:E),样品编号表!H:H,0)))) -> 润森 | G69: =_xlfn.SINGLE(INDEX(样品编号表!Z:Z,_xlfn.SINGLE(MATCH(_xlfn.SINGLE(E:E),样品编号表!H:H,0)))) -> 华尔缎 | H69: 79#红色 | I69: 170 | J69: 米 | K69: 232 | L69: 46014 | M69: 16.1 | N69: =K69*M69 -> 3735.2 | O69: 发票+TC | T69: 10.3 | U69: =T69*K69 -> 2389.6
A70: 45994 | B70: 韦欣-蔡生 | D70: TUS0345 | E70: SY25544 | F70: =_xlfn.SINGLE(INDEX(样品编号表!Y:Y,_xlfn.SINGLE(MATCH(_xlfn.SINGLE(E:E),样品编号表!H:H,0)))) -> 润森 | G70: =_xlfn.SINGLE(INDEX(样品编号表!Z:Z,_xlfn.SINGLE(MATCH(_xlfn.SINGLE(E:E),样品编号表!H:H,0)))) -> 华尔缎 | H70: 112#蓝色 | I70: 280 | J70: 米 | K70: 321 | L70: 46009 | M70: 16.1 | N70: =K70*M70 -> 5168.1 | O70: 发票+TC | T70: 10.3 | U70: =T70*K70 -> 3306.3
A71: 45994 | B71: 三佰-妮裳 | E71: SY251083 | F71: =_xlfn.SINGLE(INDEX(样品编号表!Y:Y,_xlfn.SINGLE(MATCH(_xlfn.SINGLE(E:E),样品编号表!H:H,0)))) -> 新蓝 | G71: =_xlfn.SINGLE(INDEX(样品编号表!Z:Z,_xlfn.SINGLE(MATCH(_xlfn.SINGLE(E:E),样品编号表!H:H,0)))) -> 574# | H71: 2# | I71: 270 | J71: 米 | K71: =277-8 -> 269 | L71: 46018 | M71: 21.1 | N71: =K71*M71 -> 5675.9 | O71: 现金 | T71: 15.6 | U71: =K71*T71 -> 4196.4 | V71: 2025/12/29 脏污/抽纱 扣损8米
A72: 45994 | B72: 三佰-妮裳 | E72: SY251083 | F72: =_xlfn.SINGLE(INDEX(样品编号表!Y:Y,_xlfn.SINGLE(MATCH(_xlfn.SINGLE(E:E),样品编号表!H:H,0)))) -> 新蓝 | G72: =_xlfn.SINGLE(INDEX(样品编号表!Z:Z,_xlfn.SINGLE(MATCH(_xlfn.SINGLE(E:E),样品编号表!H:H,0)))) -> 574# | H72: 3# | I72: 150 | J72: 米 | M72: 21.1 | N72: =K72*M72 -> 0 | O72: 现金 | V72: 已批大货样
A73: 45994 | B73: 三佰-妮裳 | E73: SY251083 | F73: =_xlfn.SINGLE(INDEX(样品编号表!Y:Y,_xlfn.SINGLE(MATCH(_xlfn.SINGLE(E:E),样品编号表!H:H,0)))) -> 新蓝 | G73: =_xlfn.SINGLE(INDEX(样品编号表!Z:Z,_xlfn.SINGLE(MATCH(_xlfn.SINGLE(E:E),样品编号表!H:H,0)))) -> 574# | H73: 40# | I73: 780 | J73: 米 | K73: 785 | L73: 46022 | M73: 21.1 | N73: =K73*M73 -> 16563.5 | O73: 现金 | T73: 15.6 | U73: =K73*T73 -> 12246 | V73: 已确认
A74: 45995 | B74: BTC | E74: SY251062 | F74: =_xlfn.SINGLE(INDEX(样品编号表!Y:Y,_xlfn.SINGLE(MATCH(_xlfn.SINGLE(E:E),样品编号表!H:H,0)))) -> 万顺纺织 | G74: =_xlfn.SINGLE(INDEX(样品编号表!Z:Z,_xlfn.SINGLE(MATCH(_xlfn.SINGLE(E:E),样品编号表!H:H,0)))) -> A8784 | H74: 66#米白色 | I74: 124 | J74: 米 | K74: 124 | L74: 45997 | M74: 13.9 | N74: =K74*M74 -> 1723.6 | O74: 现金 | T74: 8.8 | U74: =K74*T74 -> 1091.2
A75: 45997 | B75: BTC | D75: DAW9687 | E75: SY25738 | F75: =_xlfn.SINGLE(INDEX(样品编号表!Y:Y,_xlfn.SINGLE(MATCH(_xlfn.SINGLE(E:E),样品编号表!H:H,0)))) -> 新嘉彩 | G75: =_xlfn.SINGLE(INDEX(样品编号表!Z:Z,_xlfn.SINGLE(MATCH(_xlfn.SINGLE(E:E),样品编号表!H:H,0)))) -> 938 | H75: 32#黄色 | I75: 175 | J75: 米 | K75: 135 | L75: 46007 | M75: 14.4 | N75: =K75*M75 -> 1944 | O75: 发票+TC | T75: 10.3 | U75: =K75*T75 -> 1390.5
A76: 45997 | B76: BTC | D76: DAW9688 | E76: SY25738 | F76: =_xlfn.SINGLE(INDEX(样品编号表!Y:Y,_xlfn.SINGLE(MATCH(_xlfn.SINGLE(E:E),样品编号表!H:H,0)))) -> 新嘉彩 | G76: =_xlfn.SINGLE(INDEX(样品编号表!Z:Z,_xlfn.SINGLE(MATCH(_xlfn.SINGLE(E:E),样品编号表!H:H,0)))) -> 938 | H76: 32#黄色 | I76: 112 | J76: 米 | K76: 112 | L76: 46007 | M76: 14.4 | N76: =K76*M76 -> 1612.8 | O76: 发票+TC | T76: 10.3 | U76: =K76*T76 -> 1153.6
A77: 45997 | B77: BTC | D77: DAW9687 | E77: SY25738 | F77: =_xlfn.SINGLE(INDEX(样品编号表!Y:Y,_xlfn.SINGLE(MATCH(_xlfn.SINGLE(E:E),样品编号表!H:H,0)))) -> 新嘉彩 | G77: =_xlfn.SINGLE(INDEX(样品编号表!Z:Z,_xlfn.SINGLE(MATCH(_xlfn.SINGLE(E:E),样品编号表!H:H,0)))) -> 938 | H77: 63#白色 | I77: 290 | J77: 米 | K77: 332 | L77: 46013 | M77: 14.4 | N77: =K77*M77 -> 4780.8 | O77: 发票+TC | T77: 10.3 | U77: =K77*T77 -> 3419.6
A78: 45997 | B78: BTC | D78: DAW9686 | E78: SY25738 | F78: =_xlfn.SINGLE(INDEX(样品编号表!Y:Y,_xlfn.SINGLE(MATCH(_xlfn.SINGLE(E:E),样品编号表!H:H,0)))) -> 新嘉彩 | G78: =_xlfn.SINGLE(INDEX(样品编号表!Z:Z,_xlfn.SINGLE(MATCH(_xlfn.SINGLE(E:E),样品编号表!H:H,0)))) -> 938 | H78: 63#白色 | I78: 81 | J78: 米 | K78: 107 | L78: 46013 | M78: 14.4 | N78: =K78*M78 -> 1540.8 | O78: 发票+TC | T78: 10.3 | U78: =K78*T78 -> 1102.1
A79: 45997 | B79: BTC | D79: DAW9688 | E79: SY25738 | F79: =_xlfn.SINGLE(INDEX(样品编号表!Y:Y,_xlfn.SINGLE(MATCH(_xlfn.SINGLE(E:E),样品编号表!H:H,0)))) -> 新嘉彩 | G79: =_xlfn.SINGLE(INDEX(样品编号表!Z:Z,_xlfn.SINGLE(MATCH(_xlfn.SINGLE(E:E),样品编号表!H:H,0)))) -> 938 | H79: 63#白色 | I79: 296 | J79: 米 | K79: 301 | L79: 46013 | M79: 14.4 | N79: =K79*M79 -> 4334.4 | O79: 发票+TC | T79: 10.3 | U79: =K79*T79 -> 3100.3
A80: 45997 | B80: BTC | D80: DAW9687 | E80: SY25738 | F80: =_xlfn.SINGLE(INDEX(样品编号表!Y:Y,_xlfn.SINGLE(MATCH(_xlfn.SINGLE(E:E),样品编号表!H:H,0)))) -> 新嘉彩 | G80: =_xlfn.SINGLE(INDEX(样品编号表!Z:Z,_xlfn.SINGLE(MATCH(_xlfn.SINGLE(E:E),样品编号表!H:H,0)))) -> 938 | H80: 120#棕色 | I80: 348 | J80: 米 | K80: 366 | L80: 46007 | M80: 14.4 | N80: =K80*M80 -> 5270.4 | O80: 发票+TC | T80: 10.3 | U80: =K80*T80 -> 3769.8
A81: 45997 | B81: BTC | D81: DAW9686 | E81: SY25738 | F81: =_xlfn.SINGLE(INDEX(样品编号表!Y:Y,_xlfn.SINGLE(MATCH(_xlfn.SINGLE(E:E),样品编号表!H:H,0)))) -> 新嘉彩 | G81: =_xlfn.SINGLE(INDEX(样品编号表!Z:Z,_xlfn.SINGLE(MATCH(_xlfn.SINGLE(E:E),样品编号表!H:H,0)))) -> 938 | H81: 120#棕色 | I81: 81 | J81: 米 | K81: 100 | L81: 46007 | M81: 14.4 | N81: =K81*M81 -> 1440 | O81: 发票+TC | T81: 10.3 | U81: =K81*T81 -> 1030
A82: 45997 | B82: BTC | D82: DAW9688 | E82: SY25738 | F82: =_xlfn.SINGLE(INDEX(样品编号表!Y:Y,_xlfn.SINGLE(MATCH(_xlfn.SINGLE(E:E),样品编号表!H:H,0)))) -> 新嘉彩 | G82: =_xlfn.SINGLE(INDEX(样品编号表!Z:Z,_xlfn.SINGLE(MATCH(_xlfn.SINGLE(E:E),样品编号表!H:H,0)))) -> 938 | H82: 120#棕色 | I82: 373 | J82: 米 | K82: 391 | L82: 46007 | M82: 14.4 | N82: =K82*M82 -> 5630.4 | O82: 发票+TC | T82: 10.3 | U82: =K82*T82 -> 4027.3
A83: 45997 | B83: BTC | D83: DAW9687 | E83: SY25738 | F83: =_xlfn.SINGLE(INDEX(样品编号表!Y:Y,_xlfn.SINGLE(MATCH(_xlfn.SINGLE(E:E),样品编号表!H:H,0)))) -> 新嘉彩 | G83: =_xlfn.SINGLE(INDEX(样品编号表!Z:Z,_xlfn.SINGLE(MATCH(_xlfn.SINGLE(E:E),样品编号表!H:H,0)))) -> 938 | H83: 77#蓝色 | I83: 117 | J83: 米 | K83: 132 | L83: 46007 | M83: 14.4 | N83: =K83*M83 -> 1900.8 | O83: 发票+TC | T83: 10.3 | U83: =K83*T83 -> 1359.6
A84: 45997 | B84: BTC | C84: KAT17833 | D84: WAAT003173 | E84: SY251429 | F84: =_xlfn.SINGLE(INDEX(样品编号表!Y:Y,_xlfn.SINGLE(MATCH(_xlfn.SINGLE(E:E),样品编号表!H:H,0)))) -> 粤信布业 | G84: =_xlfn.SINGLE(INDEX(样品编号表!Z:Z,_xlfn.SINGLE(MATCH(_xlfn.SINGLE(E:E),样品编号表!H:H,0)))) -> 32支精棉拉架YX81010 | H84: 13#白/咖条纹 | I84: 92 | J84: 米 | K84: 91 | L84: 46004 | M84: 20 | N84: =K84*M84 -> 1820 | O84: 发票+BCI | T84: 44 | U84: =T84*24.2 -> 1064.8
A85: 45997 | B85: BTC | C85: KAT17843 | D85: WAAT003174 | E85: SY251429 | F85: =_xlfn.SINGLE(INDEX(样品编号表!Y:Y,_xlfn.SINGLE(MATCH(_xlfn.SINGLE(E:E),样品编号表!H:H,0)))) -> 粤信布业 | G85: =_xlfn.SINGLE(INDEX(样品编号表!Z:Z,_xlfn.SINGLE(MATCH(_xlfn.SINGLE(E:E),样品编号表!H:H,0)))) -> 32支精棉拉架YX81010 | H85: 13#白/咖条纹 | I85: 53 | J85: 米 | K85: 53 | L85: 46004 | M85: 20 | N85: =K85*M85 -> 1060 | O85: 发票+BCI | T85: 44 | U85: =T85*16.9 -> 743.6
A86: 45997 | B86: BTC | C86: KAT17834 | D86: WAAT003211 | E86: SY251429 | F86: =_xlfn.SINGLE(INDEX(样品编号表!Y:Y,_xlfn.SINGLE(MATCH(_xlfn.SINGLE(E:E),样品编号表!H:H,0)))) -> 粤信布业 | G86: =_xlfn.SINGLE(INDEX(样品编号表!Z:Z,_xlfn.SINGLE(MATCH(_xlfn.SINGLE(E:E),样品编号表!H:H,0)))) -> 32支精棉拉架YX81010 | H86: 13#白/咖条纹 | I86: 135 | J86: 米 | K86: 135 | L86: 46004 | M86: 20 | N86: =K86*M86 -> 2700 | O86: 发票+BCI | T86: 44 | U86: =T86*47.8 -> 2103.2
A87: 45997 | B87: BTC | C87: KAT17843 | D87: WAAT003174 | E87: SY251429 | F87: =_xlfn.SINGLE(INDEX(样品编号表!Y:Y,_xlfn.SINGLE(MATCH(_xlfn.SINGLE(E:E),样品编号表!H:H,0)))) -> 粤信布业 | G87: =_xlfn.SINGLE(INDEX(样品编号表!Z:Z,_xlfn.SINGLE(MATCH(_xlfn.SINGLE(E:E),样品编号表!H:H,0)))) -> 32支精棉拉架YX81010 | H87: 4#白/红条纹 | I87: 53 | J87: 米 | K87: 64 | L87: 46004 | M87: 20 | N87: =K87*M87 -> 1280 | O87: 发票+BCI | T87: 44 | U87: =T87*21.1 -> 928.4
A88: 45997 | B88: BTC | C88: KAT17834 | D88: WAAT003211 | E88: SY251429 | F88: =_xlfn.SINGLE(INDEX(样品编号表!Y:Y,_xlfn.SINGLE(MATCH(_xlfn.SINGLE(E:E),样品编号表!H:H,0)))) -> 粤信布业 | G88: =_xlfn.SINGLE(INDEX(样品编号表!Z:Z,_xlfn.SINGLE(MATCH(_xlfn.SINGLE(E:E),样品编号表!H:H,0)))) -> 32支精棉拉架YX81010 | H88: 26#白/宝蓝条纹 | I88: 201 | J88: 米 | K88: 229 | L88: 46004 | M88: 20 | N88: =K88*M88 -> 4580 | O88: 发票+BCI | T88: 44 | U88: =T88*73 -> 3212
A89: 45997 | B89: BTC | C89: WAAT003175 | D89: KAT17841 | E89: SY251093 | F89: =_xlfn.SINGLE(INDEX(样品编号表!Y:Y,_xlfn.SINGLE(MATCH(_xlfn.SINGLE(E:E),样品编号表!H:H,0)))) -> 东盛恒旺布行 | G89: =_xlfn.SINGLE(INDEX(样品编号表!Z:Z,_xlfn.SINGLE(MATCH(_xlfn.SINGLE(E:E),样品编号表!H:H,0)))) -> 13210# | H89: 7#酒红色 | I89: 161 | J89: 米 | K89: 165 | L89: 46009 | M89: 16.8 | N89: =K89*M89 -> 2772 | O89: 发票+BCI
A90: 45997 | B90: BTC | C90: WAAT003177 | D90: KAT17827 | E90: SY251093 | F90: =_xlfn.SINGLE(INDEX(样品编号表!Y:Y,_xlfn.SINGLE(MATCH(_xlfn.SINGLE(E:E),样品编号表!H:H,0)))) -> 东盛恒旺布行 | G90: =_xlfn.SINGLE(INDEX(样品编号表!Z:Z,_xlfn.SINGLE(MATCH(_xlfn.SINGLE(E:E),样品编号表!H:H,0)))) -> 13210# | H90: 7#酒红色 | I90: 224 | J90: 米 | K90: 237 | L90: 46009 | M90: 16.8 | N90: =K90*M90 -> 3981.6 | O90: 发票+BCI
A91: 45997 | B91: BTC | C91: WAAT003178 | D91: KAT17826 | E91: SY251093 | F91: =_xlfn.SINGLE(INDEX(样品编号表!Y:Y,_xlfn.SINGLE(MATCH(_xlfn.SINGLE(E:E),样品编号表!H:H,0)))) -> 东盛恒旺布行 | G91: =_xlfn.SINGLE(INDEX(样品编号表!Z:Z,_xlfn.SINGLE(MATCH(_xlfn.SINGLE(E:E),样品编号表!H:H,0)))) -> 13210# | H91: 7#酒红色 | I91: 170 | J91: 米 | K91: 184 | L91: 46009 | M91: 16.8 | N91: =K91*M91 -> 3091.2 | O91: 发票+BCI
A92: 45997 | B92: BTC | C92: WAAT003175 | D92: KAT17841 | E92: SY251093 | F92: =_xlfn.SINGLE(INDEX(样品编号表!Y:Y,_xlfn.SINGLE(MATCH(_xlfn.SINGLE(E:E),样品编号表!H:H,0)))) -> 东盛恒旺布行 | G92: =_xlfn.SINGLE(INDEX(样品编号表!Z:Z,_xlfn.SINGLE(MATCH(_xlfn.SINGLE(E:E),样品编号表!H:H,0)))) -> 13210# | H92: 2#黑色 | I92: 241 | J92: 米 | K92: 258 | L92: 46009 | M92: 16.8 | N92: =K92*M92 -> 4334.4 | O92: 发票+BCI
A93: 45997 | B93: BTC | C93: WAAT003176 | D93: KAT17825 | E93: SY251093 | F93: =_xlfn.SINGLE(INDEX(样品编号表!Y:Y,_xlfn.SINGLE(MATCH(_xlfn.SINGLE(E:E),样品编号表!H:H,0)))) -> 东盛恒旺布行 | G93: =_xlfn.SINGLE(INDEX(样品编号表!Z:Z,_xlfn.SINGLE(MATCH(_xlfn.SINGLE(E:E),样品编号表!H:H,0)))) -> 13210# | H93: 2#黑色 | I93: 99 | J93: 米 | K93: 92 | L93: 46009 | M93: 16.8 | N93: =K93*M93 -> 1545.6 | O93: 发票+BCI
A94: 45997 | B94: BTC | C94: WAAT003177 | D94: KAT17827 | E94: SY251093 | F94: =_xlfn.SINGLE(INDEX(样品编号表!Y:Y,_xlfn.SINGLE(MATCH(_xlfn.SINGLE(E:E),样品编号表!H:H,0)))) -> 东盛恒旺布行 | G94: =_xlfn.SINGLE(INDEX(样品编号表!Z:Z,_xlfn.SINGLE(MATCH(_xlfn.SINGLE(E:E),样品编号表!H:H,0)))) -> 13210# | H94: 2#黑色 | I94: 335 | J94: 米 | K94: 347 | L94: 46009 | M94: 16.8 | N94: =K94*M94 -> 5829.6 | O94: 发票+BCI
A95: 45997 | B95: BTC | C95: WAAT003178 | D95: KAT17826 | E95: SY251093 | F95: =_xlfn.SINGLE(INDEX(样品编号表!Y:Y,_xlfn.SINGLE(MATCH(_xlfn.SINGLE(E:E),样品编号表!H:H,0)))) -> 东盛恒旺布行 | G95: =_xlfn.SINGLE(INDEX(样品编号表!Z:Z,_xlfn.SINGLE(MATCH(_xlfn.SINGLE(E:E),样品编号表!H:H,0)))) -> 13210# | H95: 2#黑色 | I95: 253 | J95: 米 | K95: 272 | L95: 46009 | M95: 16.8 | N95: =K95*M95 -> 4569.6 | O95: 发票+BCI
A96: 45997 | B96: BTC | C96: WAAT003175 | D96: KAT17841 | E96: SY251093 | F96: =_xlfn.SINGLE(INDEX(样品编号表!Y:Y,_xlfn.SINGLE(MATCH(_xlfn.SINGLE(E:E),样品编号表!H:H,0)))) -> 东盛恒旺布行 | G96: =_xlfn.SINGLE(INDEX(样品编号表!Z:Z,_xlfn.SINGLE(MATCH(_xlfn.SINGLE(E:E),样品编号表!H:H,0)))) -> 13210# | H96: 17#大白色 | I96: 241 | J96: 米 | K96: 274 | L96: 46009 | M96: 16.8 | N96: =K96*M96 -> 4603.2 | O96: 发票+BCI
A97: 45997 | B97: BTC | C97: WAAT003176 | D97: KAT17825 | E97: SY251093 | F97: =_xlfn.SINGLE(INDEX(样品编号表!Y:Y,_xlfn.SINGLE(MATCH(_xlfn.SINGLE(E:E),样品编号表!H:H,0)))) -> 东盛恒旺布行 | G97: =_xlfn.SINGLE(INDEX(样品编号表!Z:Z,_xlfn.SINGLE(MATCH(_xlfn.SINGLE(E:E),样品编号表!H:H,0)))) -> 13210# | H97: 17#大白色 | I97: 99 | J97: 米 | K97: 94 | L97: 46009 | M97: 16.8 | N97: =K97*M97 -> 1579.2 | O97: 发票+BCI
A98: 45999 | B98: BTC | D98: WATQTM022/WATQTM022C | E98: SY251062 | F98: =_xlfn.SINGLE(INDEX(样品编号表!Y:Y,_xlfn.SINGLE(MATCH(_xlfn.SINGLE(E:E),样品编号表!H:H,0)))) -> 万顺纺织 | G98: =_xlfn.SINGLE(INDEX(样品编号表!Z:Z,_xlfn.SINGLE(MATCH(_xlfn.SINGLE(E:E),样品编号表!H:H,0)))) -> A8784 | H98: 黑色 | I98: 691 | J98: 米 | K98: 651 | L98: 46013 | M98: 13.9 | N98: =K98*M98 -> 9048.9 | O98: 开票+TC | T98: 8.8 | U98: =K98*T98 -> 5728.8
A99: 45999 | B99: BTC | D99: WATQTM022/WATQTM022C | E99: SY251062 | F99: =_xlfn.SINGLE(INDEX(样品编号表!Y:Y,_xlfn.SINGLE(MATCH(_xlfn.SINGLE(E:E),样品编号表!H:H,0)))) -> 万顺纺织 | G99: =_xlfn.SINGLE(INDEX(样品编号表!Z:Z,_xlfn.SINGLE(MATCH(_xlfn.SINGLE(E:E),样品编号表!H:H,0)))) -> A8784 | H99: 14#粉色 | I99: 433 | J99: 米 | K99: 443 | L99: 46013 | M99: 13.9 | N99: =K99*M99 -> 6157.7 | O99: 开票+TC | T99: 8.8 | U99: =K99*T99 -> 3898.4
A100: 45999 | B100: BTC | C100: WAAT003060 | D100: WATQTM030 | E100: SY25419 | F100: =_xlfn.SINGLE(INDEX(样品编号表!Y:Y,_xlfn.SINGLE(MATCH(_xlfn.SINGLE(E:E),样品编号表!H:H,0)))) -> 艺纺 | G100: =_xlfn.SINGLE(INDEX(样品编号表!Z:Z,_xlfn.SINGLE(MATCH(_xlfn.SINGLE(E:E),样品编号表!H:H,0)))) -> 11865-3 | H100: 31#黑色 | I100: 197 | J100: 米 | K100: 208 | L100: 46015 | M100: 19.6 | N100: =K100*M100 -> 4076.8 | O100: 开票+TC | T100: 12.8 | U100: =K100*T100 -> 2662.4
...

Sheet 留底
A1: 日期 | B1: 加工厂 | C1: 订单类型 | D1: 布种编号 | E1: 供应商 | F1: 编号 | G1: 颜色 | H1: 数量 | I1: 单位 | J1: 采购价 | K1: 金额 | L1: 备注
A2: 45775 | B2: XXL | C2: 留底 | D2: SY25016 | E2: =_xlfn.SINGLE(INDEX(样品编号表!Y:Y,_xlfn.SINGLE(MATCH(_xlfn.SINGLE(D:D),样品编号表!H:H,0)))) -> 光大纺织 | F2: =_xlfn.SINGLE(INDEX(样品编号表!Z:Z,_xlfn.SINGLE(MATCH(_xlfn.SINGLE(D:D),样品编号表!H:H,0)))) -> C580 | G2: 15# | H2: 1 | I2: 米 | J2: 14 | K2: =H2*J2 -> 14
A3: 45793 | B3: XXL | C3: 留底 | D3: SP25032 | E3: =_xlfn.SINGLE(INDEX(样品编号表!Y:Y,_xlfn.SINGLE(MATCH(_xlfn.SINGLE(D:D),样品编号表!H:H,0)))) -> 昌勋纺织 | F3: =_xlfn.SINGLE(INDEX(样品编号表!Z:Z,_xlfn.SINGLE(MATCH(_xlfn.SINGLE(D:D),样品编号表!H:H,0)))) -> C734 | G3: 32# | H3: 1 | I3: 米 | J3: 14 | K3: =H3*J3 -> 14
A4: 45814 | B4: XXL | C4: 留底 | D4: SC25020-14 | E4: =_xlfn.SINGLE(INDEX(样品编号表!Y:Y,_xlfn.SINGLE(MATCH(_xlfn.SINGLE(D:D),样品编号表!H:H,0)))) -> 金绣 | F4: =_xlfn.SINGLE(INDEX(样品编号表!Z:Z,_xlfn.SINGLE(MATCH(_xlfn.SINGLE(D:D),样品编号表!H:H,0)))) -> A2185 | G4: 白色 | H4: 1 | I4: 米 | J4: 33 | K4: 25
A5: 45814 | B5: XXL | C5: 留底 | D5: SC25020-2 | E5: =_xlfn.SINGLE(INDEX(样品编号表!Y:Y,_xlfn.SINGLE(MATCH(_xlfn.SINGLE(D:D),样品编号表!H:H,0)))) -> 真成纺织 | F5: =_xlfn.SINGLE(INDEX(样品编号表!Z:Z,_xlfn.SINGLE(MATCH(_xlfn.SINGLE(D:D),样品编号表!H:H,0)))) -> B-894 | G5: 白色 | H5: 1 | I5: 米 | J5: 33.7 | K5: 25
A6: 45817 | B6: XXL | C6: 留底 | D6: SY25063 | E6: =_xlfn.SINGLE(INDEX(样品编号表!Y:Y,_xlfn.SINGLE(MATCH(_xlfn.SINGLE(D:D),样品编号表!H:H,0)))) -> 年年发纺织 | F6: =_xlfn.SINGLE(INDEX(样品编号表!Z:Z,_xlfn.SINGLE(MATCH(_xlfn.SINGLE(D:D),样品编号表!H:H,0)))) -> 303# | G6: 4#米黄色 | H6: 1 | I6: 米 | J6: 21 | K6: 16
A7: 45776 | B7: XXL | C7: 留底 | D7: SP25035 | E7: =_xlfn.SINGLE(INDEX(样品编号表!Y:Y,_xlfn.SINGLE(MATCH(_xlfn.SINGLE(D:D),样品编号表!H:H,0)))) -> 华联 | F7: =_xlfn.SINGLE(INDEX(样品编号表!Z:Z,_xlfn.SINGLE(MATCH(_xlfn.SINGLE(D:D),样品编号表!H:H,0)))) -> 3926-10# | G7: 70# | H7: 2 | I7: 米 | J7: 18 | K7: =H7*J7 -> 36
A8: 45776 | B8: XXL | C8: 留底 | E8: 华强纺织 | F8: 8265-1 | G8: 37# | H8: 1 | I8: 米 | J8: 14 | K8: =H8*J8 -> 14
A9: 45776 | B9: XXL | C9: 留底 | E9: 华强纺织 | F9: 8265-1 | G9: 38# | H9: 1 | I9: 米 | J9: 14 | K9: =H9*J9 -> 14
A10: 45791 | B10: XXL | C10: 留底 | D10: SY25066 | E10: =_xlfn.SINGLE(INDEX(样品编号表!Y:Y,_xlfn.SINGLE(MATCH(_xlfn.SINGLE(D:D),样品编号表!H:H,0)))) -> 展业布行 | F10: =_xlfn.SINGLE(INDEX(样品编号表!Z:Z,_xlfn.SINGLE(MATCH(_xlfn.SINGLE(D:D),样品编号表!H:H,0)))) -> ZY138# | G10: 59# | H10: 1 | I10: 米 | J10: 30 | K10: =H10*J10 -> 30
A11: 45791 | B11: XXL | C11: 留底 | D11: SY25069 | E11: =_xlfn.SINGLE(INDEX(样品编号表!Y:Y,_xlfn.SINGLE(MATCH(_xlfn.SINGLE(D:D),样品编号表!H:H,0)))) -> 东盛恒旺布行 | F11: =_xlfn.SINGLE(INDEX(样品编号表!Z:Z,_xlfn.SINGLE(MATCH(_xlfn.SINGLE(D:D),样品编号表!H:H,0)))) -> 39008# | G11: 137# | H11: 1 | I11: 米 | J11: 30 | K11: =H11*J11 -> 30
A12: 45799 | B12: XXL | C12: 留底 | D12: SC25022 | E12: =_xlfn.SINGLE(INDEX(样品编号表!Y:Y,_xlfn.SINGLE(MATCH(_xlfn.SINGLE(D:D),样品编号表!H:H,0)))) -> 欧纺时尚 | F12: =_xlfn.SINGLE(INDEX(样品编号表!Z:Z,_xlfn.SINGLE(MATCH(_xlfn.SINGLE(D:D),样品编号表!H:H,0)))) -> 686#（金丝棉） | G12: 白色 | H12: 1 | I12: 米 | J12: 10 | K12: =H12*J12 -> 10
A13: 45799 | B13: XXL | C13: 留底 | D13: SP25040 | E13: =_xlfn.SINGLE(INDEX(样品编号表!Y:Y,_xlfn.SINGLE(MATCH(_xlfn.SINGLE(D:D),样品编号表!H:H,0)))) -> 欧纺时尚 | F13: =_xlfn.SINGLE(INDEX(样品编号表!Z:Z,_xlfn.SINGLE(MATCH(_xlfn.SINGLE(D:D),样品编号表!H:H,0)))) -> 75D全光 | G13: 白色 | H13: 1 | I13: 米 | J13: 12 | K13: =H13*J13 -> 12
A14: 45799 | B14: XXL | C14: 留底 | D14: SP25039 | E14: =_xlfn.SINGLE(INDEX(样品编号表!Y:Y,_xlfn.SINGLE(MATCH(_xlfn.SINGLE(D:D),样品编号表!H:H,0)))) -> 欧纺时尚 | F14: =_xlfn.SINGLE(INDEX(样品编号表!Z:Z,_xlfn.SINGLE(MATCH(_xlfn.SINGLE(D:D),样品编号表!H:H,0)))) -> 50D全光加厚 | G14: 白色 | H14: 1 | I14: 米 | J14: 12 | K14: =H14*J14 -> 12
A15: 45799 | B15: XXL | C15: 留底 | D15: SP25041 | E15: =_xlfn.SINGLE(INDEX(样品编号表!Y:Y,_xlfn.SINGLE(MATCH(_xlfn.SINGLE(D:D),样品编号表!H:H,0)))) -> 精品里布 | F15: =_xlfn.SINGLE(INDEX(样品编号表!Z:Z,_xlfn.SINGLE(MATCH(_xlfn.SINGLE(D:D),样品编号表!H:H,0)))) -> 加舒美绸 | G15: 白色 | H15: 1 | I15: 米 | J15: 6 | K15: =H15*J15 -> 6
A16: 45799 | B16: XXL | C16: 留底 | D16: SP25042 | E16: =_xlfn.SINGLE(INDEX(样品编号表!Y:Y,_xlfn.SINGLE(MATCH(_xlfn.SINGLE(D:D),样品编号表!H:H,0)))) -> 精品里布 | F16: =_xlfn.SINGLE(INDEX(样品编号表!Z:Z,_xlfn.SINGLE(MATCH(_xlfn.SINGLE(D:D),样品编号表!H:H,0)))) -> 精品韩国里 （加韩）80克 | G16: 白色 | H16: 1 | I16: 米 | J16: 5 | K16: =H16*J16 -> 5
A17: 45799 | B17: XXL | C17: 留底 | D17: SP25044 | E17: =_xlfn.SINGLE(INDEX(样品编号表!Y:Y,_xlfn.SINGLE(MATCH(_xlfn.SINGLE(D:D),样品编号表!H:H,0)))) -> 精品里布 | F17: =_xlfn.SINGLE(INDEX(样品编号表!Z:Z,_xlfn.SINGLE(MATCH(_xlfn.SINGLE(D:D),样品编号表!H:H,0)))) -> 50D超柔四面弹（88克） | G17: 白色 | H17: 1 | I17: 米 | J17: 5 | K17: =H17*J17 -> 5
A18: 45799 | B18: XXL | C18: 留底 | D18: SP25043 | E18: =_xlfn.SINGLE(INDEX(样品编号表!Y:Y,_xlfn.SINGLE(MATCH(_xlfn.SINGLE(D:D),样品编号表!H:H,0)))) -> 精品里布 | F18: =_xlfn.SINGLE(INDEX(样品编号表!Z:Z,_xlfn.SINGLE(MATCH(_xlfn.SINGLE(D:D),样品编号表!H:H,0)))) -> 加密仿人丝（加舒）110克 | G18: 白色 | H18: 1 | I18: 米 | J18: 12 | K18: =H18*J18 -> 12
A19: 45812 | B19: XXL | C19: 留底 | D19: SP25036 | E19: =_xlfn.SINGLE(INDEX(样品编号表!Y:Y,_xlfn.SINGLE(MATCH(_xlfn.SINGLE(D:D),样品编号表!H:H,0)))) -> 汇美纺织 | F19: =_xlfn.SINGLE(INDEX(样品编号表!Z:Z,_xlfn.SINGLE(MATCH(_xlfn.SINGLE(D:D),样品编号表!H:H,0)))) -> H6835-1 | G19: 3# | H19: 1 | I19: 米 | J19: 19 | K19: =H19*J19 -> 19
A20: 45812 | B20: XXL | C20: 留底 | D20: SY25064 | E20: =_xlfn.SINGLE(INDEX(样品编号表!Y:Y,_xlfn.SINGLE(MATCH(_xlfn.SINGLE(D:D),样品编号表!H:H,0)))) -> 新伟兴纺织 | F20: =_xlfn.SINGLE(INDEX(样品编号表!Z:Z,_xlfn.SINGLE(MATCH(_xlfn.SINGLE(D:D),样品编号表!H:H,0)))) -> A13518 | G20: 2# | H20: 1 | I20: 米 | J20: 46 | K20: =H20*J20 -> 46
A21: 45812 | B21: XXL | C21: 留底 | D21: SP25037 | E21: =_xlfn.SINGLE(INDEX(样品编号表!Y:Y,_xlfn.SINGLE(MATCH(_xlfn.SINGLE(D:D),样品编号表!H:H,0)))) -> 新蓝 | F21: =_xlfn.SINGLE(INDEX(样品编号表!Z:Z,_xlfn.SINGLE(MATCH(_xlfn.SINGLE(D:D),样品编号表!H:H,0)))) -> 512# | G21: 114# | H21: 1 | I21: 米 | J21: 14 | K21: =H21*J21 -> 14
A22: 45815 | B22: XXL | C22: 留底 | E22: 韦恩纺织 | F22: W3168 | G22: 100#黑色 | H22: 1 | I22: 米 | J22: 20 | K22: =H22*J22 -> 20 | L22: Cheryl调样
A23: 45832 | B23: XXL | C23: 留底 | D23: SY25016 | E23: =_xlfn.SINGLE(INDEX(样品编号表!Y:Y,_xlfn.SINGLE(MATCH(_xlfn.SINGLE(D:D),样品编号表!H:H,0)))) -> 光大纺织 | F23: =_xlfn.SINGLE(INDEX(样品编号表!Z:Z,_xlfn.SINGLE(MATCH(_xlfn.SINGLE(D:D),样品编号表!H:H,0)))) -> C580 | G23: 白色 | H23: 10 | I23: 米 | J23: 15 | K23: =H23*J23 -> 150 | L23: 印花打样
A24: 45832 | B24: XXL | C24: 留底 | D24: SY25531 | E24: =_xlfn.SINGLE(INDEX(样品编号表!Y:Y,_xlfn.SINGLE(MATCH(_xlfn.SINGLE(D:D),样品编号表!H:H,0)))) -> 凯盛亨 | F24: =_xlfn.SINGLE(INDEX(样品编号表!Z:Z,_xlfn.SINGLE(MATCH(_xlfn.SINGLE(D:D),样品编号表!H:H,0)))) -> 839# | G24: 白色 | H24: 10 | I24: 米 | J24: 16 | K24: =H24*J24 -> 160 | L24: 印花打样
A25: 45832 | B25: XXL | C25: 留底 | D25: SY25532 | E25: =_xlfn.SINGLE(INDEX(样品编号表!Y:Y,_xlfn.SINGLE(MATCH(_xlfn.SINGLE(D:D),样品编号表!H:H,0)))) -> 凯盛亨 | F25: =_xlfn.SINGLE(INDEX(样品编号表!Z:Z,_xlfn.SINGLE(MATCH(_xlfn.SINGLE(D:D),样品编号表!H:H,0)))) -> 649# | G25: 白色 | H25: 10 | I25: 米 | J25: 16 | K25: =H25*J25 -> 160 | L25: 印花打样
A26: 45832 | B26: XXL | C26: 留底 | D26: SY25534 | E26: =_xlfn.SINGLE(INDEX(样品编号表!Y:Y,_xlfn.SINGLE(MATCH(_xlfn.SINGLE(D:D),样品编号表!H:H,0)))) -> 宏丰棉麻 | F26: =_xlfn.SINGLE(INDEX(样品编号表!Z:Z,_xlfn.SINGLE(MATCH(_xlfn.SINGLE(D:D),样品编号表!H:H,0)))) -> 045 | G26: 白色 | H26: 10 | I26: 米 | J26: 16 | K26: =H26*J26 -> 160 | L26: 印花打样
A27: 45832 | B27: XXL | C27: 留底 | D27: SY25536 | E27: =_xlfn.SINGLE(INDEX(样品编号表!Y:Y,_xlfn.SINGLE(MATCH(_xlfn.SINGLE(D:D),样品编号表!H:H,0)))) -> 年年发纺织 | F27: =_xlfn.SINGLE(INDEX(样品编号表!Z:Z,_xlfn.SINGLE(MATCH(_xlfn.SINGLE(D:D),样品编号表!H:H,0)))) -> HC12支/12支竹节 | G27: 白色 | H27: 10 | I27: 米 | J27: 16 | K27: =H27*J27 -> 160 | L27: 印花打样
A28: 45839 | B28: XXL | C28: 留底 | E28: 福泰里布 | F28: 高密油丁 | G28: 红色 | H28: 4 | I28: 米 | J28: 8 | K28: =H28*J28 -> 32 | L28: 校服
A29: 45861 | B29: XXL | C29: 留底 | D29: SY25063 | E29: =_xlfn.SINGLE(INDEX(样品编号表!Y:Y,_xlfn.SINGLE(MATCH(_xlfn.SINGLE(D:D),样品编号表!H:H,0)))) -> 年年发纺织 | F29: =_xlfn.SINGLE(INDEX(样品编号表!Z:Z,_xlfn.SINGLE(MATCH(_xlfn.SINGLE(D:D),样品编号表!H:H,0)))) -> 303# | G29: 35#绿色 | H29: 1 | I29: 米 | J29: 16 | K29: =H29*J29 -> 16 | L29: 大货样
A30: 45889 | B30: XXL | C30: 留底 | D30: SY25531 | E30: =_xlfn.SINGLE(INDEX(样品编号表!Y:Y,_xlfn.SINGLE(MATCH(_xlfn.SINGLE(D:D),样品编号表!H:H,0)))) -> 凯盛亨 | F30: =_xlfn.SINGLE(INDEX(样品编号表!Z:Z,_xlfn.SINGLE(MATCH(_xlfn.SINGLE(D:D),样品编号表!H:H,0)))) -> 839# | G30: 43#黄油色 | H30: 2 | I30: 米 | J30: 16 | K30: =H30*J30 -> 32
A31: 45896 | B31: XXL | C31: 留底 | D31: SY25914 | E31: =_xlfn.SINGLE(INDEX(样品编号表!Y:Y,_xlfn.SINGLE(MATCH(_xlfn.SINGLE(D:D),样品编号表!H:H,0)))) -> 三好 | F31: =_xlfn.SINGLE(INDEX(样品编号表!Z:Z,_xlfn.SINGLE(MATCH(_xlfn.SINGLE(D:D),样品编号表!H:H,0)))) -> 1808 | G31: #42 | H31: 1 | I31: 米
A32: 45898 | B32: XXL | C32: 留底 | D32: SY25016 | E32: =_xlfn.SINGLE(INDEX(样品编号表!Y:Y,_xlfn.SINGLE(MATCH(_xlfn.SINGLE(D:D),样品编号表!H:H,0)))) -> 光大纺织 | F32: =_xlfn.SINGLE(INDEX(样品编号表!Z:Z,_xlfn.SINGLE(MATCH(_xlfn.SINGLE(D:D),样品编号表!H:H,0)))) -> C580 | G32: 2#白色 | H32: 1 | I32: 米
A33: 45898 | B33: XXL | C33: 留底 | D33: SY25016 | E33: =_xlfn.SINGLE(INDEX(样品编号表!Y:Y,_xlfn.SINGLE(MATCH(_xlfn.SINGLE(D:D),样品编号表!H:H,0)))) -> 光大纺织 | F33: =_xlfn.SINGLE(INDEX(样品编号表!Z:Z,_xlfn.SINGLE(MATCH(_xlfn.SINGLE(D:D),样品编号表!H:H,0)))) -> C580 | G33: 40#粉色 | H33: 1 | I33: 米
A34: 45930 | B34: XXL | C34: 留底 | D34: SY25531 | E34: =_xlfn.SINGLE(INDEX(样品编号表!Y:Y,_xlfn.SINGLE(MATCH(_xlfn.SINGLE(D:D),样品编号表!H:H,0)))) -> 凯盛亨 | F34: =_xlfn.SINGLE(INDEX(样品编号表!Z:Z,_xlfn.SINGLE(MATCH(_xlfn.SINGLE(D:D),样品编号表!H:H,0)))) -> 839# | G34: 黑色 | H34: 1 | I34: 米 | L34: 异常样寄Ricky
A35: 45929 | D35: M6539 | E35: 欧纺时尚 | F35: 数码直喷册子 | G35: 本白 | H35: 1 | I35: 米 | J35: 13 | L35: 寄Ricky
A36: 45929 | D36: M6558 | E36: 欧纺时尚 | F36: 数码直喷册子 | G36: 本白 | H36: 1 | I36: 米 | J36: 13 | L36: 寄Ricky
A37: 45929 | D37: M6560 | E37: 欧纺时尚 | F37: 数码直喷册子 | G37: 本白 | H37: 1 | I37: 米 | J37: 13 | L37: 寄Ricky
A38: 45979 | D38: SP25031 | E38: =_xlfn.SINGLE(INDEX(样品编号表!Y:Y,_xlfn.SINGLE(MATCH(_xlfn.SINGLE(D:D),样品编号表!H:H,0)))) -> 凯盛亨 | F38: =_xlfn.SINGLE(INDEX(样品编号表!Z:Z,_xlfn.SINGLE(MATCH(_xlfn.SINGLE(D:D),样品编号表!H:H,0)))) -> 262# | G38: 27# | H38: 2 | I38: 米 | J38: 16
A39: 45992 | D39: SY25977 | E39: =_xlfn.SINGLE(INDEX(样品编号表!Y:Y,_xlfn.SINGLE(MATCH(_xlfn.SINGLE(D:D),样品编号表!H:H,0)))) -> 健润纺织 | F39: =_xlfn.SINGLE(INDEX(样品编号表!Z:Z,_xlfn.SINGLE(MATCH(_xlfn.SINGLE(D:D),样品编号表!H:H,0)))) -> 逸柔3*2罗纹-RS | G39: 黑色 | H39: 1 | I39: 米 | L39: 寄Ricky
A40: 45959 | D40: SY251242 | E40: =_xlfn.SINGLE(INDEX(样品编号表!Y:Y,_xlfn.SINGLE(MATCH(_xlfn.SINGLE(D:D),样品编号表!H:H,0)))) -> 凯盛亨 | F40: =_xlfn.SINGLE(INDEX(样品编号表!Z:Z,_xlfn.SINGLE(MATCH(_xlfn.SINGLE(D:D),样品编号表!H:H,0)))) -> 1016# | G40: 黑色 | H40: 14 | I40: 米 | J40: 16 | L40: 多剪14米版布
A41: 45960 | D41: SY25016 | E41: =_xlfn.SINGLE(INDEX(样品编号表!Y:Y,_xlfn.SINGLE(MATCH(_xlfn.SINGLE(D:D),样品编号表!H:H,0)))) -> 光大纺织 | F41: =_xlfn.SINGLE(INDEX(样品编号表!Z:Z,_xlfn.SINGLE(MATCH(_xlfn.SINGLE(D:D),样品编号表!H:H,0)))) -> C580 | G41: 半漂 | H41: 3 | I41: 米 | J41: 15
A42: 45980 | E42: 欧纺时尚 | F42: 高牢度健康布 | G42: 30# | H42: 6 | I42: 米 | J42: 30 | L42: 张总
A43: 45980 | E43: 欧纺时尚 | F43: 高牢度健康布 | G43: 32# | H43: 6 | I43: 米 | J43: 30 | L43: 张总
A44: 45957 | E44: 春盛布业 | F44: 066 | G44: 黑色 | H44: 1 | I44: 米 | J44: 20

Sheet 加工厂
A1: 加工厂 | B1: 剪版地址 | C1: 大货地址 | D1: 备注
A2: 杰登 | B2: 东莞市虎门镇虎门寨振华路东下四巷53号6楼 刘小姐 15917680929 | C2: 送鸿洲酒店充电站停车场 13509807206老刘车队收 送 虎门寨振华路东下四巷53号六楼 杰登服饰 18829907161 徐小姐 | D2: 大货布面要贴标签，标签上要有昇奕隆/布种品名信息
A3: BTC | B3: 广州市番禺区洛浦街西三村开发东路3号达新工业园C栋中梯五层504-505 刘小姐15915701761 | C3: 送亮发纺织 广州市海珠区逸景路银岭三期C1206A档 苏珊贝绸刘小姐的货。下午1点到5点
A4: 韦欣-蔡生 | B4: 广州市番禺区积光工业园1栋四楼，蔡生13544390809 | C4: 飞龙物流鸿洲充电桩停车场出口B62一B63号，13538795909蒋生，收货人：韦欣蔡生13544390809
A5: 韦欣-小助 | B5: 海珠区赤沙南便基横街广州晨恩服饰2楼—泰丰制衣厂—小助收13068801544 | C5: 老崔车队13002018168-鸿州充电站21位—收货-赤沙小助
A6: 圣德 | B6: 东莞市虎门镇威远大道230号熙曜楼4楼 《东莞市圣德服饰有限公司》 收件人：汤德新：13829221076 | C6: 《珠江轻纺城：D区广州酒家对面》 老刘车队13509807206： 写上：汤生13829221076
A7: D&J | B7: 韦恩集团 广州市番禺区石碁镇亚运大道895号合劲嘉福创新城6号楼（F栋） （1楼） 13622255651彩琼
A8: 万泰 | B8: 田田 18677947720 广东省佛山市南海区海北大道129号三楼（加油站对面，广磊石材工程部隔壁楼三楼 | C8: 送佛山阿强货运 中大国际轻纺城B区08号车位 15876555680 万泰服饰 傅生 18588578221 | D8: 对账单需要随货一起出
A9: 三佰 | B9: 广东省深圳市宝安区沙井街道后亭第二工业区福新创客大厦C座2楼 深圳三佰服装有限公司 Yannis 18218567292
A10: 三佰-夜色 | B10: 东莞市虎门镇永勤工业区D栋3楼夜色服饰 芝芝13268697803
A11: 三佰-正恒 | B11: 付小姐 18002881313 正恒 广东省东莞市虎门镇博头宝丽印刷厂A栋4楼正恒服饰
A12: 三佰-妮裳 | B12: 虎门镇镇口第二工业区顺成产业园A栋3楼财务室 飞飞，15817384767
A13: 越安 | B13: 广州市花都区狮岭镇狮岭皮革城四期南广场7到9号海粤物流，4555收，14758359976(PHUONG THAO 0835.942.886
A14: 家棋服饰 | B14: 东莞市虎门镇家棋服饰有限公司，虎门镇太新路六街2号一楼 黄莹13532450641
A15: 扑喜 | B15: 上海市宝山区城银路555弄绿地领海7号楼202 扑喜商贸 单正亚 13917266991
A16: 广州橙爱 | B16: 广东省广州市番禺区南村镇南光路永顺大厦一楼，小宇13112523551 | D16: 版布地址是橙爱的印花厂
A17: 汕头佳音 | B17: 汕头市龙湖区经发大厦B座8楼 汕头佳音服装有限公司，吕晓璇 15817902354
A18: 依斯高 | B18: 广州市越秀区沿江中路299号 银海大厦19楼 依斯高贸易公司 SANDY 黄小姐 020-66842111（内线64）
A19: 锦兰 | B19: 广州花都区铁山河西路301厂房19899193025丘丽珠
A20: 慧帆服饰 | B20: 佛山市南海区大沥镇盐步河西陆东工业区德启创意园C座4楼 慧帆服饰 (采购部) 陈小菲17322661281

Sheet Sheet1
A1: 是 | B1: N/A
A2: 否 | B2: GRS证书
B3: BCI证书
